Workbook

Sheet ⚙ Parámetros
A1: mesoestetic® · Project Scoring System — Parámetros del Modelo
A2: Celdas en azul = inputs editables · Celdas en negro = fórmulas calculadas · Cambia cualquier valor y todo se recalcula
A3: 1. Pesos de Dimensiones (deben sumar 100%)
A4: Dimensión | D4: Peso (%) | E4: Descripción
A5: D1 — Compliance / Legal / Riesgo | B5: 30 | C5: Peso en % (editable)
A6: D2 — Estratégico / Prioridad Consejo | B6: 20 | C6: Peso en % (editable)
A7: D3 — ROI / Valor de negocio | B7: 20 | C7: Peso en % (editable)
A8: D4 — Técnica / Madurez TRL | B8: 12 | C8: Peso en % (editable)
A9: D5 — Implantación / Facilidad | B9: 10 | C9: Peso en % (editable)
A10: D6 — Personas / ESG | B10: 8 | C10: Peso en % (editable)
A11: TOTAL (debe ser 100%) | B11: =SUM(B5:B10) -> 100 | C11: =IF(B11=100,"✓ Correcto","✗ Revisar") -> ✓ Correcto
A13: 2. Parámetros Sigmoid Boost Boost(S) = max( α₀/(1+2^(−β₀·(S−C₀))), α/(1+2^(−β·(S−C))), 1 )
A14: Dim | B14: C₀ (base) | C14: β₀ (base) | D14: α₀ (base) | E14: C (boost) | F14: β (boost) | G14: α (boost) | H14: Peso critr.
A15: D1 — Compliance / Legal / Riesgo | B15: 3 | C15: 1 | D15: 2 | E15: 7 | F15: 2 | G15: 9
A16: D2 — Estratégico / Prioridad Consejo | B16: 4 | C16: 1 | D16: 3 | E16: 8 | F16: 2 | G16: 9
A17: D3 — ROI / Valor de negocio | B17: 4 | C17: 1 | D17: 3 | E17: 8 | F17: 2 | G17: 8
A18: D4 — Técnica / Madurez TRL | B18: 4 | C18: 1 | D18: 3 | E18: 8 | F18: 1.5 | G18: 7
A19: D5 — Implantación / Facilidad | B19: 4 | C19: 1 | D19: 3 | E19: 8 | F19: 1.5 | G19: 7
A20: D6 — Personas / ESG | B20: 4 | C20: 1 | D20: 2 | E20: 8 | F20: 1 | G20: 6
A22: 3. Umbrales de Clasificación de Score
A23: Prioritario Estratégico ≥ | B23: 8.5
A24: Alta Prioridad ≥ | B24: 7
A25: Prioridad Media ≥ | B25: 5.5
A26: Baja Prioridad ≥ | B26: 4
A28: 4. Umbrales de Pools por Horas
A29: Corto — máximo horas | B29: 30
A30: Medio — máximo horas | B30: 100
A32: 5. Aging Factor Score_final = min(Score_base × Aging, 10) Aging = min(1 + (días/365) × tasa, máximo)
A33: Tasa de aging anual | B33: 0.15
A34: Aging máximo | B34: 1.25

Sheet 📋 Evaluación
A1: mesoestetic® · Evaluación de Proyecto Individual
A2: Introduce las notas (1–10) en azul · Todo se calcula automáticamente desde ⚙ Parámetros
A3: Datos del Proyecto
B4: Nombre del proyecto
B5: Área promotora
B6: Tipo de proyecto | C6: p.ej. Integración, Digitalización, BI...
B7: Sponsor ejecutivo | C7: Nombre del sponsor
B8: Fecha de solicitud | C8: dd/mm/aaaa
B9: Días en cartera | C9: =IF(C7="","—",IF(ISNUMBER(C7),TEXT(TODAY()-C7,"0")&" días","—")) -> —
B10: Aging factor | C10: =IF(C7="","×1.000",IF(ISNUMBER(C7),TEXT(MIN(1+MAX(0,TODAY()-C7)/365*'⚙ Parámetros'!B33,'⚙ Parámetros'!B34),"0.000")&"×","×1.000")) -> ×1.000
A12: Evaluación por Dimensiones (notas 1–10 en azul → score se calcula automáticamente)
B13: Criterio de evaluación | C13: Nota (1–10) | D13: Boost (auto) | E13: pw×B×N (auto) | F13: pw×B (auto) | G13: % peso dim | H13: Score dimensión | I13: Clasif.
A14: D1 | B14: Riesgo legal / regulatorio | C14: 5 | D14: =MAX('⚙ Parámetros'!D15/(1+2^(-'⚙ Parámetros'!C15*(C14-'⚙ Parámetros'!B15))),'⚙ Parámetros'!G15/(1+2^(-'⚙ Parámetros'!F15*(C14-'⚙ Parámetros'!E15))),1) -> 1.6 | E14: =30/100*D14*C14 -> 2.4 | F14: =30/100*D14 -> 0.48 | G14: 30%
B15: Seguridad y PRL | C15: 5 | D15: =MAX('⚙ Parámetros'!D15/(1+2^(-'⚙ Parámetros'!C15*(C15-'⚙ Parámetros'!B15))),'⚙ Parámetros'!G15/(1+2^(-'⚙ Parámetros'!F15*(C15-'⚙ Parámetros'!E15))),1) -> 1.6 | E15: =30/100*D15*C15 -> 2.4 | F15: =30/100*D15 -> 0.48 | G15: 30% | H15: =IFERROR(SUM(E14:E17)/SUM(F14:F17),0) -> 5
B16: Riesgo reputacional | C16: 5 | D16: =MAX('⚙ Parámetros'!D15/(1+2^(-'⚙ Parámetros'!C15*(C16-'⚙ Parámetros'!B15))),'⚙ Parámetros'!G15/(1+2^(-'⚙ Parámetros'!F15*(C16-'⚙ Parámetros'!E15))),1) -> 1.6 | E16: =20/100*D16*C16 -> 1.6 | F16: =20/100*D16 -> 0.32 | G16: 20%
B17: Obligación normativa | C17: 5 | D17: =MAX('⚙ Parámetros'!D15/(1+2^(-'⚙ Parámetros'!C15*(C17-'⚙ Parámetros'!B15))),'⚙ Parámetros'!G15/(1+2^(-'⚙ Parámetros'!F15*(C17-'⚙ Parámetros'!E15))),1) -> 1.6 | E17: =20/100*D17*C17 -> 1.6 | F17: =20/100*D17 -> 0.32 | G17: 20%
A18: D2 | B18: Mandato del Consejo | C18: 5 | D18: =MAX('⚙ Parámetros'!D16/(1+2^(-'⚙ Parámetros'!C16*(C18-'⚙ Parámetros'!B16))),'⚙ Parámetros'!G16/(1+2^(-'⚙ Parámetros'!F16*(C18-'⚙ Parámetros'!E16))),1) -> 2 | E18: =35/100*D18*C18 -> 3.5 | F18: =35/100*D18 -> 0.7 | G18: 35%
B19: Expansión internacional | C19: 5 | D19: =MAX('⚙ Parámetros'!D16/(1+2^(-'⚙ Parámetros'!C16*(C19-'⚙ Parámetros'!B16))),'⚙ Parámetros'!G16/(1+2^(-'⚙ Parámetros'!F16*(C19-'⚙ Parámetros'!E16))),1) -> 2 | E19: =25/100*D19*C19 -> 2.5 | F19: =25/100*D19 -> 0.5 | G19: 25% | H19: =IFERROR(SUM(E18:E21)/SUM(F18:F21),0) -> 5
B20: Innovación / I+D | C20: 5 | D20: =MAX('⚙ Parámetros'!D16/(1+2^(-'⚙ Parámetros'!C16*(C20-'⚙ Parámetros'!B16))),'⚙ Parámetros'!G16/(1+2^(-'⚙ Parámetros'!F16*(C20-'⚙ Parámetros'!E16))),1) -> 2 | E20: =20/100*D20*C20 -> 2 | F20: =20/100*D20 -> 0.4 | G20: 20%
B21: Urgencia estratégica | C21: 5 | D21: =MAX('⚙ Parámetros'!D16/(1+2^(-'⚙ Parámetros'!C16*(C21-'⚙ Parámetros'!B16))),'⚙ Parámetros'!G16/(1+2^(-'⚙ Parámetros'!F16*(C21-'⚙ Parámetros'!E16))),1) -> 2 | E21: =20/100*D21*C21 -> 2 | F21: =20/100*D21 -> 0.4 | G21: 20%
A22: D3 | B22: Impacto en ingresos | C22: 5 | D22: =MAX('⚙ Parámetros'!D17/(1+2^(-'⚙ Parámetros'!C17*(C22-'⚙ Parámetros'!B17))),'⚙ Parámetros'!G17/(1+2^(-'⚙ Parámetros'!F17*(C22-'⚙ Parámetros'!E17))),1) -> 2 | E22: =30/100*D22*C22 -> 3 | F22: =30/100*D22 -> 0.6 | G22: 30%
B23: Ahorro de costes | C23: 5 | D23: =MAX('⚙ Parámetros'!D17/(1+2^(-'⚙ Parámetros'!C17*(C23-'⚙ Parámetros'!B17))),'⚙ Parámetros'!G17/(1+2^(-'⚙ Parámetros'!F17*(C23-'⚙ Parámetros'!E17))),1) -> 2 | E23: =25/100*D23*C23 -> 2.5 | F23: =25/100*D23 -> 0.5 | G23: 25% | H23: =IFERROR(SUM(E22:E25)/SUM(F22:F25),0) -> 5
B24: ROI y payback | C24: 5 | D24: =MAX('⚙ Parámetros'!D17/(1+2^(-'⚙ Parámetros'!C17*(C24-'⚙ Parámetros'!B17))),'⚙ Parámetros'!G17/(1+2^(-'⚙ Parámetros'!F17*(C24-'⚙ Parámetros'!E17))),1) -> 2 | E24: =25/100*D24*C24 -> 2.5 | F24: =25/100*D24 -> 0.5 | G24: 25%
B25: Calidad y servicio | C25: 5 | D25: =MAX('⚙ Parámetros'!D17/(1+2^(-'⚙ Parámetros'!C17*(C25-'⚙ Parámetros'!B17))),'⚙ Parámetros'!G17/(1+2^(-'⚙ Parámetros'!F17*(C25-'⚙ Parámetros'!E17))),1) -> 2 | E25: =20/100*D25*C25 -> 2 | F25: =20/100*D25 -> 0.4 | G25: 20%
A26: D4 | B26: Madurez tecnológica (TRL) | C26: 5 | D26: =MAX('⚙ Parámetros'!D18/(1+2^(-'⚙ Parámetros'!C18*(C26-'⚙ Parámetros'!B18))),'⚙ Parámetros'!G18/(1+2^(-'⚙ Parámetros'!F18*(C26-'⚙ Parámetros'!E18))),1) -> 2 | E26: =30/100*D26*C26 -> 3 | F26: =30/100*D26 -> 0.6 | G26: 30%
B27: Integración con ERP/sistemas | C27: 5 | D27: =MAX('⚙ Parámetros'!D18/(1+2^(-'⚙ Parámetros'!C18*(C27-'⚙ Parámetros'!B18))),'⚙ Parámetros'!G18/(1+2^(-'⚙ Parámetros'!F18*(C27-'⚙ Parámetros'!E18))),1) -> 2 | E27: =30/100*D27*C27 -> 3 | F27: =30/100*D27 -> 0.6 | G27: 30% | H27: =IFERROR(SUM(E26:E29)/SUM(F26:F29),0) -> 5
B28: Escalabilidad | C28: 5 | D28: =MAX('⚙ Parámetros'!D18/(1+2^(-'⚙ Parámetros'!C18*(C28-'⚙ Parámetros'!B18))),'⚙ Parámetros'!G18/(1+2^(-'⚙ Parámetros'!F18*(C28-'⚙ Parámetros'!E18))),1) -> 2 | E28: =20/100*D28*C28 -> 2 | F28: =20/100*D28 -> 0.4 | G28: 20%
B29: Ciberseguridad / GDPR | C29: 5 | D29: =MAX('⚙ Parámetros'!D18/(1+2^(-'⚙ Parámetros'!C18*(C29-'⚙ Parámetros'!B18))),'⚙ Parámetros'!G18/(1+2^(-'⚙ Parámetros'!F18*(C29-'⚙ Parámetros'!E18))),1) -> 2 | E29: =20/100*D29*C29 -> 2 | F29: =20/100*D29 -> 0.4 | G29: 20%
A30: D5 | B30: Capacidad interna IT | C30: 5 | D30: =MAX('⚙ Parámetros'!D19/(1+2^(-'⚙ Parámetros'!C19*(C30-'⚙ Parámetros'!B19))),'⚙ Parámetros'!G19/(1+2^(-'⚙ Parámetros'!F19*(C30-'⚙ Parámetros'!E19))),1) -> 2 | E30: =30/100*D30*C30 -> 3 | F30: =30/100*D30 -> 0.6 | G30: 30%
B31: Gestión del cambio | C31: 5 | D31: =MAX('⚙ Parámetros'!D19/(1+2^(-'⚙ Parámetros'!C19*(C31-'⚙ Parámetros'!B19))),'⚙ Parámetros'!G19/(1+2^(-'⚙ Parámetros'!F19*(C31-'⚙ Parámetros'!E19))),1) -> 2 | E31: =35/100*D31*C31 -> 3.5 | F31: =35/100*D31 -> 0.7 | G31: 35% | H31: =IFERROR(SUM(E30:E32)/SUM(F30:F32),0) -> 5
B32: Time-to-value | C32: 5 | D32: =MAX('⚙ Parámetros'!D19/(1+2^(-'⚙ Parámetros'!C19*(C32-'⚙ Parámetros'!B19))),'⚙ Parámetros'!G19/(1+2^(-'⚙ Parámetros'!F19*(C32-'⚙ Parámetros'!E19))),1) -> 2 | E32: =35/100*D32*C32 -> 3.5 | F32: =35/100*D32 -> 0.7 | G32: 35%
A33: D6 | B33: Experiencia del empleado | C33: 5 | D33: =MAX('⚙ Parámetros'!D20/(1+2^(-'⚙ Parámetros'!C20*(C33-'⚙ Parámetros'!B20))),'⚙ Parámetros'!G20/(1+2^(-'⚙ Parámetros'!F20*(C33-'⚙ Parámetros'!E20))),1) -> 1.3333333 | E33: =35/100*D33*C33 -> 2.3333333 | F33: =35/100*D33 -> 0.46666667 | G33: 35%
B34: Sostenibilidad / ESG | C34: 5 | D34: =MAX('⚙ Parámetros'!D20/(1+2^(-'⚙ Parámetros'!C20*(C34-'⚙ Parámetros'!B20))),'⚙ Parámetros'!G20/(1+2^(-'⚙ Parámetros'!F20*(C34-'⚙ Parámetros'!E20))),1) -> 1.3333333 | E34: =35/100*D34*C34 -> 2.3333333 | F34: =35/100*D34 -> 0.46666667 | G34: 35% | H34: =IFERROR(SUM(E33:E35)/SUM(F33:F35),0) -> 5
B35: Formación y cultura | C35: 5 | D35: =MAX('⚙ Parámetros'!D20/(1+2^(-'⚙ Parámetros'!C20*(C35-'⚙ Parámetros'!B20))),'⚙ Parámetros'!G20/(1+2^(-'⚙ Parámetros'!F20*(C35-'⚙ Parámetros'!E20))),1) -> 1.3333333 | E35: =30/100*D35*C35 -> 2 | F35: =30/100*D35 -> 0.4 | G35: 30%
A37: Resultado Final
B38: Score base (sin aging) | C38: =('⚙ Parámetros'!B5/100*H15+'⚙ Parámetros'!B6/100*H19+'⚙ Parámetros'!B7/100*H23+'⚙ Parámetros'!B8/100*H27+'⚙ Parámetros'!B9/100*H31+'⚙ Parámetros'!B10/100*H34) -> 5
B39: Aging factor | C39: =IFERROR(MIN(1+IF(C7<>"",MAX(0,TODAY()-DATEVALUE(C7))/365,0)*'⚙ Parámetros'!B33,'⚙ Parámetros'!B34),1) -> 1
B40: SCORE FINAL | C40: =IFERROR(MIN((('⚙ Parámetros'!B5/100*H15+'⚙ Parámetros'!B6/100*H19+'⚙ Parámetros'!B7/100*H23+'⚙ Parámetros'!B8/100*H27+'⚙ Parámetros'!B9/100*H31+'⚙ Parámetros'!B10/100*H34))*MIN(1+IF(C7<>"",MAX(0,TODAY()-DATEVALUE(C7))/365,0)*'⚙ Parámetros'!B33,'⚙ Parámetros'!B34),10),0) -> 0
B41: Clasificación | C41: =IFERROR(IF(C4<>"",IF(HH15>='⚙ Parámetros'!B23,"⚑ AUTO-PRIORITARIO (D1≥8)",IF(C40>='⚙ Parámetros'!B23,"PRIORITARIO ESTRATÉGICO",IF(C40>='⚙ Parámetros'!B24,"ALTA PRIORIDAD",IF(C40>='⚙ Parámetros'!B25,"PRIORIDAD MEDIA",IF(C40>='⚙ Parámetros'!B26,"BAJA PRIORIDAD","DESCARTAR"))))),"Sin evaluar"),"Sin evaluar") -> Sin evaluar
B42: Horas estimadas | D42: Pool | E42: =IF(C42="","Sin estimar",IF(C42<'⚙ Parámetros'!B29,"🟢 Corto",IF(C42<'⚙ Parámetros'!B30,"🟡 Medio","🔴 Largo"))) -> Sin estimar

Sheet 📊 Cartera
A1: mesoestetic® · Cartera de Proyectos — Scoring Automático
A2: Introduce notas 1–10 en las columnas D–Y (en azul) · El scoring se calcula automáticamente · Parámetros configurables en ⚙ Parámetros
A4: # | B4: Nombre del proyecto | C4: Área | D4: Sponsor | E4: Fecha solicitud | F4: D1 | H4: D2 | J4: D2 | L4: D3 | N4: D3 | P4: D4 | R4: D4 | T4: D5 | V4: D5 | W4: D6 | Y4: D6 | AA4: D1 | AB4: D1 | AC4: D2 | AD4: D3 | AE4: D4 | AF4: D5 | AG4: D6 | AH4: Base | AI4: Aging | AJ4: FINAL | AK4: Clasificación | AL4: D1≥8 | AM4: Horas | AN4: Pool
A5: # | B5: Nombre | C5: Área | D5: Sponsor | E5: Fecha | F5: R.legal | G5: PRL | H5: Reput. | I5: Reg. | J5: Consejo | K5: Int. | L5: I+D | M5: Urg. | N5: Ingr. | O5: Ahorro | P5: ROI | Q5: Cal. | R5: TRL | S5: Integr. | T5: Esc. | U5: GDPR | V5: Cap.IT | W5: Cambio | X5: TtV | Y5: Emp. | Z5: ESG | AA5: Form. | AB5: D1 | AC5: D2 | AD5: D3 | AE5: D4 | AF5: D5 | AG5: D6 | AH5: Base | AI5: Aging | AJ5: Final | AK5: Clasif. | AL5: D1≥8 | AM5: Horas | AN5: Pool
A6: 1 | B6: MPG-FIN-006_01 Nuevas necesidades de BLOQUEO de clientes y de integraición CYC | C6: Finanzas y control | D6: Fernando García | E6: 23/12/2024 | F6: 9 | G6: 5 | H6: 9 | I6: 5 | J6: 7 | K6: 1 | L6: 8 | M6: 3 | N6: 7 | O6: 6 | P6: 7 | Q6: 6 | R6: 9 | S6: 9 | T6: 5 | U6: 5 | V6: 8 | W6: 6 | X6: 3 | Y6: 9 | Z6: 2 | AA6: 5 | AB6: 7 | AC6: =IFERROR((35/100*MAX('⚙ Parámetros'!D16/(1+2^(-'⚙ Parámetros'!C16*(J6-'⚙ Parámetros'!B16))),'⚙ Parámetros'!G16/(1+2^(-'⚙ Parámetros'!F16*(J6-'⚙ Parámetros'!E16))),1)*J6+25/100*MAX('⚙ Parámetros'!D16/(1+2^(-'⚙ Parámetros'!C16*(K6-'⚙ Parámetros'!B16))),'⚙ Parámetros'!G16/(1+2^(-'⚙ Parámetros'!F16*(K6-'⚙ Parámetros'!E16))),1)*K6+20/100*MAX('⚙ Parámetros'!D16/(1+2^(-'⚙ Parámetros'!C16*(L6-'⚙ Parámetros'!B16))),'⚙ Parámetros'!G16/(1+2^(-'⚙ Parámetros'!F16*(L6-'⚙ Parámetros'!E16))),1)*L6+20/100*MAX('⚙ Parámetros'!D16/(1+2^(-'⚙ Parámetros'!C16*(M6-'⚙ Parámetros'!B16))),'⚙ Parámetros'!G16/(1+2^(-'⚙ Parámetros'!F16*(M6-'⚙ Parámetros'!E16))),1)*M6)/(35/100*MAX('⚙ Parámetros'!D16/(1+2^(-'⚙ Parámetros'!C16*(J6-'⚙ Parámetros'!B16))),'⚙ Parámetros'!G16/(1+2^(-'⚙ Parámetros'!F16*(J6-'⚙ Parámetros'!E16))),1)+25/100*MAX('⚙ Parámetros'!D16/(1+2^(-'⚙ Parámetros'!C16*(K6-'⚙ Parámetros'!B16))),'⚙ Parámetros'!G16/(1+2^(-'⚙ Parámetros'!F16*(K6-'⚙ Parámetros'!E16))),1)+20/100*MAX('⚙ Parámetros'!D16/(1+2^(-'⚙ Parámetros'!C16*(L6-'⚙ Parámetros'!B16))),'⚙ Parámetros'!G16/(1+2^(-'⚙ Parámetros'!F16*(L6-'⚙ Parámetros'!E16))),1)+20/100*MAX('⚙ Parámetros'!D16/(1+2^(-'⚙ Parámetros'!C16*(M6-'⚙ Parámetros'!B16))),'⚙ Parámetros'!G16/(1+2^(-'⚙ Parámetros'!F16*(M6-'⚙ Parámetros'!E16))),1)),0) -> 6.3868613 | AD6: =IFERROR((30/100*MAX('⚙ Parámetros'!D17/(1+2^(-'⚙ Parámetros'!C17*(N6-'⚙ Parámetros'!B17))),'⚙ Parámetros'!G17/(1+2^(-'⚙ Parámetros'!F17*(N6-'⚙ Parámetros'!E17))),1)*N6+25/100*MAX('⚙ Parámetros'!D17/(1+2^(-'⚙ Parámetros'!C17*(O6-'⚙ Parámetros'!B17))),'⚙ Parámetros'!G17/(1+2^(-'⚙ Parámetros'!F17*(O6-'⚙ Parámetros'!E17))),1)*O6+25/100*MAX('⚙ Parámetros'!D17/(1+2^(-'⚙ Parámetros'!C17*(P6-'⚙ Parámetros'!B17))),'⚙ Parámetros'!G17/(1+2^(-'⚙ Parámetros'!F17*(P6-'⚙ Parámetros'!E17))),1)*P6+20/100*MAX('⚙ Parámetros'!D17/(1+2^(-'⚙ Parámetros'!C17*(Q6-'⚙ Parámetros'!B17))),'⚙ Parámetros'!G17/(1+2^(-'⚙ Parámetros'!F17*(Q6-'⚙ Parámetros'!E17))),1)*Q6)/(30/100*MAX('⚙ Parámetros'!D17/(1+2^(-'⚙ Parámetros'!C17*(N6-'⚙ Parámetros'!B17))),'⚙ Parámetros'!G17/(1+2^(-'⚙ Parámetros'!F17*(N6-'⚙ Parámetros'!E17))),1)+25/100*MAX('⚙ Parámetros'!D17/(1+2^(-'⚙ Parámetros'!C17*(O6-'⚙ Parámetros'!B17))),'⚙ Parámetros'!G17/(1+2^(-'⚙ Parámetros'!F17*(O6-'⚙ Parámetros'!E17))),1)+25/100*MAX('⚙ Parámetros'!D17/(1+2^(-'⚙ Parámetros'!C17*(P6-'⚙ Parámetros'!B17))),'⚙ Parámetros'!G17/(1+2^(-'⚙ Parámetros'!F17*(P6-'⚙ Parámetros'!E17))),1)+20/100*MAX('⚙ Parámetros'!D17/(1+2^(-'⚙ Parámetros'!C17*(Q6-'⚙ Parámetros'!B17))),'⚙ Parámetros'!G17/(1+2^(-'⚙ Parámetros'!F17*(Q6-'⚙ Parámetros'!E17))),1)),0) -> 6.5759162 | AE6: =IFERROR((30/100*MAX('⚙ Parámetros'!D18/(1+2^(-'⚙ Parámetros'!C18*(R6-'⚙ Parámetros'!B18))),'⚙ Parámetros'!G18/(1+2^(-'⚙ Parámetros'!F18*(R6-'⚙ Parámetros'!E18))),1)*R6+30/100*MAX('⚙ Parámetros'!D18/(1+2^(-'⚙ Parámetros'!C18*(S6-'⚙ Parámetros'!B18))),'⚙ Parámetros'!G18/(1+2^(-'⚙ Parámetros'!F18*(S6-'⚙ Parámetros'!E18))),1)*S6+20/100*MAX('⚙ Parámetros'!D18/(1+2^(-'⚙ Parámetros'!C18*(T6-'⚙ Parámetros'!B18))),'⚙ Parámetros'!G18/(1+2^(-'⚙ Parámetros'!F18*(T6-'⚙ Parámetros'!E18))),1)*T6+20/100*MAX('⚙ Parámetros'!D18/(1+2^(-'⚙ Parámetros'!C18*(U6-'⚙ Parámetros'!B18))),'⚙ Parámetros'!G18/(1+2^(-'⚙ Parámetros'!F18*(U6-'⚙ Parámetros'!E18))),1)*U6)/(30/100*MAX('⚙ Parámetros'!D18/(1+2^(-'⚙ Parámetros'!C18*(R6-'⚙ Parámetros'!B18))),'⚙ Parámetros'!G18/(1+2^(-'⚙ Parámetros'!F18*(R6-'⚙ Parámetros'!E18))),1)+30/100*MAX('⚙ Parámetros'!D18/(1+2^(-'⚙ Parámetros'!C18*(S6-'⚙ Parámetros'!B18))),'⚙ Parámetros'!G18/(1+2^(-'⚙ Parámetros'!F18*(S6-'⚙ Parámetros'!E18))),1)+20/100*MAX('⚙ Parámetros'!D18/(1+2^(-'⚙ Parámetros'!C18*(T6-'⚙ Parámetros'!B18))),'⚙ Parámetros'!G18/(1+2^(-'⚙ Parámetros'!F18*(T6-'⚙ Parámetros'!E18))),1)+20/100*MAX('⚙ Parámetros'!D18/(1+2^(-'⚙ Parámetros'!C18*(U6-'⚙ Parámetros'!B18))),'⚙ Parámetros'!G18/(1+2^(-'⚙ Parámetros'!F18*(U6-'⚙ Parámetros'!E18))),1)),0) -> 8.180106 | AF6: =IFERROR((30/100*MAX('⚙ Parámetros'!D19/(1+2^(-'⚙ Parámetros'!C19*(V6-'⚙ Parámetros'!B19))),'⚙ Parámetros'!G19/(1+2^(-'⚙ Parámetros'!F19*(V6-'⚙ Parámetros'!E19))),1)*V6+35/100*MAX('⚙ Parámetros'!D19/(1+2^(-'⚙ Parámetros'!C19*(W6-'⚙ Parámetros'!B19))),'⚙ Parámetros'!G19/(1+2^(-'⚙ Parámetros'!F19*(W6-'⚙ Parámetros'!E19))),1)*W6+35/100*MAX('⚙ Parámetros'!D19/(1+2^(-'⚙ Parámetros'!C19*(X6-'⚙ Parámetros'!B19))),'⚙ Parámetros'!G19/(1+2^(-'⚙ Parámetros'!F19*(X6-'⚙ Parámetros'!E19))),1)*X6)/(30/100*MAX('⚙ Parámetros'!D19/(1+2^(-'⚙ Parámetros'!C19*(V6-'⚙ Parámetros'!B19))),'⚙ Parámetros'!G19/(1+2^(-'⚙ Parámetros'!F19*(V6-'⚙ Parámetros'!E19))),1)+35/100*MAX('⚙ Parámetros'!D19/(1+2^(-'⚙ Parámetros'!C19*(W6-'⚙ Parámetros'!B19))),'⚙ Parámetros'!G19/(1+2^(-'⚙ Parámetros'!F19*(W6-'⚙ Parámetros'!E19))),1)+35/100*MAX('⚙ Parámetros'!D19/(1+2^(-'⚙ Parámetros'!C19*(X6-'⚙ Parámetros'!B19))),'⚙ Parámetros'!G19/(1+2^(-'⚙ Parámetros'!F19*(X6-'⚙ Parámetros'!E19))),1)),0) -> 6.46875 | AG6: =IFERROR((35/100*MAX('⚙ Parámetros'!D20/(1+2^(-'⚙ Parámetros'!C20*(Y6-'⚙ Parámetros'!B20))),'⚙ Parámetros'!G20/(1+2^(-'⚙ Parámetros'!F20*(Y6-'⚙ Parámetros'!E20))),1)*Y6+35/100*MAX('⚙ Parámetros'!D20/(1+2^(-'⚙ Parámetros'!C20*(Z6-'⚙ Parámetros'!B20))),'⚙ Parámetros'!G20/(1+2^(-'⚙ Parámetros'!F20*(Z6-'⚙ Parámetros'!E20))),1)*Z6+30/100*MAX('⚙ Parámetros'!D20/(1+2^(-'⚙ Parámetros'!C20*(AA6-'⚙ Parámetros'!B20))),'⚙ Parámetros'!G20/(1+2^(-'⚙ Parámetros'!F20*(AA6-'⚙ Parámetros'!E20))),1)*AA6)/(35/100*MAX('⚙ Parámetros'!D20/(1+2^(-'⚙ Parámetros'!C20*(Y6-'⚙ Parámetros'!B20))),'⚙ Parámetros'!G20/(1+2^(-'⚙ Parámetros'!F20*(Y6-'⚙ Parámetros'!E20))),1)+35/100*MAX('⚙ Parámetros'!D20/(1+2^(-'⚙ Parámetros'!C20*(Z6-'⚙ Parámetros'!B20))),'⚙ Parámetros'!G20/(1+2^(-'⚙ Parámetros'!F20*(Z6-'⚙ Parámetros'!E20))),1)+30/100*MAX('⚙ Parámetros'!D20/(1+2^(-'⚙ Parámetros'!C20*(AA6-'⚙ Parámetros'!B20))),'⚙ Parámetros'!G20/(1+2^(-'⚙ Parámetros'!F20*(AA6-'⚙ Parámetros'!E20))),1)),0) -> 7.1162791 | AH6: =('⚙ Parámetros'!B5/100*AB6+'⚙ Parámetros'!B6/100*AC6+'⚙ Parámetros'!B7/100*AD6+'⚙ Parámetros'!B8/100*AE6+'⚙ Parámetros'!B9/100*AF6+'⚙ Parámetros'!B10/100*AG6) -> 6.8903456 | AI6: =MIN(1+MAX(0,TODAY()-DATE(2024,12,23))/365*'⚙ Parámetros'!B33,'⚙ Parámetros'!B34) -> 1.220274 | AJ6: =IFERROR(MIN(AH6*AI6,10),0) -> 8.4081093 | AK6: =IF(AB6>='⚙ Parámetros'!B23,"⚑ AUTO-PRIOR.(D1≥8)",IF(AJ6>='⚙ Parámetros'!B23,"PRIORITARIO",IF(AJ6>='⚙ Parámetros'!B24,"ALTA PRIORIDAD",IF(AJ6>='⚙ Parámetros'!B25,"PRIORIDAD MEDIA",IF(AJ6>='⚙ Parámetros'!B26,"BAJA PRIORIDAD","DESCARTAR"))))) -> ALTA PRIORIDAD | AL6: =IF(AB6>=8,"SÍ ⚑","—") -> — | AM6: 50 | AN6: =IF(AM6="","—",IF(AM6<'⚙ Parámetros'!B29,"🟢 Corto",IF(AM6<'⚙ Parámetros'!B30,"🟡 Medio","🔴 Largo"))) -> 🟡 Medio
A7: 2 | B7: MPG-LOG-065 Integración almacén DSV | C7: Supply chain y logística | D7: Marc Bometon | E7: 21/04/2026 | F7: 6 | G7: 5 | H7: 5 | I7: 5 | J7: 10 | K7: 8 | L7: 8 | M7: 9 | N7: 8 | O7: 8 | P7: 1 | Q7: 8 | R7: 6 | S7: 5 | T7: 5 | U7: 5 | V7: 5 | W7: 6 | X7: 3 | Y7: 5 | Z7: 2 | AA7: 8 | AB7: =IFERROR((30/100*MAX('⚙ Parámetros'!D15/(1+2^(-'⚙ Parámetros'!C15*(F7-'⚙ Parámetros'!B15))),'⚙ Parámetros'!G15/(1+2^(-'⚙ Parámetros'!F15*(F7-'⚙ Parámetros'!E15))),1)*F7+30/100*MAX('⚙ Parámetros'!D15/(1+2^(-'⚙ Parámetros'!C15*(G7-'⚙ Parámetros'!B15))),'⚙ Parámetros'!G15/(1+2^(-'⚙ Parámetros'!F15*(G7-'⚙ Parámetros'!E15))),1)*G7+20/100*MAX('⚙ Parámetros'!D15/(1+2^(-'⚙ Parámetros'!C15*(H7-'⚙ Parámetros'!B15))),'⚙ Parámetros'!G15/(1+2^(-'⚙ Parámetros'!F15*(H7-'⚙ Parámetros'!E15))),1)*H7+20/100*MAX('⚙ Parámetros'!D15/(1+2^(-'⚙ Parámetros'!C15*(I7-'⚙ Parámetros'!B15))),'⚙ Parámetros'!G15/(1+2^(-'⚙ Parámetros'!F15*(I7-'⚙ Parámetros'!E15))),1)*I7)/(30/100*MAX('⚙ Parámetros'!D15/(1+2^(-'⚙ Parámetros'!C15*(F7-'⚙ Parámetros'!B15))),'⚙ Parámetros'!G15/(1+2^(-'⚙ Parámetros'!F15*(F7-'⚙ Parámetros'!E15))),1)+30/100*MAX('⚙ Parámetros'!D15/(1+2^(-'⚙ Parámetros'!C15*(G7-'⚙ Parámetros'!B15))),'⚙ Parámetros'!G15/(1+2^(-'⚙ Parámetros'!F15*(G7-'⚙ Parámetros'!E15))),1)+20/100*MAX('⚙ Parámetros'!D15/(1+2^(-'⚙ Parámetros'!C15*(H7-'⚙ Parámetros'!B15))),'⚙ Parámetros'!G15/(1+2^(-'⚙ Parámetros'!F15*(H7-'⚙ Parámetros'!E15))),1)+20/100*MAX('⚙ Parámetros'!D15/(1+2^(-'⚙ Parámetros'!C15*(I7-'⚙ Parámetros'!B15))),'⚙ Parámetros'!G15/(1+2^(-'⚙ Parámetros'!F15*(I7-'⚙ Parámetros'!E15))),1)),0) -> 5.3253012 | AC7: =IFERROR((35/100*MAX('⚙ Parámetros'!D16/(1+2^(-'⚙ Parámetros'!C16*(J7-'⚙ Parámetros'!B16))),'⚙ Parámetros'!G16/(1+2^(-'⚙ Parámetros'!F16*(J7-'⚙ Parámetros'!E16))),1)*J7+25/100*MAX('⚙ Parámetros'!D16/(1+2^(-'⚙ Parámetros'!C16*(K7-'⚙ Parámetros'!B16))),'⚙ Parámetros'!G16/(1+2^(-'⚙ Parámetros'!F16*(K7-'⚙ Parámetros'!E16))),1)*K7+20/100*MAX('⚙ Parámetros'!D16/(1+2^(-'⚙ Parámetros'!C16*(L7-'⚙ Parámetros'!B16))),'⚙ Parámetros'!G16/(1+2^(-'⚙ Parámetros'!F16*(L7-'⚙ Parámetros'!E16))),1)*L7+20/100*MAX('⚙ Parámetros'!D16/(1+2^(-'⚙ Parámetros'!C16*(M7-'⚙ Parámetros'!B16))),'⚙ Parámetros'!G16/(1+2^(-'⚙ Parámetros'!F16*(M7-'⚙ Parámetros'!E16))),1)*M7)/(35/100*MAX('⚙ Parámetros'!D16/(1+2^(-'⚙ Parámetros'!C16*(J7-'⚙ Parámetros'!B16))),'⚙ Parámetros'!G16/(1+2^(-'⚙ Parámetros'!F16*(J7-'⚙ Parámetros'!E16))),1)+25/100*MAX('⚙ Parámetros'!D16/(1+2^(-'⚙ Parámetros'!C16*(K7-'⚙ Parámetros'!B16))),'⚙ Parámetros'!G16/(1+2^(-'⚙ Parámetros'!F16*(K7-'⚙ Parámetros'!E16))),1)+20/100*MAX('⚙ Parámetros'!D16/(1+2^(-'⚙ Parámetros'!C16*(L7-'⚙ Parámetros'!B16))),'⚙ Parámetros'!G16/(1+2^(-'⚙ Parámetros'!F16*(L7-'⚙ Parámetros'!E16))),1)+20/100*MAX('⚙ Parámetros'!D16/(1+2^(-'⚙ Parámetros'!C16*(M7-'⚙ Parámetros'!B16))),'⚙ Parámetros'!G16/(1+2^(-'⚙ Parámetros'!F16*(M7-'⚙ Parámetros'!E16))),1)),0) -> 9.1461507 | AD7: =IFERROR((30/100*MAX('⚙ Parámetros'!D17/(1+2^(-'⚙ Parámetros'!C17*(N7-'⚙ Parámetros'!B17))),'⚙ Parámetros'!G17/(1+2^(-'⚙ Parámetros'!F17*(N7-'⚙ Parámetros'!E17))),1)*N7+25/100*MAX('⚙ Parámetros'!D17/(1+2^(-'⚙ Parámetros'!C17*(O7-'⚙ Parámetros'!B17))),'⚙ Parámetros'!G17/(1+2^(-'⚙ Parámetros'!F17*(O7-'⚙ Parámetros'!E17))),1)*O7+25/100*MAX('⚙ Parámetros'!D17/(1+2^(-'⚙ Parámetros'!C17*(P7-'⚙ Parámetros'!B17))),'⚙ Parámetros'!G17/(1+2^(-'⚙ Parámetros'!F17*(P7-'⚙ Parámetros'!E17))),1)*P7+20/100*MAX('⚙ Parámetros'!D17/(1+2^(-'⚙ Parámetros'!C17*(Q7-'⚙ Parámetros'!B17))),'⚙ Parámetros'!G17/(1+2^(-'⚙ Parámetros'!F17*(Q7-'⚙ Parámetros'!E17))),1)*Q7)/(30/100*MAX('⚙ Parámetros'!D17/(1+2^(-'⚙ Parámetros'!C17*(N7-'⚙ Parámetros'!B17))),'⚙ Parámetros'!G17/(1+2^(-'⚙ Parámetros'!F17*(N7-'⚙ Parámetros'!E17))),1)+25/100*MAX('⚙ Parámetros'!D17/(1+2^(-'⚙ Parámetros'!C17*(O7-'⚙ Parámetros'!B17))),'⚙ Parámetros'!G17/(1+2^(-'⚙ Parámetros'!F17*(O7-'⚙ Parámetros'!E17))),1)+25/100*MAX('⚙ Parámetros'!D17/(1+2^(-'⚙ Parámetros'!C17*(P7-'⚙ Parámetros'!B17))),'⚙ Parámetros'!G17/(1+2^(-'⚙ Parámetros'!F17*(P7-'⚙ Parámetros'!E17))),1)+20/100*MAX('⚙ Parámetros'!D17/(1+2^(-'⚙ Parámetros'!C17*(Q7-'⚙ Parámetros'!B17))),'⚙ Parámetros'!G17/(1+2^(-'⚙ Parámetros'!F17*(Q7-'⚙ Parámetros'!E17))),1)),0) -> 7.4615385 | AE7: =IFERROR((30/100*MAX('⚙ Parámetros'!D18/(1+2^(-'⚙ Parámetros'!C18*(R7-'⚙ Parámetros'!B18))),'⚙ Parámetros'!G18/(1+2^(-'⚙ Parámetros'!F18*(R7-'⚙ Parámetros'!E18))),1)*R7+30/100*MAX('⚙ Parámetros'!D18/(1+2^(-'⚙ Parámetros'!C18*(S7-'⚙ Parámetros'!B18))),'⚙ Parámetros'!G18/(1+2^(-'⚙ Parámetros'!F18*(S7-'⚙ Parámetros'!E18))),1)*S7+20/100*MAX('⚙ Parámetros'!D18/(1+2^(-'⚙ Parámetros'!C18*(T7-'⚙ Parámetros'!B18))),'⚙ Parámetros'!G18/(1+2^(-'⚙ Parámetros'!F18*(T7-'⚙ Parámetros'!E18))),1)*T7+20/100*MAX('⚙ Parámetros'!D18/(1+2^(-'⚙ Parámetros'!C18*(U7-'⚙ Parámetros'!B18))),'⚙ Parámetros'!G18/(1+2^(-'⚙ Parámetros'!F18*(U7-'⚙ Parámetros'!E18))),1)*U7)/(30/100*MAX('⚙ Parámetros'!D18/(1+2^(-'⚙ Parámetros'!C18*(R7-'⚙ Parámetros'!B18))),'⚙ Parámetros'!G18/(1+2^(-'⚙ Parámetros'!F18*(R7-'⚙ Parámetros'!E18))),1)+30/100*MAX('⚙ Parámetros'!D18/(1+2^(-'⚙ Parámetros'!C18*(S7-'⚙ Parámetros'!B18))),'⚙ Parámetros'!G18/(1+2^(-'⚙ Parámetros'!F18*(S7-'⚙ Parámetros'!E18))),1)+20/100*MAX('⚙ Parámetros'!D18/(1+2^(-'⚙ Parámetros'!C18*(T7-'⚙ Parámetros'!B18))),'⚙ Parámetros'!G18/(1+2^(-'⚙ Parámetros'!F18*(T7-'⚙ Parámetros'!E18))),1)+20/100*MAX('⚙ Parámetros'!D18/(1+2^(-'⚙ Parámetros'!C18*(U7-'⚙ Parámetros'!B18))),'⚙ Parámetros'!G18/(1+2^(-'⚙ Parámetros'!F18*(U7-'⚙ Parámetros'!E18))),1)),0) -> 5.3396226 | AF7: =IFERROR((30/100*MAX('⚙ Parámetros'!D19/(1+2^(-'⚙ Parámetros'!C19*(V7-'⚙ Parámetros'!B19))),'⚙ Parámetros'!G19/(1+2^(-'⚙ Parámetros'!F19*(V7-'⚙ Parámetros'!E19))),1)*V7+35/100*MAX('⚙ Parámetros'!D19/(1+2^(-'⚙ Parámetros'!C19*(W7-'⚙ Parámetros'!B19))),'⚙ Parámetros'!G19/(1+2^(-'⚙ Parámetros'!F19*(W7-'⚙ Parámetros'!E19))),1)*W7+35/100*MAX('⚙ Parámetros'!D19/(1+2^(-'⚙ Parámetros'!C19*(X7-'⚙ Parámetros'!B19))),'⚙ Parámetros'!G19/(1+2^(-'⚙ Parámetros'!F19*(X7-'⚙ Parámetros'!E19))),1)*X7)/(30/100*MAX('⚙ Parámetros'!D19/(1+2^(-'⚙ Parámetros'!C19*(V7-'⚙ Parámetros'!B19))),'⚙ Parámetros'!G19/(1+2^(-'⚙ Parámetros'!F19*(V7-'⚙ Parámetros'!E19))),1)+35/100*MAX('⚙ Parámetros'!D19/(1+2^(-'⚙ Parámetros'!C19*(W7-'⚙ Parámetros'!B19))),'⚙ Parámetros'!G19/(1+2^(-'⚙ Parámetros'!F19*(W7-'⚙ Parámetros'!E19))),1)+35/100*MAX('⚙ Parámetros'!D19/(1+2^(-'⚙ Parámetros'!C19*(X7-'⚙ Parámetros'!B19))),'⚙ Parámetros'!G19/(1+2^(-'⚙ Parámetros'!F19*(X7-'⚙ Parámetros'!E19))),1)),0) -> 5.0782123 | AG7: =IFERROR((35/100*MAX('⚙ Parámetros'!D20/(1+2^(-'⚙ Parámetros'!C20*(Y7-'⚙ Parámetros'!B20))),'⚙ Parámetros'!G20/(1+2^(-'⚙ Parámetros'!F20*(Y7-'⚙ Parámetros'!E20))),1)*Y7+35/100*MAX('⚙ Parámetros'!D20/(1+2^(-'⚙ Parámetros'!C20*(Z7-'⚙ Parámetros'!B20))),'⚙ Parámetros'!G20/(1+2^(-'⚙ Parámetros'!F20*(Z7-'⚙ Parámetros'!E20))),1)*Z7+30/100*MAX('⚙ Parámetros'!D20/(1+2^(-'⚙ Parámetros'!C20*(AA7-'⚙ Parámetros'!B20))),'⚙ Parámetros'!G20/(1+2^(-'⚙ Parámetros'!F20*(AA7-'⚙ Parámetros'!E20))),1)*AA7)/(35/100*MAX('⚙ Parámetros'!D20/(1+2^(-'⚙ Parámetros'!C20*(Y7-'⚙ Parámetros'!B20))),'⚙ Parámetros'!G20/(1+2^(-'⚙ Parámetros'!F20*(Y7-'⚙ Parámetros'!E20))),1)+35/100*MAX('⚙ Parámetros'!D20/(1+2^(-'⚙ Parámetros'!C20*(Z7-'⚙ Parámetros'!B20))),'⚙ Parámetros'!G20/(1+2^(-'⚙ Parámetros'!F20*(Z7-'⚙ Parámetros'!E20))),1)+30/100*MAX('⚙ Parámetros'!D20/(1+2^(-'⚙ Parámetros'!C20*(AA7-'⚙ Parámetros'!B20))),'⚙ Parámetros'!G20/(1+2^(-'⚙ Parámetros'!F20*(AA7-'⚙ Parámetros'!E20))),1)),0) -> 5.961165 | AH7: =('⚙ Parámetros'!B5/100*AB7+'⚙ Parámetros'!B6/100*AC7+'⚙ Parámetros'!B7/100*AD7+'⚙ Parámetros'!B8/100*AE7+'⚙ Parámetros'!B9/100*AF7+'⚙ Parámetros'!B10/100*AG7) -> 6.5445973 | AI7: =MIN(1+MAX(0,TODAY()-DATE(2026,4,21))/365*'⚙ Parámetros'!B33,'⚙ Parámetros'!B34) -> 1.0213699 | AJ7: =IFERROR(MIN(AH7*AI7,10),0) -> 6.6844545 | AK7: =IF(AB7>='⚙ Parámetros'!B23,"⚑ AUTO-PRIOR.(D1≥8)",IF(AJ7>='⚙ Parámetros'!B23,"PRIORITARIO",IF(AJ7>='⚙ Parámetros'!B24,"ALTA PRIORIDAD",IF(AJ7>='⚙ Parámetros'!B25,"PRIORIDAD MEDIA",IF(AJ7>='⚙ Parámetros'!B26,"BAJA PRIORIDAD","DESCARTAR"))))) -> PRIORIDAD MEDIA | AL7: =IF(AB7>=8,"SÍ ⚑","—") -> — | AM7: 250 | AN7: =IF(AM7="","—",IF(AM7<'⚙ Parámetros'!B29,"🟢 Corto",IF(AM7<'⚙ Parámetros'!B30,"🟡 Medio","🔴 Largo"))) -> 🔴 Largo
A8: 4 | B8: MPG-CAL-018 COA - Firma electronica | C8: Regulatorio y calidad | D8: Marc Bometon | E8: 14/01/2026 | F8: 9 | G8: 5 | H8: 7 | I8: 8 | J8: 1 | K8: 1 | L8: 8 | M8: 3 | N8: 7 | O8: 1 | P8: 1 | Q8: 8 | R8: 5 | S8: 5 | T8: 5 | U8: 8 | V8: 8 | W8: 6 | X8: 9 | Y8: 4 | Z8: 2 | AA8: 5 | AB8: =IFERROR((30/100*MAX('⚙ Parámetros'!D15/(1+2^(-'⚙ Parámetros'!C15*(F8-'⚙ Parámetros'!B15))),'⚙ Parámetros'!G15/(1+2^(-'⚙ Parámetros'!F15*(F8-'⚙ Parámetros'!E15))),1)*F8+30/100*MAX('⚙ Parámetros'!D15/(1+2^(-'⚙ Parámetros'!C15*(G8-'⚙ Parámetros'!B15))),'⚙ Parámetros'!G15/(1+2^(-'⚙ Parámetros'!F15*(G8-'⚙ Parámetros'!E15))),1)*G8+20/100*MAX('⚙ Parámetros'!D15/(1+2^(-'⚙ Parámetros'!C15*(H8-'⚙ Parámetros'!B15))),'⚙ Parámetros'!G15/(1+2^(-'⚙ Parámetros'!F15*(H8-'⚙ Parámetros'!E15))),1)*H8+20/100*MAX('⚙ Parámetros'!D15/(1+2^(-'⚙ Parámetros'!C15*(I8-'⚙ Parámetros'!B15))),'⚙ Parámetros'!G15/(1+2^(-'⚙ Parámetros'!F15*(I8-'⚙ Parámetros'!E15))),1)*I8)/(30/100*MAX('⚙ Parámetros'!D15/(1+2^(-'⚙ Parámetros'!C15*(F8-'⚙ Parámetros'!B15))),'⚙ Parámetros'!G15/(1+2^(-'⚙ Parámetros'!F15*(F8-'⚙ Parámetros'!E15))),1)+30/100*MAX('⚙ Parámetros'!D15/(1+2^(-'⚙ Parámetros'!C15*(G8-'⚙ Parámetros'!B15))),'⚙ Parámetros'!G15/(1+2^(-'⚙ Parámetros'!F15*(G8-'⚙ Parámetros'!E15))),1)+20/100*MAX('⚙ Parámetros'!D15/(1+2^(-'⚙ Parámetros'!C15*(H8-'⚙ Parámetros'!B15))),'⚙ Parámetros'!G15/(1+2^(-'⚙ Parámetros'!F15*(H8-'⚙ Parámetros'!E15))),1)+20/100*MAX('⚙ Parámetros'!D15/(1+2^(-'⚙ Parámetros'!C15*(I8-'⚙ Parámetros'!B15))),'⚙ Parámetros'!G15/(1+2^(-'⚙ Parámetros'!F15*(I8-'⚙ Parámetros'!E15))),1)),0) -> 8.0375247 | AC8: =IFERROR((35/100*MAX('⚙ Parámetros'!D16/(1+2^(-'⚙ Parámetros'!C16*(J8-'⚙ Parámetros'!B16))),'⚙ Parámetros'!G16/(1+2^(-'⚙ Parámetros'!F16*(J8-'⚙ Parámetros'!E16))),1)*J8+25/100*MAX('⚙ Parámetros'!D16/(1+2^(-'⚙ Parámetros'!C16*(K8-'⚙ Parámetros'!B16))),'⚙ Parámetros'!G16/(1+2^(-'⚙ Parámetros'!F16*(K8-'⚙ Parámetros'!E16))),1)*K8+20/100*MAX('⚙ Parámetros'!D16/(1+2^(-'⚙ Parámetros'!C16*(L8-'⚙ Parámetros'!B16))),'⚙ Parámetros'!G16/(1+2^(-'⚙ Parámetros'!F16*(L8-'⚙ Parámetros'!E16))),1)*L8+20/100*MAX('⚙ Parámetros'!D16/(1+2^(-'⚙ Parámetros'!C16*(M8-'⚙ Parámetros'!B16))),'⚙ Parámetros'!G16/(1+2^(-'⚙ Parámetros'!F16*(M8-'⚙ Parámetros'!E16))),1)*M8)/(35/100*MAX('⚙ Parámetros'!D16/(1+2^(-'⚙ Parámetros'!C16*(J8-'⚙ Parámetros'!B16))),'⚙ Parámetros'!G16/(1+2^(-'⚙ Parámetros'!F16*(J8-'⚙ Parámetros'!E16))),1)+25/100*MAX('⚙ Parámetros'!D16/(1+2^(-'⚙ Parámetros'!C16*(K8-'⚙ Parámetros'!B16))),'⚙ Parámetros'!G16/(1+2^(-'⚙ Parámetros'!F16*(K8-'⚙ Parámetros'!E16))),1)+20/100*MAX('⚙ Parámetros'!D16/(1+2^(-'⚙ Parámetros'!C16*(L8-'⚙ Parámetros'!B16))),'⚙ Parámetros'!G16/(1+2^(-'⚙ Parámetros'!F16*(L8-'⚙ Parámetros'!E16))),1)+20/100*MAX('⚙ Parámetros'!D16/(1+2^(-'⚙ Parámetros'!C16*(M8-'⚙ Parámetros'!B16))),'⚙ Parámetros'!G16/(1+2^(-'⚙ Parámetros'!F16*(M8-'⚙ Parámetros'!E16))),1)),0) -> 4.9411765 | AD8: =IFERROR((30/100*MAX('⚙ Parámetros'!D17/(1+2^(-'⚙ Parámetros'!C17*(N8-'⚙ Parámetros'!B17))),'⚙ Parámetros'!G17/(1+2^(-'⚙ Parámetros'!F17*(N8-'⚙ Parámetros'!E17))),1)*N8+25/100*MAX('⚙ Parámetros'!D17/(1+2^(-'⚙ Parámetros'!C17*(O8-'⚙ Parámetros'!B17))),'⚙ Parámetros'!G17/(1+2^(-'⚙ Parámetros'!F17*(O8-'⚙ Parámetros'!E17))),1)*O8+25/100*MAX('⚙ Parámetros'!D17/(1+2^(-'⚙ Parámetros'!C17*(P8-'⚙ Parámetros'!B17))),'⚙ Parámetros'!G17/(1+2^(-'⚙ Parámetros'!F17*(P8-'⚙ Parámetros'!E17))),1)*P8+20/100*MAX('⚙ Parámetros'!D17/(1+2^(-'⚙ Parámetros'!C17*(Q8-'⚙ Parámetros'!B17))),'⚙ Parámetros'!G17/(1+2^(-'⚙ Parámetros'!F17*(Q8-'⚙ Parámetros'!E17))),1)*Q8)/(30/100*MAX('⚙ Parámetros'!D17/(1+2^(-'⚙ Parámetros'!C17*(N8-'⚙ Parámetros'!B17))),'⚙ Parámetros'!G17/(1+2^(-'⚙ Parámetros'!F17*(N8-'⚙ Parámetros'!E17))),1)+25/100*MAX('⚙ Parámetros'!D17/(1+2^(-'⚙ Parámetros'!C17*(O8-'⚙ Parámetros'!B17))),'⚙ Parámetros'!G17/(1+2^(-'⚙ Parámetros'!F17*(O8-'⚙ Parámetros'!E17))),1)+25/100*MAX('⚙ Parámetros'!D17/(1+2^(-'⚙ Parámetros'!C17*(P8-'⚙ Parámetros'!B17))),'⚙ Parámetros'!G17/(1+2^(-'⚙ Parámetros'!F17*(P8-'⚙ Parámetros'!E17))),1)+20/100*MAX('⚙ Parámetros'!D17/(1+2^(-'⚙ Parámetros'!C17*(Q8-'⚙ Parámetros'!B17))),'⚙ Parámetros'!G17/(1+2^(-'⚙ Parámetros'!F17*(Q8-'⚙ Parámetros'!E17))),1)),0) -> 5.952381 | AE8: =IFERROR((30/100*MAX('⚙ Parámetros'!D18/(1+2^(-'⚙ Parámetros'!C18*(R8-'⚙ Parámetros'!B18))),'⚙ Parámetros'!G18/(1+2^(-'⚙ Parámetros'!F18*(R8-'⚙ Parámetros'!E18))),1)*R8+30/100*MAX('⚙ Parámetros'!D18/(1+2^(-'⚙ Parámetros'!C18*(S8-'⚙ Parámetros'!B18))),'⚙ Parámetros'!G18/(1+2^(-'⚙ Parámetros'!F18*(S8-'⚙ Parámetros'!E18))),1)*S8+20/100*MAX('⚙ Parámetros'!D18/(1+2^(-'⚙ Parámetros'!C18*(T8-'⚙ Parámetros'!B18))),'⚙ Parámetros'!G18/(1+2^(-'⚙ Parámetros'!F18*(T8-'⚙ Parámetros'!E18))),1)*T8+20/100*MAX('⚙ Parámetros'!D18/(1+2^(-'⚙ Parámetros'!C18*(U8-'⚙ Parámetros'!B18))),'⚙ Parámetros'!G18/(1+2^(-'⚙ Parámetros'!F18*(U8-'⚙ Parámetros'!E18))),1)*U8)/(30/100*MAX('⚙ Parámetros'!D18/(1+2^(-'⚙ Parámetros'!C18*(R8-'⚙ Parámetros'!B18))),'⚙ Parámetros'!G18/(1+2^(-'⚙ Parámetros'!F18*(R8-'⚙ Parámetros'!E18))),1)+30/100*MAX('⚙ Parámetros'!D18/(1+2^(-'⚙ Parámetros'!C18*(S8-'⚙ Parámetros'!B18))),'⚙ Parámetros'!G18/(1+2^(-'⚙ Parámetros'!F18*(S8-'⚙ Parámetros'!E18))),1)+20/100*MAX('⚙ Parámetros'!D18/(1+2^(-'⚙ Parámetros'!C18*(T8-'⚙ Parámetros'!B18))),'⚙ Parámetros'!G18/(1+2^(-'⚙ Parámetros'!F18*(T8-'⚙ Parámetros'!E18))),1)+20/100*MAX('⚙ Parámetros'!D18/(1+2^(-'⚙ Parámetros'!C18*(U8-'⚙ Parámetros'!B18))),'⚙ Parámetros'!G18/(1+2^(-'⚙ Parámetros'!F18*(U8-'⚙ Parámetros'!E18))),1)),0) -> 5.9130435 | AF8: =IFERROR((30/100*MAX('⚙ Parámetros'!D19/(1+2^(-'⚙ Parámetros'!C19*(V8-'⚙ Parámetros'!B19))),'⚙ Parámetros'!G19/(1+2^(-'⚙ Parámetros'!F19*(V8-'⚙ Parámetros'!E19))),1)*V8+35/100*MAX('⚙ Parámetros'!D19/(1+2^(-'⚙ Parámetros'!C19*(W8-'⚙ Parámetros'!B19))),'⚙ Parámetros'!G19/(1+2^(-'⚙ Parámetros'!F19*(W8-'⚙ Parámetros'!E19))),1)*W8+35/100*MAX('⚙ Parámetros'!D19/(1+2^(-'⚙ Parámetros'!C19*(X8-'⚙ Parámetros'!B19))),'⚙ Parámetros'!G19/(1+2^(-'⚙ Parámetros'!F19*(X8-'⚙ Parámetros'!E19))),1)*X8)/(30/100*MAX('⚙ Parámetros'!D19/(1+2^(-'⚙ Parámetros'!C19*(V8-'⚙ Parámetros'!B19))),'⚙ Parámetros'!G19/(1+2^(-'⚙ Parámetros'!F19*(V8-'⚙ Parámetros'!E19))),1)+35/100*MAX('⚙ Parámetros'!D19/(1+2^(-'⚙ Parámetros'!C19*(W8-'⚙ Parámetros'!B19))),'⚙ Parámetros'!G19/(1+2^(-'⚙ Parámetros'!F19*(W8-'⚙ Parámetros'!E19))),1)+35/100*MAX('⚙ Parámetros'!D19/(1+2^(-'⚙ Parámetros'!C19*(X8-'⚙ Parámetros'!B19))),'⚙ Parámetros'!G19/(1+2^(-'⚙ Parámetros'!F19*(X8-'⚙ Parámetros'!E19))),1)),0) -> 8.0351483 | AG8: =IFERROR((35/100*MAX('⚙ Parámetros'!D20/(1+2^(-'⚙ Parámetros'!C20*(Y8-'⚙ Parámetros'!B20))),'⚙ Parámetros'!G20/(1+2^(-'⚙ Parámetros'!F20*(Y8-'⚙ Parámetros'!E20))),1)*Y8+35/100*MAX('⚙ Parámetros'!D20/(1+2^(-'⚙ Parámetros'!C20*(Z8-'⚙ Parámetros'!B20))),'⚙ Parámetros'!G20/(1+2^(-'⚙ Parámetros'!F20*(Z8-'⚙ Parámetros'!E20))),1)*Z8+30/100*MAX('⚙ Parámetros'!D20/(1+2^(-'⚙ Parámetros'!C20*(AA8-'⚙ Parámetros'!B20))),'⚙ Parámetros'!G20/(1+2^(-'⚙ Parámetros'!F20*(AA8-'⚙ Parámetros'!E20))),1)*AA8)/(35/100*MAX('⚙ Parámetros'!D20/(1+2^(-'⚙ Parámetros'!C20*(Y8-'⚙ Parámetros'!B20))),'⚙ Parámetros'!G20/(1+2^(-'⚙ Parámetros'!F20*(Y8-'⚙ Parámetros'!E20))),1)+35/100*MAX('⚙ Parámetros'!D20/(1+2^(-'⚙ Parámetros'!C20*(Z8-'⚙ Parámetros'!B20))),'⚙ Parámetros'!G20/(1+2^(-'⚙ Parámetros'!F20*(Z8-'⚙ Parámetros'!E20))),1)+30/100*MAX('⚙ Parámetros'!D20/(1+2^(-'⚙ Parámetros'!C20*(AA8-'⚙ Parámetros'!B20))),'⚙ Parámetros'!G20/(1+2^(-'⚙ Parámetros'!F20*(AA8-'⚙ Parámetros'!E20))),1)),0) -> 3.7272727 | AH8: =('⚙ Parámetros'!B5/100*AB8+'⚙ Parámetros'!B6/100*AC8+'⚙ Parámetros'!B7/100*AD8+'⚙ Parámetros'!B8/100*AE8+'⚙ Parámetros'!B9/100*AF8+'⚙ Parámetros'!B10/100*AG8) -> 6.4012308 | AI8: =MIN(1+MAX(0,TODAY()-DATE(2026,1,14))/365*'⚙ Parámetros'!B33,'⚙ Parámetros'!B34) -> 1.0612329 | AJ8: =IFERROR(MIN(AH8*AI8,10),0) -> 6.7931965 | AK8: =IF(AB8>='⚙ Parámetros'!B23,"⚑ AUTO-PRIOR.(D1≥8)",IF(AJ8>='⚙ Parámetros'!B23,"PRIORITARIO",IF(AJ8>='⚙ Parámetros'!B24,"ALTA PRIORIDAD",IF(AJ8>='⚙ Parámetros'!B25,"PRIORIDAD MEDIA",IF(AJ8>='⚙ Parámetros'!B26,"BAJA PRIORIDAD","DESCARTAR"))))) -> PRIORIDAD MEDIA | AL8: =IF(AB8>=8,"SÍ ⚑","—") -> SÍ ⚑ | AM8: 100 | AN8: =IF(AM8="","—",IF(AM8<'⚙ Parámetros'!B29,"🟢 Corto",IF(AM8<'⚙ Parámetros'!B30,"🟡 Medio","🔴 Largo"))) -> 🔴 Largo
A9: 5 | B9: MPG-COM-014 Integracion DocuWare - D365 | C9: Supply chain y logística | D9: Marc Bometon | E9: 30/06/2025 | F9: 8 | G9: 1 | H9: 5 | I9: 8 | J9: 7 | K9: 1 | L9: 8 | M9: 3 | N9: 7 | O9: 1 | P9: 7 | Q9: 8 | R9: 5 | S9: 5 | T9: 5 | U9: 5 | V9: 5 | W9: 6 | X9: 3 | Y9: 4 | Z9: 2 | AA9: 8 | AB9: =IFERROR((30/100*MAX('⚙ Parámetros'!D15/(1+2^(-'⚙ Parámetros'!C15*(F9-'⚙ Parámetros'!B15))),'⚙ Parámetros'!G15/(1+2^(-'⚙ Parámetros'!F15*(F9-'⚙ Parámetros'!E15))),1)*F9+30/100*MAX('⚙ Parámetros'!D15/(1+2^(-'⚙ Parámetros'!C15*(G9-'⚙ Parámetros'!B15))),'⚙ Parámetros'!G15/(1+2^(-'⚙ Parámetros'!F15*(G9-'⚙ Parámetros'!E15))),1)*G9+20/100*MAX('⚙ Parámetros'!D15/(1+2^(-'⚙ Parámetros'!C15*(H9-'⚙ Parámetros'!B15))),'⚙ Parámetros'!G15/(1+2^(-'⚙ Parámetros'!F15*(H9-'⚙ Parámetros'!E15))),1)*H9+20/100*MAX('⚙ Parámetros'!D15/(1+2^(-'⚙ Parámetros'!C15*(I9-'⚙ Parámetros'!B15))),'⚙ Parámetros'!G15/(1+2^(-'⚙ Parámetros'!F15*(I9-'⚙ Parámetros'!E15))),1)*I9)/(30/100*MAX('⚙ Parámetros'!D15/(1+2^(-'⚙ Parámetros'!C15*(F9-'⚙ Parámetros'!B15))),'⚙ Parámetros'!G15/(1+2^(-'⚙ Parámetros'!F15*(F9-'⚙ Parámetros'!E15))),1)+30/100*MAX('⚙ Parámetros'!D15/(1+2^(-'⚙ Parámetros'!C15*(G9-'⚙ Parámetros'!B15))),'⚙ Parámetros'!G15/(1+2^(-'⚙ Parámetros'!F15*(G9-'⚙ Parámetros'!E15))),1)+20/100*MAX('⚙ Parámetros'!D15/(1+2^(-'⚙ Parámetros'!C15*(H9-'⚙ Parámetros'!B15))),'⚙ Parámetros'!G15/(1+2^(-'⚙ Parámetros'!F15*(H9-'⚙ Parámetros'!E15))),1)+20/100*MAX('⚙ Parámetros'!D15/(1+2^(-'⚙ Parámetros'!C15*(I9-'⚙ Parámetros'!B15))),'⚙ Parámetros'!G15/(1+2^(-'⚙ Parámetros'!F15*(I9-'⚙ Parámetros'!E15))),1)),0) -> 7.2748815 | AC9: =IFERROR((35/100*MAX('⚙ Parámetros'!D16/(1+2^(-'⚙ Parámetros'!C16*(J9-'⚙ Parámetros'!B16))),'⚙ Parámetros'!G16/(1+2^(-'⚙ Parámetros'!F16*(J9-'⚙ Parámetros'!E16))),1)*J9+25/100*MAX('⚙ Parámetros'!D16/(1+2^(-'⚙ Parámetros'!C16*(K9-'⚙ Parámetros'!B16))),'⚙ Parámetros'!G16/(1+2^(-'⚙ Parámetros'!F16*(K9-'⚙ Parámetros'!E16))),1)*K9+20/100*MAX('⚙ Parámetros'!D16/(1+2^(-'⚙ Parámetros'!C16*(L9-'⚙ Parámetros'!B16))),'⚙ Parámetros'!G16/(1+2^(-'⚙ Parámetros'!F16*(L9-'⚙ Parámetros'!E16))),1)*L9+20/100*MAX('⚙ Parámetros'!D16/(1+2^(-'⚙ Parámetros'!C16*(M9-'⚙ Parámetros'!B16))),'⚙ Parámetros'!G16/(1+2^(-'⚙ Parámetros'!F16*(M9-'⚙ Parámetros'!E16))),1)*M9)/(35/100*MAX('⚙ Parámetros'!D16/(1+2^(-'⚙ Parámetros'!C16*(J9-'⚙ Parámetros'!B16))),'⚙ Parámetros'!G16/(1+2^(-'⚙ Parámetros'!F16*(J9-'⚙ Parámetros'!E16))),1)+25/100*MAX('⚙ Parámetros'!D16/(1+2^(-'⚙ Parámetros'!C16*(K9-'⚙ Parámetros'!B16))),'⚙ Parámetros'!G16/(1+2^(-'⚙ Parámetros'!F16*(K9-'⚙ Parámetros'!E16))),1)+20/100*MAX('⚙ Parámetros'!D16/(1+2^(-'⚙ Parámetros'!C16*(L9-'⚙ Parámetros'!B16))),'⚙ Parámetros'!G16/(1+2^(-'⚙ Parámetros'!F16*(L9-'⚙ Parámetros'!E16))),1)+20/100*MAX('⚙ Parámetros'!D16/(1+2^(-'⚙ Parámetros'!C16*(M9-'⚙ Parámetros'!B16))),'⚙ Parámetros'!G16/(1+2^(-'⚙ Parámetros'!F16*(M9-'⚙ Parámetros'!E16))),1)),0) -> 6.3868613 | AD9: =IFERROR((30/100*MAX('⚙ Parámetros'!D17/(1+2^(-'⚙ Parámetros'!C17*(N9-'⚙ Parámetros'!B17))),'⚙ Parámetros'!G17/(1+2^(-'⚙ Parámetros'!F17*(N9-'⚙ Parámetros'!E17))),1)*N9+25/100*MAX('⚙ Parámetros'!D17/(1+2^(-'⚙ Parámetros'!C17*(O9-'⚙ Parámetros'!B17))),'⚙ Parámetros'!G17/(1+2^(-'⚙ Parámetros'!F17*(O9-'⚙ Parámetros'!E17))),1)*O9+25/100*MAX('⚙ Parámetros'!D17/(1+2^(-'⚙ Parámetros'!C17*(P9-'⚙ Parámetros'!B17))),'⚙ Parámetros'!G17/(1+2^(-'⚙ Parámetros'!F17*(P9-'⚙ Parámetros'!E17))),1)*P9+20/100*MAX('⚙ Parámetros'!D17/(1+2^(-'⚙ Parámetros'!C17*(Q9-'⚙ Parámetros'!B17))),'⚙ Parámetros'!G17/(1+2^(-'⚙ Parámetros'!F17*(Q9-'⚙ Parámetros'!E17))),1)*Q9)/(30/100*MAX('⚙ Parámetros'!D17/(1+2^(-'⚙ Parámetros'!C17*(N9-'⚙ Parámetros'!B17))),'⚙ Parámetros'!G17/(1+2^(-'⚙ Parámetros'!F17*(N9-'⚙ Parámetros'!E17))),1)+25/100*MAX('⚙ Parámetros'!D17/(1+2^(-'⚙ Parámetros'!C17*(O9-'⚙ Parámetros'!B17))),'⚙ Parámetros'!G17/(1+2^(-'⚙ Parámetros'!F17*(O9-'⚙ Parámetros'!E17))),1)+25/100*MAX('⚙ Parámetros'!D17/(1+2^(-'⚙ Parámetros'!C17*(P9-'⚙ Parámetros'!B17))),'⚙ Parámetros'!G17/(1+2^(-'⚙ Parámetros'!F17*(P9-'⚙ Parámetros'!E17))),1)+20/100*MAX('⚙ Parámetros'!D17/(1+2^(-'⚙ Parámetros'!C17*(Q9-'⚙ Parámetros'!B17))),'⚙ Parámetros'!G17/(1+2^(-'⚙ Parámetros'!F17*(Q9-'⚙ Parámetros'!E17))),1)),0) -> 6.7218543 | AE9: =IFERROR((30/100*MAX('⚙ Parámetros'!D18/(1+2^(-'⚙ Parámetros'!C18*(R9-'⚙ Parámetros'!B18))),'⚙ Parámetros'!G18/(1+2^(-'⚙ Parámetros'!F18*(R9-'⚙ Parámetros'!E18))),1)*R9+30/100*MAX('⚙ Parámetros'!D18/(1+2^(-'⚙ Parámetros'!C18*(S9-'⚙ Parámetros'!B18))),'⚙ Parámetros'!G18/(1+2^(-'⚙ Parámetros'!F18*(S9-'⚙ Parámetros'!E18))),1)*S9+20/100*MAX('⚙ Parámetros'!D18/(1+2^(-'⚙ Parámetros'!C18*(T9-'⚙ Parámetros'!B18))),'⚙ Parámetros'!G18/(1+2^(-'⚙ Parámetros'!F18*(T9-'⚙ Parámetros'!E18))),1)*T9+20/100*MAX('⚙ Parámetros'!D18/(1+2^(-'⚙ Parámetros'!C18*(U9-'⚙ Parámetros'!B18))),'⚙ Parámetros'!G18/(1+2^(-'⚙ Parámetros'!F18*(U9-'⚙ Parámetros'!E18))),1)*U9)/(30/100*MAX('⚙ Parámetros'!D18/(1+2^(-'⚙ Parámetros'!C18*(R9-'⚙ Parámetros'!B18))),'⚙ Parámetros'!G18/(1+2^(-'⚙ Parámetros'!F18*(R9-'⚙ Parámetros'!E18))),1)+30/100*MAX('⚙ Parámetros'!D18/(1+2^(-'⚙ Parámetros'!C18*(S9-'⚙ Parámetros'!B18))),'⚙ Parámetros'!G18/(1+2^(-'⚙ Parámetros'!F18*(S9-'⚙ Parámetros'!E18))),1)+20/100*MAX('⚙ Parámetros'!D18/(1+2^(-'⚙ Parámetros'!C18*(T9-'⚙ Parámetros'!B18))),'⚙ Parámetros'!G18/(1+2^(-'⚙ Parámetros'!F18*(T9-'⚙ Parámetros'!E18))),1)+20/100*MAX('⚙ Parámetros'!D18/(1+2^(-'⚙ Parámetros'!C18*(U9-'⚙ Parámetros'!B18))),'⚙ Parámetros'!G18/(1+2^(-'⚙ Parámetros'!F18*(U9-'⚙ Parámetros'!E18))),1)),0) -> 5 | AF9: =IFERROR((30/100*MAX('⚙ Parámetros'!D19/(1+2^(-'⚙ Parámetros'!C19*(V9-'⚙ Parámetros'!B19))),'⚙ Parámetros'!G19/(1+2^(-'⚙ Parámetros'!F19*(V9-'⚙ Parámetros'!E19))),1)*V9+35/100*MAX('⚙ Parámetros'!D19/(1+2^(-'⚙ Parámetros'!C19*(W9-'⚙ Parámetros'!B19))),'⚙ Parámetros'!G19/(1+2^(-'⚙ Parámetros'!F19*(W9-'⚙ Parámetros'!E19))),1)*W9+35/100*MAX('⚙ Parámetros'!D19/(1+2^(-'⚙ Parámetros'!C19*(X9-'⚙ Parámetros'!B19))),'⚙ Parámetros'!G19/(1+2^(-'⚙ Parámetros'!F19*(X9-'⚙ Parámetros'!E19))),1)*X9)/(30/100*MAX('⚙ Parámetros'!D19/(1+2^(-'⚙ Parámetros'!C19*(V9-'⚙ Parámetros'!B19))),'⚙ Parámetros'!G19/(1+2^(-'⚙ Parámetros'!F19*(V9-'⚙ Parámetros'!E19))),1)+35/100*MAX('⚙ Parámetros'!D19/(1+2^(-'⚙ Parámetros'!C19*(W9-'⚙ Parámetros'!B19))),'⚙ Parámetros'!G19/(1+2^(-'⚙ Parámetros'!F19*(W9-'⚙ Parámetros'!E19))),1)+35/100*MAX('⚙ Parámetros'!D19/(1+2^(-'⚙ Parámetros'!C19*(X9-'⚙ Parámetros'!B19))),'⚙ Parámetros'!G19/(1+2^(-'⚙ Parámetros'!F19*(X9-'⚙ Parámetros'!E19))),1)),0) -> 5.0782123 | AG9: =IFERROR((35/100*MAX('⚙ Parámetros'!D20/(1+2^(-'⚙ Parámetros'!C20*(Y9-'⚙ Parámetros'!B20))),'⚙ Parámetros'!G20/(1+2^(-'⚙ Parámetros'!F20*(Y9-'⚙ Parámetros'!E20))),1)*Y9+35/100*MAX('⚙ Parámetros'!D20/(1+2^(-'⚙ Parámetros'!C20*(Z9-'⚙ Parámetros'!B20))),'⚙ Parámetros'!G20/(1+2^(-'⚙ Parámetros'!F20*(Z9-'⚙ Parámetros'!E20))),1)*Z9+30/100*MAX('⚙ Parámetros'!D20/(1+2^(-'⚙ Parámetros'!C20*(AA9-'⚙ Parámetros'!B20))),'⚙ Parámetros'!G20/(1+2^(-'⚙ Parámetros'!F20*(AA9-'⚙ Parámetros'!E20))),1)*AA9)/(35/100*MAX('⚙ Parámetros'!D20/(1+2^(-'⚙ Parámetros'!C20*(Y9-'⚙ Parámetros'!B20))),'⚙ Parámetros'!G20/(1+2^(-'⚙ Parámetros'!F20*(Y9-'⚙ Parámetros'!E20))),1)+35/100*MAX('⚙ Parámetros'!D20/(1+2^(-'⚙ Parámetros'!C20*(Z9-'⚙ Parámetros'!B20))),'⚙ Parámetros'!G20/(1+2^(-'⚙ Parámetros'!F20*(Z9-'⚙ Parámetros'!E20))),1)+30/100*MAX('⚙ Parámetros'!D20/(1+2^(-'⚙ Parámetros'!C20*(AA9-'⚙ Parámetros'!B20))),'⚙ Parámetros'!G20/(1+2^(-'⚙ Parámetros'!F20*(AA9-'⚙ Parámetros'!E20))),1)),0) -> 5.8125 | AH9: =('⚙ Parámetros'!B5/100*AB9+'⚙ Parámetros'!B6/100*AC9+'⚙ Parámetros'!B7/100*AD9+'⚙ Parámetros'!B8/100*AE9+'⚙ Parámetros'!B9/100*AF9+'⚙ Parámetros'!B10/100*AG9) -> 6.3770288 | AI9: =MIN(1+MAX(0,TODAY()-DATE(2025,6,30))/365*'⚙ Parámetros'!B33,'⚙ Parámetros'!B34) -> 1.1426027 | AJ9: =IFERROR(MIN(AH9*AI9,10),0) -> 7.2864106 | AK9: =IF(AB9>='⚙ Parámetros'!B23,"⚑ AUTO-PRIOR.(D1≥8)",IF(AJ9>='⚙ Parámetros'!B23,"PRIORITARIO",IF(AJ9>='⚙ Parámetros'!B24,"ALTA PRIORIDAD",IF(AJ9>='⚙ Parámetros'!B25,"PRIORIDAD MEDIA",IF(AJ9>='⚙ Parámetros'!B26,"BAJA PRIORIDAD","DESCARTAR"))))) -> ALTA PRIORIDAD | AL9: =IF(AB9>=8,"SÍ ⚑","—") -> — | AM9: 25 | AN9: =IF(AM9="","—",IF(AM9<'⚙ Parámetros'!B29,"🟢 Corto",IF(AM9<'⚙ Parámetros'!B30,"🟡 Medio","🔴 Largo"))) -> 🟢 Corto
A10: 6 | B10: MPG-VTA-006_1 Integracion B2B --> MiddleWare | C10: Ventas y marketing | D10: Marc Bometon | E10: 24/03/2026 | F10: 5 | G10: 1 | H10: 5 | I10: 1 | J10: 10 | K10: 9 | L10: 8 | M10: 9 | N10: 8 | O10: 8 | P10: 7 | Q10: 6 | R10: 9 | S10: 9 | T10: 5 | U10: 5 | V10: 7 | W10: 6 | X10: 5 | Y10: 5 | Z10: 2 | AA10: 5 | AB10: =IFERROR((30/100*MAX('⚙ Parámetros'!D15/(1+2^(-'⚙ Parámetros'!C15*(F10-'⚙ Parámetros'!B15))),'⚙ Parámetros'!G15/(1+2^(-'⚙ Parámetros'!F15*(F10-'⚙ Parámetros'!E15))),1)*F10+30/100*MAX('⚙ Parámetros'!D15/(1+2^(-'⚙ Parámetros'!C15*(G10-'⚙ Parámetros'!B15))),'⚙ Parámetros'!G15/(1+2^(-'⚙ Parámetros'!F15*(G10-'⚙ Parámetros'!E15))),1)*G10+20/100*MAX('⚙ Parámetros'!D15/(1+2^(-'⚙ Parámetros'!C15*(H10-'⚙ Parámetros'!B15))),'⚙ Parámetros'!G15/(1+2^(-'⚙ Parámetros'!F15*(H10-'⚙ Parámetros'!E15))),1)*H10+20/100*MAX('⚙ Parámetros'!D15/(1+2^(-'⚙ Parámetros'!C15*(I10-'⚙ Parámetros'!B15))),'⚙ Parámetros'!G15/(1+2^(-'⚙ Parámetros'!F15*(I10-'⚙ Parámetros'!E15))),1)*I10)/(30/100*MAX('⚙ Parámetros'!D15/(1+2^(-'⚙ Parámetros'!C15*(F10-'⚙ Parámetros'!B15))),'⚙ Parámetros'!G15/(1+2^(-'⚙ Parámetros'!F15*(F10-'⚙ Parámetros'!E15))),1)+30/100*MAX('⚙ Parámetros'!D15/(1+2^(-'⚙ Parámetros'!C15*(G10-'⚙ Parámetros'!B15))),'⚙ Parámetros'!G15/(1+2^(-'⚙ Parámetros'!F15*(G10-'⚙ Parámetros'!E15))),1)+20/100*MAX('⚙ Parámetros'!D15/(1+2^(-'⚙ Parámetros'!C15*(H10-'⚙ Parámetros'!B15))),'⚙ Parámetros'!G15/(1+2^(-'⚙ Parámetros'!F15*(H10-'⚙ Parámetros'!E15))),1)+20/100*MAX('⚙ Parámetros'!D15/(1+2^(-'⚙ Parámetros'!C15*(I10-'⚙ Parámetros'!B15))),'⚙ Parámetros'!G15/(1+2^(-'⚙ Parámetros'!F15*(I10-'⚙ Parámetros'!E15))),1)),0) -> 3.4615385 | AC10: =IFERROR((35/100*MAX('⚙ Parámetros'!D16/(1+2^(-'⚙ Parámetros'!C16*(J10-'⚙ Parámetros'!B16))),'⚙ Parámetros'!G16/(1+2^(-'⚙ Parámetros'!F16*(J10-'⚙ Parámetros'!E16))),1)*J10+25/100*MAX('⚙ Parámetros'!D16/(1+2^(-'⚙ Parámetros'!C16*(K10-'⚙ Parámetros'!B16))),'⚙ Parámetros'!G16/(1+2^(-'⚙ Parámetros'!F16*(K10-'⚙ Parámetros'!E16))),1)*K10+20/100*MAX('⚙ Parámetros'!D16/(1+2^(-'⚙ Parámetros'!C16*(L10-'⚙ Parámetros'!B16))),'⚙ Parámetros'!G16/(1+2^(-'⚙ Parámetros'!F16*(L10-'⚙ Parámetros'!E16))),1)*L10+20/100*MAX('⚙ Parámetros'!D16/(1+2^(-'⚙ Parámetros'!C16*(M10-'⚙ Parámetros'!B16))),'⚙ Parámetros'!G16/(1+2^(-'⚙ Parámetros'!F16*(M10-'⚙ Parámetros'!E16))),1)*M10)/(35/100*MAX('⚙ Parámetros'!D16/(1+2^(-'⚙ Parámetros'!C16*(J10-'⚙ Parámetros'!B16))),'⚙ Parámetros'!G16/(1+2^(-'⚙ Parámetros'!F16*(J10-'⚙ Parámetros'!E16))),1)+25/100*MAX('⚙ Parámetros'!D16/(1+2^(-'⚙ Parámetros'!C16*(K10-'⚙ Parámetros'!B16))),'⚙ Parámetros'!G16/(1+2^(-'⚙ Parámetros'!F16*(K10-'⚙ Parámetros'!E16))),1)+20/100*MAX('⚙ Parámetros'!D16/(1+2^(-'⚙ Parámetros'!C16*(L10-'⚙ Parámetros'!B16))),'⚙ Parámetros'!G16/(1+2^(-'⚙ Parámetros'!F16*(L10-'⚙ Parámetros'!E16))),1)+20/100*MAX('⚙ Parámetros'!D16/(1+2^(-'⚙ Parámetros'!C16*(M10-'⚙ Parámetros'!B16))),'⚙ Parámetros'!G16/(1+2^(-'⚙ Parámetros'!F16*(M10-'⚙ Parámetros'!E16))),1)),0) -> 9.290611 | AD10: =IFERROR((30/100*MAX('⚙ Parámetros'!D17/(1+2^(-'⚙ Parámetros'!C17*(N10-'⚙ Parámetros'!B17))),'⚙ Parámetros'!G17/(1+2^(-'⚙ Parámetros'!F17*(N10-'⚙ Parámetros'!E17))),1)*N10+25/100*MAX('⚙ Parámetros'!D17/(1+2^(-'⚙ Parámetros'!C17*(O10-'⚙ Parámetros'!B17))),'⚙ Parámetros'!G17/(1+2^(-'⚙ Parámetros'!F17*(O10-'⚙ Parámetros'!E17))),1)*O10+25/100*MAX('⚙ Parámetros'!D17/(1+2^(-'⚙ Parámetros'!C17*(P10-'⚙ Parámetros'!B17))),'⚙ Parámetros'!G17/(1+2^(-'⚙ Parámetros'!F17*(P10-'⚙ Parámetros'!E17))),1)*P10+20/100*MAX('⚙ Parámetros'!D17/(1+2^(-'⚙ Parámetros'!C17*(Q10-'⚙ Parámetros'!B17))),'⚙ Parámetros'!G17/(1+2^(-'⚙ Parámetros'!F17*(Q10-'⚙ Parámetros'!E17))),1)*Q10)/(30/100*MAX('⚙ Parámetros'!D17/(1+2^(-'⚙ Parámetros'!C17*(N10-'⚙ Parámetros'!B17))),'⚙ Parámetros'!G17/(1+2^(-'⚙ Parámetros'!F17*(N10-'⚙ Parámetros'!E17))),1)+25/100*MAX('⚙ Parámetros'!D17/(1+2^(-'⚙ Parámetros'!C17*(O10-'⚙ Parámetros'!B17))),'⚙ Parámetros'!G17/(1+2^(-'⚙ Parámetros'!F17*(O10-'⚙ Parámetros'!E17))),1)+25/100*MAX('⚙ Parámetros'!D17/(1+2^(-'⚙ Parámetros'!C17*(P10-'⚙ Parámetros'!B17))),'⚙ Parámetros'!G17/(1+2^(-'⚙ Parámetros'!F17*(P10-'⚙ Parámetros'!E17))),1)+20/100*MAX('⚙ Parámetros'!D17/(1+2^(-'⚙ Parámetros'!C17*(Q10-'⚙ Parámetros'!B17))),'⚙ Parámetros'!G17/(1+2^(-'⚙ Parámetros'!F17*(Q10-'⚙ Parámetros'!E17))),1)),0) -> 7.5139442 | AE10: =IFERROR((30/100*MAX('⚙ Parámetros'!D18/(1+2^(-'⚙ Parámetros'!C18*(R10-'⚙ Parámetros'!B18))),'⚙ Parámetros'!G18/(1+2^(-'⚙ Parámetros'!F18*(R10-'⚙ Parámetros'!E18))),1)*R10+30/100*MAX('⚙ Parámetros'!D18/(1+2^(-'⚙ Parámetros'!C18*(S10-'⚙ Parámetros'!B18))),'⚙ Parámetros'!G18/(1+2^(-'⚙ Parámetros'!F18*(S10-'⚙ Parámetros'!E18))),1)*S10+20/100*MAX('⚙ Parámetros'!D18/(1+2^(-'⚙ Parámetros'!C18*(T10-'⚙ Parámetros'!B18))),'⚙ Parámetros'!G18/(1+2^(-'⚙ Parámetros'!F18*(T10-'⚙ Parámetros'!E18))),1)*T10+20/100*MAX('⚙ Parámetros'!D18/(1+2^(-'⚙ Parámetros'!C18*(U10-'⚙ Parámetros'!B18))),'⚙ Parámetros'!G18/(1+2^(-'⚙ Parámetros'!F18*(U10-'⚙ Parámetros'!E18))),1)*U10)/(30/100*MAX('⚙ Parámetros'!D18/(1+2^(-'⚙ Parámetros'!C18*(R10-'⚙ Parámetros'!B18))),'⚙ Parámetros'!G18/(1+2^(-'⚙ Parámetros'!F18*(R10-'⚙ Parámetros'!E18))),1)+30/100*MAX('⚙ Parámetros'!D18/(1+2^(-'⚙ Parámetros'!C18*(S10-'⚙ Parámetros'!B18))),'⚙ Parámetros'!G18/(1+2^(-'⚙ Parámetros'!F18*(S10-'⚙ Parámetros'!E18))),1)+20/100*MAX('⚙ Parámetros'!D18/(1+2^(-'⚙ Parámetros'!C18*(T10-'⚙ Parámetros'!B18))),'⚙ Parámetros'!G18/(1+2^(-'⚙ Parámetros'!F18*(T10-'⚙ Parámetros'!E18))),1)+20/100*MAX('⚙ Parámetros'!D18/(1+2^(-'⚙ Parámetros'!C18*(U10-'⚙ Parámetros'!B18))),'⚙ Parámetros'!G18/(1+2^(-'⚙ Parámetros'!F18*(U10-'⚙ Parámetros'!E18))),1)),0) -> 8.180106 | AF10: =IFERROR((30/100*MAX('⚙ Parámetros'!D19/(1+2^(-'⚙ Parámetros'!C19*(V10-'⚙ Parámetros'!B19))),'⚙ Parámetros'!G19/(1+2^(-'⚙ Parámetros'!F19*(V10-'⚙ Parámetros'!E19))),1)*V10+35/100*MAX('⚙ Parámetros'!D19/(1+2^(-'⚙ Parámetros'!C19*(W10-'⚙ Parámetros'!B19))),'⚙ Parámetros'!G19/(1+2^(-'⚙ Parámetros'!F19*(W10-'⚙ Parámetros'!E19))),1)*W10+35/100*MAX('⚙ Parámetros'!D19/(1+2^(-'⚙ Parámetros'!C19*(X10-'⚙ Parámetros'!B19))),'⚙ Parámetros'!G19/(1+2^(-'⚙ Parámetros'!F19*(X10-'⚙ Parámetros'!E19))),1)*X10)/(30/100*MAX('⚙ Parámetros'!D19/(1+2^(-'⚙ Parámetros'!C19*(V10-'⚙ Parámetros'!B19))),'⚙ Parámetros'!G19/(1+2^(-'⚙ Parámetros'!F19*(V10-'⚙ Parámetros'!E19))),1)+35/100*MAX('⚙ Parámetros'!D19/(1+2^(-'⚙ Parámetros'!C19*(W10-'⚙ Parámetros'!B19))),'⚙ Parámetros'!G19/(1+2^(-'⚙ Parámetros'!F19*(W10-'⚙ Parámetros'!E19))),1)+35/100*MAX('⚙ Parámetros'!D19/(1+2^(-'⚙ Parámetros'!C19*(X10-'⚙ Parámetros'!B19))),'⚙ Parámetros'!G19/(1+2^(-'⚙ Parámetros'!F19*(X10-'⚙ Parámetros'!E19))),1)),0) -> 6.042735 | AG10: =IFERROR((35/100*MAX('⚙ Parámetros'!D20/(1+2^(-'⚙ Parámetros'!C20*(Y10-'⚙ Parámetros'!B20))),'⚙ Parámetros'!G20/(1+2^(-'⚙ Parámetros'!F20*(Y10-'⚙ Parámetros'!E20))),1)*Y10+35/100*MAX('⚙ Parámetros'!D20/(1+2^(-'⚙ Parámetros'!C20*(Z10-'⚙ Parámetros'!B20))),'⚙ Parámetros'!G20/(1+2^(-'⚙ Parámetros'!F20*(Z10-'⚙ Parámetros'!E20))),1)*Z10+30/100*MAX('⚙ Parámetros'!D20/(1+2^(-'⚙ Parámetros'!C20*(AA10-'⚙ Parámetros'!B20))),'⚙ Parámetros'!G20/(1+2^(-'⚙ Parámetros'!F20*(AA10-'⚙ Parámetros'!E20))),1)*AA10)/(35/100*MAX('⚙ Parámetros'!D20/(1+2^(-'⚙ Parámetros'!C20*(Y10-'⚙ Parámetros'!B20))),'⚙ Parámetros'!G20/(1+2^(-'⚙ Parámetros'!F20*(Y10-'⚙ Parámetros'!E20))),1)+35/100*MAX('⚙ Parámetros'!D20/(1+2^(-'⚙ Parámetros'!C20*(Z10-'⚙ Parámetros'!B20))),'⚙ Parámetros'!G20/(1+2^(-'⚙ Parámetros'!F20*(Z10-'⚙ Parámetros'!E20))),1)+30/100*MAX('⚙ Parámetros'!D20/(1+2^(-'⚙ Parámetros'!C20*(AA10-'⚙ Parámetros'!B20))),'⚙ Parámetros'!G20/(1+2^(-'⚙ Parámetros'!F20*(AA10-'⚙ Parámetros'!E20))),1)),0) -> 4.1369863 | AH10: =('⚙ Parámetros'!B5/100*AB10+'⚙ Parámetros'!B6/100*AC10+'⚙ Parámetros'!B7/100*AD10+'⚙ Parámetros'!B8/100*AE10+'⚙ Parámetros'!B9/100*AF10+'⚙ Parámetros'!B10/100*AG10) -> 6.3162177 | AI10: =MIN(1+MAX(0,TODAY()-DATE(2026,3,24))/365*'⚙ Parámetros'!B33,'⚙ Parámetros'!B34) -> 1.0328767 | AJ10: =IFERROR(MIN(AH10*AI10,10),0) -> 6.5238742 | AK10: =IF(AB10>='⚙ Parámetros'!B23,"⚑ AUTO-PRIOR.(D1≥8)",IF(AJ10>='⚙ Parámetros'!B23,"PRIORITARIO",IF(AJ10>='⚙ Parámetros'!B24,"ALTA PRIORIDAD",IF(AJ10>='⚙ Parámetros'!B25,"PRIORIDAD MEDIA",IF(AJ10>='⚙ Parámetros'!B26,"BAJA PRIORIDAD","DESCARTAR"))))) -> PRIORIDAD MEDIA | AL10: =IF(AB10>=8,"SÍ ⚑","—") -> — | AM10: 34 | AN10: =IF(AM10="","—",IF(AM10<'⚙ Parámetros'!B29,"🟢 Corto",IF(AM10<'⚙ Parámetros'!B30,"🟡 Medio","🔴 Largo"))) -> 🟡 Medio
A11: 7 | B11: MPG-CAL-025 Mejoras de calidad - alerta PDA | C11: Regulatorio y calidad | D11: Marc Bometon | E11: 25/11/2025 | F11: 8 | G11: 7 | H11: 1 | I11: 8 | J11: 1 | K11: 1 | L11: 8 | M11: 3 | N11: 1 | O11: 6 | P11: 1 | Q11: 8 | R11: 9 | S11: 9 | T11: 5 | U11: 5 | V11: 8 | W11: 4 | X11: 5 | Y11: 4 | Z11: 2 | AA11: 5 | AB11: =IFERROR((30/100*MAX('⚙ Parámetros'!D15/(1+2^(-'⚙ Parámetros'!C15*(F11-'⚙ Parámetros'!B15))),'⚙ Parámetros'!G15/(1+2^(-'⚙ Parámetros'!F15*(F11-'⚙ Parámetros'!E15))),1)*F11+30/100*MAX('⚙ Parámetros'!D15/(1+2^(-'⚙ Parámetros'!C15*(G11-'⚙ Parámetros'!B15))),'⚙ Parámetros'!G15/(1+2^(-'⚙ Parámetros'!F15*(G11-'⚙ Parámetros'!E15))),1)*G11+20/100*MAX('⚙ Parámetros'!D15/(1+2^(-'⚙ Parámetros'!C15*(H11-'⚙ Parámetros'!B15))),'⚙ Parámetros'!G15/(1+2^(-'⚙ Parámetros'!F15*(H11-'⚙ Parámetros'!E15))),1)*H11+20/100*MAX('⚙ Parámetros'!D15/(1+2^(-'⚙ Parámetros'!C15*(I11-'⚙ Parámetros'!B15))),'⚙ Parámetros'!G15/(1+2^(-'⚙ Parámetros'!F15*(I11-'⚙ Parámetros'!E15))),1)*I11)/(30/100*MAX('⚙ Parámetros'!D15/(1+2^(-'⚙ Parámetros'!C15*(F11-'⚙ Parámetros'!B15))),'⚙ Parámetros'!G15/(1+2^(-'⚙ Parámetros'!F15*(F11-'⚙ Parámetros'!E15))),1)+30/100*MAX('⚙ Parámetros'!D15/(1+2^(-'⚙ Parámetros'!C15*(G11-'⚙ Parámetros'!B15))),'⚙ Parámetros'!G15/(1+2^(-'⚙ Parámetros'!F15*(G11-'⚙ Parámetros'!E15))),1)+20/100*MAX('⚙ Parámetros'!D15/(1+2^(-'⚙ Parámetros'!C15*(H11-'⚙ Parámetros'!B15))),'⚙ Parámetros'!G15/(1+2^(-'⚙ Parámetros'!F15*(H11-'⚙ Parámetros'!E15))),1)+20/100*MAX('⚙ Parámetros'!D15/(1+2^(-'⚙ Parámetros'!C15*(I11-'⚙ Parámetros'!B15))),'⚙ Parámetros'!G15/(1+2^(-'⚙ Parámetros'!F15*(I11-'⚙ Parámetros'!E15))),1)),0) -> 7.4660194 | AC11: =IFERROR((35/100*MAX('⚙ Parámetros'!D16/(1+2^(-'⚙ Parámetros'!C16*(J11-'⚙ Parámetros'!B16))),'⚙ Parámetros'!G16/(1+2^(-'⚙ Parámetros'!F16*(J11-'⚙ Parámetros'!E16))),1)*J11+25/100*MAX('⚙ Parámetros'!D16/(1+2^(-'⚙ Parámetros'!C16*(K11-'⚙ Parámetros'!B16))),'⚙ Parámetros'!G16/(1+2^(-'⚙ Parámetros'!F16*(K11-'⚙ Parámetros'!E16))),1)*K11+20/100*MAX('⚙ Parámetros'!D16/(1+2^(-'⚙ Parámetros'!C16*(L11-'⚙ Parámetros'!B16))),'⚙ Parámetros'!G16/(1+2^(-'⚙ Parámetros'!F16*(L11-'⚙ Parámetros'!E16))),1)*L11+20/100*MAX('⚙ Parámetros'!D16/(1+2^(-'⚙ Parámetros'!C16*(M11-'⚙ Parámetros'!B16))),'⚙ Parámetros'!G16/(1+2^(-'⚙ Parámetros'!F16*(M11-'⚙ Parámetros'!E16))),1)*M11)/(35/100*MAX('⚙ Parámetros'!D16/(1+2^(-'⚙ Parámetros'!C16*(J11-'⚙ Parámetros'!B16))),'⚙ Parámetros'!G16/(1+2^(-'⚙ Parámetros'!F16*(J11-'⚙ Parámetros'!E16))),1)+25/100*MAX('⚙ Parámetros'!D16/(1+2^(-'⚙ Parámetros'!C16*(K11-'⚙ Parámetros'!B16))),'⚙ Parámetros'!G16/(1+2^(-'⚙ Parámetros'!F16*(K11-'⚙ Parámetros'!E16))),1)+20/100*MAX('⚙ Parámetros'!D16/(1+2^(-'⚙ Parámetros'!C16*(L11-'⚙ Parámetros'!B16))),'⚙ Parámetros'!G16/(1+2^(-'⚙ Parámetros'!F16*(L11-'⚙ Parámetros'!E16))),1)+20/100*MAX('⚙ Parámetros'!D16/(1+2^(-'⚙ Parámetros'!C16*(M11-'⚙ Parámetros'!B16))),'⚙ Parámetros'!G16/(1+2^(-'⚙ Parámetros'!F16*(M11-'⚙ Parámetros'!E16))),1)),0) -> 4.9411765 | AD11: =IFERROR((30/100*MAX('⚙ Parámetros'!D17/(1+2^(-'⚙ Parámetros'!C17*(N11-'⚙ Parámetros'!B17))),'⚙ Parámetros'!G17/(1+2^(-'⚙ Parámetros'!F17*(N11-'⚙ Parámetros'!E17))),1)*N11+25/100*MAX('⚙ Parámetros'!D17/(1+2^(-'⚙ Parámetros'!C17*(O11-'⚙ Parámetros'!B17))),'⚙ Parámetros'!G17/(1+2^(-'⚙ Parámetros'!F17*(O11-'⚙ Parámetros'!E17))),1)*O11+25/100*MAX('⚙ Parámetros'!D17/(1+2^(-'⚙ Parámetros'!C17*(P11-'⚙ Parámetros'!B17))),'⚙ Parámetros'!G17/(1+2^(-'⚙ Parámetros'!F17*(P11-'⚙ Parámetros'!E17))),1)*P11+20/100*MAX('⚙ Parámetros'!D17/(1+2^(-'⚙ Parámetros'!C17*(Q11-'⚙ Parámetros'!B17))),'⚙ Parámetros'!G17/(1+2^(-'⚙ Parámetros'!F17*(Q11-'⚙ Parámetros'!E17))),1)*Q11)/(30/100*MAX('⚙ Parámetros'!D17/(1+2^(-'⚙ Parámetros'!C17*(N11-'⚙ Parámetros'!B17))),'⚙ Parámetros'!G17/(1+2^(-'⚙ Parámetros'!F17*(N11-'⚙ Parámetros'!E17))),1)+25/100*MAX('⚙ Parámetros'!D17/(1+2^(-'⚙ Parámetros'!C17*(O11-'⚙ Parámetros'!B17))),'⚙ Parámetros'!G17/(1+2^(-'⚙ Parámetros'!F17*(O11-'⚙ Parámetros'!E17))),1)+25/100*MAX('⚙ Parámetros'!D17/(1+2^(-'⚙ Parámetros'!C17*(P11-'⚙ Parámetros'!B17))),'⚙ Parámetros'!G17/(1+2^(-'⚙ Parámetros'!F17*(P11-'⚙ Parámetros'!E17))),1)+20/100*MAX('⚙ Parámetros'!D17/(1+2^(-'⚙ Parámetros'!C17*(Q11-'⚙ Parámetros'!B17))),'⚙ Parámetros'!G17/(1+2^(-'⚙ Parámetros'!F17*(Q11-'⚙ Parámetros'!E17))),1)),0) -> 5.4102564 | AE11: =IFERROR((30/100*MAX('⚙ Parámetros'!D18/(1+2^(-'⚙ Parámetros'!C18*(R11-'⚙ Parámetros'!B18))),'⚙ Parámetros'!G18/(1+2^(-'⚙ Parámetros'!F18*(R11-'⚙ Parámetros'!E18))),1)*R11+30/100*MAX('⚙ Parámetros'!D18/(1+2^(-'⚙ Parámetros'!C18*(S11-'⚙ Parámetros'!B18))),'⚙ Parámetros'!G18/(1+2^(-'⚙ Parámetros'!F18*(S11-'⚙ Parámetros'!E18))),1)*S11+20/100*MAX('⚙ Parámetros'!D18/(1+2^(-'⚙ Parámetros'!C18*(T11-'⚙ Parámetros'!B18))),'⚙ Parámetros'!G18/(1+2^(-'⚙ Parámetros'!F18*(T11-'⚙ Parámetros'!E18))),1)*T11+20/100*MAX('⚙ Parámetros'!D18/(1+2^(-'⚙ Parámetros'!C18*(U11-'⚙ Parámetros'!B18))),'⚙ Parámetros'!G18/(1+2^(-'⚙ Parámetros'!F18*(U11-'⚙ Parámetros'!E18))),1)*U11)/(30/100*MAX('⚙ Parámetros'!D18/(1+2^(-'⚙ Parámetros'!C18*(R11-'⚙ Parámetros'!B18))),'⚙ Parámetros'!G18/(1+2^(-'⚙ Parámetros'!F18*(R11-'⚙ Parámetros'!E18))),1)+30/100*MAX('⚙ Parámetros'!D18/(1+2^(-'⚙ Parámetros'!C18*(S11-'⚙ Parámetros'!B18))),'⚙ Parámetros'!G18/(1+2^(-'⚙ Parámetros'!F18*(S11-'⚙ Parámetros'!E18))),1)+20/100*MAX('⚙ Parámetros'!D18/(1+2^(-'⚙ Parámetros'!C18*(T11-'⚙ Parámetros'!B18))),'⚙ Parámetros'!G18/(1+2^(-'⚙ Parámetros'!F18*(T11-'⚙ Parámetros'!E18))),1)+20/100*MAX('⚙ Parámetros'!D18/(1+2^(-'⚙ Parámetros'!C18*(U11-'⚙ Parámetros'!B18))),'⚙ Parámetros'!G18/(1+2^(-'⚙ Parámetros'!F18*(U11-'⚙ Parámetros'!E18))),1)),0) -> 8.180106 | AF11: =IFERROR((30/100*MAX('⚙ Parámetros'!D19/(1+2^(-'⚙ Parámetros'!C19*(V11-'⚙ Parámetros'!B19))),'⚙ Parámetros'!G19/(1+2^(-'⚙ Parámetros'!F19*(V11-'⚙ Parámetros'!E19))),1)*V11+35/100*MAX('⚙ Parámetros'!D19/(1+2^(-'⚙ Parámetros'!C19*(W11-'⚙ Parámetros'!B19))),'⚙ Parámetros'!G19/(1+2^(-'⚙ Parámetros'!F19*(W11-'⚙ Parámetros'!E19))),1)*W11+35/100*MAX('⚙ Parámetros'!D19/(1+2^(-'⚙ Parámetros'!C19*(X11-'⚙ Parámetros'!B19))),'⚙ Parámetros'!G19/(1+2^(-'⚙ Parámetros'!F19*(X11-'⚙ Parámetros'!E19))),1)*X11)/(30/100*MAX('⚙ Parámetros'!D19/(1+2^(-'⚙ Parámetros'!C19*(V11-'⚙ Parámetros'!B19))),'⚙ Parámetros'!G19/(1+2^(-'⚙ Parámetros'!F19*(V11-'⚙ Parámetros'!E19))),1)+35/100*MAX('⚙ Parámetros'!D19/(1+2^(-'⚙ Parámetros'!C19*(W11-'⚙ Parámetros'!B19))),'⚙ Parámetros'!G19/(1+2^(-'⚙ Parámetros'!F19*(W11-'⚙ Parámetros'!E19))),1)+35/100*MAX('⚙ Parámetros'!D19/(1+2^(-'⚙ Parámetros'!C19*(X11-'⚙ Parámetros'!B19))),'⚙ Parámetros'!G19/(1+2^(-'⚙ Parámetros'!F19*(X11-'⚙ Parámetros'!E19))),1)),0) -> 6.1538462 | AG11: =IFERROR((35/100*MAX('⚙ Parámetros'!D20/(1+2^(-'⚙ Parámetros'!C20*(Y11-'⚙ Parámetros'!B20))),'⚙ Parámetros'!G20/(1+2^(-'⚙ Parámetros'!F20*(Y11-'⚙ Parámetros'!E20))),1)*Y11+35/100*MAX('⚙ Parámetros'!D20/(1+2^(-'⚙ Parámetros'!C20*(Z11-'⚙ Parámetros'!B20))),'⚙ Parámetros'!G20/(1+2^(-'⚙ Parámetros'!F20*(Z11-'⚙ Parámetros'!E20))),1)*Z11+30/100*MAX('⚙ Parámetros'!D20/(1+2^(-'⚙ Parámetros'!C20*(AA11-'⚙ Parámetros'!B20))),'⚙ Parámetros'!G20/(1+2^(-'⚙ Parámetros'!F20*(AA11-'⚙ Parámetros'!E20))),1)*AA11)/(35/100*MAX('⚙ Parámetros'!D20/(1+2^(-'⚙ Parámetros'!C20*(Y11-'⚙ Parámetros'!B20))),'⚙ Parámetros'!G20/(1+2^(-'⚙ Parámetros'!F20*(Y11-'⚙ Parámetros'!E20))),1)+35/100*MAX('⚙ Parámetros'!D20/(1+2^(-'⚙ Parámetros'!C20*(Z11-'⚙ Parámetros'!B20))),'⚙ Parámetros'!G20/(1+2^(-'⚙ Parámetros'!F20*(Z11-'⚙ Parámetros'!E20))),1)+30/100*MAX('⚙ Parámetros'!D20/(1+2^(-'⚙ Parámetros'!C20*(AA11-'⚙ Parámetros'!B20))),'⚙ Parámetros'!G20/(1+2^(-'⚙ Parámetros'!F20*(AA11-'⚙ Parámetros'!E20))),1)),0) -> 3.7272727 | AH11: =('⚙ Parámetros'!B5/100*AB11+'⚙ Parámetros'!B6/100*AC11+'⚙ Parámetros'!B7/100*AD11+'⚙ Parámetros'!B8/100*AE11+'⚙ Parámetros'!B9/100*AF11+'⚙ Parámetros'!B10/100*AG11) -> 6.2052716 | AI11: =MIN(1+MAX(0,TODAY()-DATE(2025,11,25))/365*'⚙ Parámetros'!B33,'⚙ Parámetros'!B34) -> 1.0817808 | AJ11: =IFERROR(MIN(AH11*AI11,10),0) -> 6.7127438 | AK11: =IF(AB11>='⚙ Parámetros'!B23,"⚑ AUTO-PRIOR.(D1≥8)",IF(AJ11>='⚙ Parámetros'!B23,"PRIORITARIO",IF(AJ11>='⚙ Parámetros'!B24,"ALTA PRIORIDAD",IF(AJ11>='⚙ Parámetros'!B25,"PRIORIDAD MEDIA",IF(AJ11>='⚙ Parámetros'!B26,"BAJA PRIORIDAD","DESCARTAR"))))) -> PRIORIDAD MEDIA | AL11: =IF(AB11>=8,"SÍ ⚑","—") -> — | AM11: 49 | AN11: =IF(AM11="","—",IF(AM11<'⚙ Parámetros'!B29,"🟢 Corto",IF(AM11<'⚙ Parámetros'!B30,"🟡 Medio","🔴 Largo"))) -> 🟡 Medio
A12: 8 | B12: MPG-LOG-041_01 PDA (REABASTECER/TRF) - Mejoras | C12: Supply chain y logística | D12: Marc Bometon | E12: 20/02/2026 | F12: 1 | G12: 7 | H12: 1 | I12: 1 | J12: 10 | K12: 7 | L12: 8 | M12: 9 | N12: 8 | O12: 8 | P12: 1 | Q12: 1 | R12: 6 | S12: 6 | T12: 5 | U12: 5 | V12: 5 | W12: 4 | X12: 5 | Y12: 5 | Z12: 2 | AA12: 5 | AB12: =IFERROR((30/100*MAX('⚙ Parámetros'!D15/(1+2^(-'⚙ Parámetros'!C15*(F12-'⚙ Parámetros'!B15))),'⚙ Parámetros'!G15/(1+2^(-'⚙ Parámetros'!F15*(F12-'⚙ Parámetros'!E15))),1)*F12+30/100*MAX('⚙ Parámetros'!D15/(1+2^(-'⚙ Parámetros'!C15*(G12-'⚙ Parámetros'!B15))),'⚙ Parámetros'!G15/(1+2^(-'⚙ Parámetros'!F15*(G12-'⚙ Parámetros'!E15))),1)*G12+20/100*MAX('⚙ Parámetros'!D15/(1+2^(-'⚙ Parámetros'!C15*(H12-'⚙ Parámetros'!B15))),'⚙ Parámetros'!G15/(1+2^(-'⚙ Parámetros'!F15*(H12-'⚙ Parámetros'!E15))),1)*H12+20/100*MAX('⚙ Parámetros'!D15/(1+2^(-'⚙ Parámetros'!C15*(I12-'⚙ Parámetros'!B15))),'⚙ Parámetros'!G15/(1+2^(-'⚙ Parámetros'!F15*(I12-'⚙ Parámetros'!E15))),1)*I12)/(30/100*MAX('⚙ Parámetros'!D15/(1+2^(-'⚙ Parámetros'!C15*(F12-'⚙ Parámetros'!B15))),'⚙ Parámetros'!G15/(1+2^(-'⚙ Parámetros'!F15*(F12-'⚙ Parámetros'!E15))),1)+30/100*MAX('⚙ Parámetros'!D15/(1+2^(-'⚙ Parámetros'!C15*(G12-'⚙ Parámetros'!B15))),'⚙ Parámetros'!G15/(1+2^(-'⚙ Parámetros'!F15*(G12-'⚙ Parámetros'!E15))),1)+20/100*MAX('⚙ Parámetros'!D15/(1+2^(-'⚙ Parámetros'!C15*(H12-'⚙ Parámetros'!B15))),'⚙ Parámetros'!G15/(1+2^(-'⚙ Parámetros'!F15*(H12-'⚙ Parámetros'!E15))),1)+20/100*MAX('⚙ Parámetros'!D15/(1+2^(-'⚙ Parámetros'!C15*(I12-'⚙ Parámetros'!B15))),'⚙ Parámetros'!G15/(1+2^(-'⚙ Parámetros'!F15*(I12-'⚙ Parámetros'!E15))),1)),0) -> 4.9512195 | AC12: =IFERROR((35/100*MAX('⚙ Parámetros'!D16/(1+2^(-'⚙ Parámetros'!C16*(J12-'⚙ Parámetros'!B16))),'⚙ Parámetros'!G16/(1+2^(-'⚙ Parámetros'!F16*(J12-'⚙ Parámetros'!E16))),1)*J12+25/100*MAX('⚙ Parámetros'!D16/(1+2^(-'⚙ Parámetros'!C16*(K12-'⚙ Parámetros'!B16))),'⚙ Parámetros'!G16/(1+2^(-'⚙ Parámetros'!F16*(K12-'⚙ Parámetros'!E16))),1)*K12+20/100*MAX('⚙ Parámetros'!D16/(1+2^(-'⚙ Parámetros'!C16*(L12-'⚙ Parámetros'!B16))),'⚙ Parámetros'!G16/(1+2^(-'⚙ Parámetros'!F16*(L12-'⚙ Parámetros'!E16))),1)*L12+20/100*MAX('⚙ Parámetros'!D16/(1+2^(-'⚙ Parámetros'!C16*(M12-'⚙ Parámetros'!B16))),'⚙ Parámetros'!G16/(1+2^(-'⚙ Parámetros'!F16*(M12-'⚙ Parámetros'!E16))),1)*M12)/(35/100*MAX('⚙ Parámetros'!D16/(1+2^(-'⚙ Parámetros'!C16*(J12-'⚙ Parámetros'!B16))),'⚙ Parámetros'!G16/(1+2^(-'⚙ Parámetros'!F16*(J12-'⚙ Parámetros'!E16))),1)+25/100*MAX('⚙ Parámetros'!D16/(1+2^(-'⚙ Parámetros'!C16*(K12-'⚙ Parámetros'!B16))),'⚙ Parámetros'!G16/(1+2^(-'⚙ Parámetros'!F16*(K12-'⚙ Parámetros'!E16))),1)+20/100*MAX('⚙ Parámetros'!D16/(1+2^(-'⚙ Parámetros'!C16*(L12-'⚙ Parámetros'!B16))),'⚙ Parámetros'!G16/(1+2^(-'⚙ Parámetros'!F16*(L12-'⚙ Parámetros'!E16))),1)+20/100*MAX('⚙ Parámetros'!D16/(1+2^(-'⚙ Parámetros'!C16*(M12-'⚙ Parámetros'!B16))),'⚙ Parámetros'!G16/(1+2^(-'⚙ Parámetros'!F16*(M12-'⚙ Parámetros'!E16))),1)),0) -> 9.1224798 | AD12: =IFERROR((30/100*MAX('⚙ Parámetros'!D17/(1+2^(-'⚙ Parámetros'!C17*(N12-'⚙ Parámetros'!B17))),'⚙ Parámetros'!G17/(1+2^(-'⚙ Parámetros'!F17*(N12-'⚙ Parámetros'!E17))),1)*N12+25/100*MAX('⚙ Parámetros'!D17/(1+2^(-'⚙ Parámetros'!C17*(O12-'⚙ Parámetros'!B17))),'⚙ Parámetros'!G17/(1+2^(-'⚙ Parámetros'!F17*(O12-'⚙ Parámetros'!E17))),1)*O12+25/100*MAX('⚙ Parámetros'!D17/(1+2^(-'⚙ Parámetros'!C17*(P12-'⚙ Parámetros'!B17))),'⚙ Parámetros'!G17/(1+2^(-'⚙ Parámetros'!F17*(P12-'⚙ Parámetros'!E17))),1)*P12+20/100*MAX('⚙ Parámetros'!D17/(1+2^(-'⚙ Parámetros'!C17*(Q12-'⚙ Parámetros'!B17))),'⚙ Parámetros'!G17/(1+2^(-'⚙ Parámetros'!F17*(Q12-'⚙ Parámetros'!E17))),1)*Q12)/(30/100*MAX('⚙ Parámetros'!D17/(1+2^(-'⚙ Parámetros'!C17*(N12-'⚙ Parámetros'!B17))),'⚙ Parámetros'!G17/(1+2^(-'⚙ Parámetros'!F17*(N12-'⚙ Parámetros'!E17))),1)+25/100*MAX('⚙ Parámetros'!D17/(1+2^(-'⚙ Parámetros'!C17*(O12-'⚙ Parámetros'!B17))),'⚙ Parámetros'!G17/(1+2^(-'⚙ Parámetros'!F17*(O12-'⚙ Parámetros'!E17))),1)+25/100*MAX('⚙ Parámetros'!D17/(1+2^(-'⚙ Parámetros'!C17*(P12-'⚙ Parámetros'!B17))),'⚙ Parámetros'!G17/(1+2^(-'⚙ Parámetros'!F17*(P12-'⚙ Parámetros'!E17))),1)+20/100*MAX('⚙ Parámetros'!D17/(1+2^(-'⚙ Parámetros'!C17*(Q12-'⚙ Parámetros'!B17))),'⚙ Parámetros'!G17/(1+2^(-'⚙ Parámetros'!F17*(Q12-'⚙ Parámetros'!E17))),1)),0) -> 6.8113208 | AE12: =IFERROR((30/100*MAX('⚙ Parámetros'!D18/(1+2^(-'⚙ Parámetros'!C18*(R12-'⚙ Parámetros'!B18))),'⚙ Parámetros'!G18/(1+2^(-'⚙ Parámetros'!F18*(R12-'⚙ Parámetros'!E18))),1)*R12+30/100*MAX('⚙ Parámetros'!D18/(1+2^(-'⚙ Parámetros'!C18*(S12-'⚙ Parámetros'!B18))),'⚙ Parámetros'!G18/(1+2^(-'⚙ Parámetros'!F18*(S12-'⚙ Parámetros'!E18))),1)*S12+20/100*MAX('⚙ Parámetros'!D18/(1+2^(-'⚙ Parámetros'!C18*(T12-'⚙ Parámetros'!B18))),'⚙ Parámetros'!G18/(1+2^(-'⚙ Parámetros'!F18*(T12-'⚙ Parámetros'!E18))),1)*T12+20/100*MAX('⚙ Parámetros'!D18/(1+2^(-'⚙ Parámetros'!C18*(U12-'⚙ Parámetros'!B18))),'⚙ Parámetros'!G18/(1+2^(-'⚙ Parámetros'!F18*(U12-'⚙ Parámetros'!E18))),1)*U12)/(30/100*MAX('⚙ Parámetros'!D18/(1+2^(-'⚙ Parámetros'!C18*(R12-'⚙ Parámetros'!B18))),'⚙ Parámetros'!G18/(1+2^(-'⚙ Parámetros'!F18*(R12-'⚙ Parámetros'!E18))),1)+30/100*MAX('⚙ Parámetros'!D18/(1+2^(-'⚙ Parámetros'!C18*(S12-'⚙ Parámetros'!B18))),'⚙ Parámetros'!G18/(1+2^(-'⚙ Parámetros'!F18*(S12-'⚙ Parámetros'!E18))),1)+20/100*MAX('⚙ Parámetros'!D18/(1+2^(-'⚙ Parámetros'!C18*(T12-'⚙ Parámetros'!B18))),'⚙ Parámetros'!G18/(1+2^(-'⚙ Parámetros'!F18*(T12-'⚙ Parámetros'!E18))),1)+20/100*MAX('⚙ Parámetros'!D18/(1+2^(-'⚙ Parámetros'!C18*(U12-'⚙ Parámetros'!B18))),'⚙ Parámetros'!G18/(1+2^(-'⚙ Parámetros'!F18*(U12-'⚙ Parámetros'!E18))),1)),0) -> 5.6428571 | AF12: =IFERROR((30/100*MAX('⚙ Parámetros'!D19/(1+2^(-'⚙ Parámetros'!C19*(V12-'⚙ Parámetros'!B19))),'⚙ Parámetros'!G19/(1+2^(-'⚙ Parámetros'!F19*(V12-'⚙ Parámetros'!E19))),1)*V12+35/100*MAX('⚙ Parámetros'!D19/(1+2^(-'⚙ Parámetros'!C19*(W12-'⚙ Parámetros'!B19))),'⚙ Parámetros'!G19/(1+2^(-'⚙ Parámetros'!F19*(W12-'⚙ Parámetros'!E19))),1)*W12+35/100*MAX('⚙ Parámetros'!D19/(1+2^(-'⚙ Parámetros'!C19*(X12-'⚙ Parámetros'!B19))),'⚙ Parámetros'!G19/(1+2^(-'⚙ Parámetros'!F19*(X12-'⚙ Parámetros'!E19))),1)*X12)/(30/100*MAX('⚙ Parámetros'!D19/(1+2^(-'⚙ Parámetros'!C19*(V12-'⚙ Parámetros'!B19))),'⚙ Parámetros'!G19/(1+2^(-'⚙ Parámetros'!F19*(V12-'⚙ Parámetros'!E19))),1)+35/100*MAX('⚙ Parámetros'!D19/(1+2^(-'⚙ Parámetros'!C19*(W12-'⚙ Parámetros'!B19))),'⚙ Parámetros'!G19/(1+2^(-'⚙ Parámetros'!F19*(W12-'⚙ Parámetros'!E19))),1)+35/100*MAX('⚙ Parámetros'!D19/(1+2^(-'⚙ Parámetros'!C19*(X12-'⚙ Parámetros'!B19))),'⚙ Parámetros'!G19/(1+2^(-'⚙ Parámetros'!F19*(X12-'⚙ Parámetros'!E19))),1)),0) -> 4.7123288 | AG12: =IFERROR((35/100*MAX('⚙ Parámetros'!D20/(1+2^(-'⚙ Parámetros'!C20*(Y12-'⚙ Parámetros'!B20))),'⚙ Parámetros'!G20/(1+2^(-'⚙ Parámetros'!F20*(Y12-'⚙ Parámetros'!E20))),1)*Y12+35/100*MAX('⚙ Parámetros'!D20/(1+2^(-'⚙ Parámetros'!C20*(Z12-'⚙ Parámetros'!B20))),'⚙ Parámetros'!G20/(1+2^(-'⚙ Parámetros'!F20*(Z12-'⚙ Parámetros'!E20))),1)*Z12+30/100*MAX('⚙ Parámetros'!D20/(1+2^(-'⚙ Parámetros'!C20*(AA12-'⚙ Parámetros'!B20))),'⚙ Parámetros'!G20/(1+2^(-'⚙ Parámetros'!F20*(AA12-'⚙ Parámetros'!E20))),1)*AA12)/(35/100*MAX('⚙ Parámetros'!D20/(1+2^(-'⚙ Parámetros'!C20*(Y12-'⚙ Parámetros'!B20))),'⚙ Parámetros'!G20/(1+2^(-'⚙ Parámetros'!F20*(Y12-'⚙ Parámetros'!E20))),1)+35/100*MAX('⚙ Parámetros'!D20/(1+2^(-'⚙ Parámetros'!C20*(Z12-'⚙ Parámetros'!B20))),'⚙ Parámetros'!G20/(1+2^(-'⚙ Parámetros'!F20*(Z12-'⚙ Parámetros'!E20))),1)+30/100*MAX('⚙ Parámetros'!D20/(1+2^(-'⚙ Parámetros'!C20*(AA12-'⚙ Parámetros'!B20))),'⚙ Parámetros'!G20/(1+2^(-'⚙ Parámetros'!F20*(AA12-'⚙ Parámetros'!E20))),1)),0) -> 4.1369863 | AH12: =('⚙ Parámetros'!B5/100*AB12+'⚙ Parámetros'!B6/100*AC12+'⚙ Parámetros'!B7/100*AD12+'⚙ Parámetros'!B8/100*AE12+'⚙ Parámetros'!B9/100*AF12+'⚙ Parámetros'!B10/100*AG12) -> 6.1514606 | AI12: =MIN(1+MAX(0,TODAY()-DATE(2026,2,20))/365*'⚙ Parámetros'!B33,'⚙ Parámetros'!B34) -> 1.0460274 | AJ12: =IFERROR(MIN(AH12*AI12,10),0) -> 6.4345963 | AK12: =IF(AB12>='⚙ Parámetros'!B23,"⚑ AUTO-PRIOR.(D1≥8)",IF(AJ12>='⚙ Parámetros'!B23,"PRIORITARIO",IF(AJ12>='⚙ Parámetros'!B24,"ALTA PRIORIDAD",IF(AJ12>='⚙ Parámetros'!B25,"PRIORIDAD MEDIA",IF(AJ12>='⚙ Parámetros'!B26,"BAJA PRIORIDAD","DESCARTAR"))))) -> PRIORIDAD MEDIA | AL12: =IF(AB12>=8,"SÍ ⚑","—") -> — | AM12: 29 | AN12: =IF(AM12="","—",IF(AM12<'⚙ Parámetros'!B29,"🟢 Corto",IF(AM12<'⚙ Parámetros'!B30,"🟡 Medio","🔴 Largo"))) -> 🟢 Corto
A13: 9 | B13: MPG-CAL-011 Informe caducidad materia prima | C13: Regulatorio y calidad | D13: Marc Bometon | E13: 13/09/2024 | F13: 6 | G13: 7 | H13: 1 | I13: 1 | J13: 1 | K13: 1 | L13: 8 | M13: 3 | N13: 1 | O13: 8 | P13: 6 | Q13: 8 | R13: 9 | S13: 9 | T13: 5 | U13: 5 | V13: 8 | W13: 6 | X13: 9 | Y13: 4 | Z13: 2 | AA13: 5 | AB13: =IFERROR((30/100*MAX('⚙ Parámetros'!D15/(1+2^(-'⚙ Parámetros'!C15*(F13-'⚙ Parámetros'!B15))),'⚙ Parámetros'!G15/(1+2^(-'⚙ Parámetros'!F15*(F13-'⚙ Parámetros'!E15))),1)*F13+30/100*MAX('⚙ Parámetros'!D15/(1+2^(-'⚙ Parámetros'!C15*(G13-'⚙ Parámetros'!B15))),'⚙ Parámetros'!G15/(1+2^(-'⚙ Parámetros'!F15*(G13-'⚙ Parámetros'!E15))),1)*G13+20/100*MAX('⚙ Parámetros'!D15/(1+2^(-'⚙ Parámetros'!C15*(H13-'⚙ Parámetros'!B15))),'⚙ Parámetros'!G15/(1+2^(-'⚙ Parámetros'!F15*(H13-'⚙ Parámetros'!E15))),1)*H13+20/100*MAX('⚙ Parámetros'!D15/(1+2^(-'⚙ Parámetros'!C15*(I13-'⚙ Parámetros'!B15))),'⚙ Parámetros'!G15/(1+2^(-'⚙ Parámetros'!F15*(I13-'⚙ Parámetros'!E15))),1)*I13)/(30/100*MAX('⚙ Parámetros'!D15/(1+2^(-'⚙ Parámetros'!C15*(F13-'⚙ Parámetros'!B15))),'⚙ Parámetros'!G15/(1+2^(-'⚙ Parámetros'!F15*(F13-'⚙ Parámetros'!E15))),1)+30/100*MAX('⚙ Parámetros'!D15/(1+2^(-'⚙ Parámetros'!C15*(G13-'⚙ Parámetros'!B15))),'⚙ Parámetros'!G15/(1+2^(-'⚙ Parámetros'!F15*(G13-'⚙ Parámetros'!E15))),1)+20/100*MAX('⚙ Parámetros'!D15/(1+2^(-'⚙ Parámetros'!C15*(H13-'⚙ Parámetros'!B15))),'⚙ Parámetros'!G15/(1+2^(-'⚙ Parámetros'!F15*(H13-'⚙ Parámetros'!E15))),1)+20/100*MAX('⚙ Parámetros'!D15/(1+2^(-'⚙ Parámetros'!C15*(I13-'⚙ Parámetros'!B15))),'⚙ Parámetros'!G15/(1+2^(-'⚙ Parámetros'!F15*(I13-'⚙ Parámetros'!E15))),1)),0) -> 5.7161572 | AC13: =IFERROR((35/100*MAX('⚙ Parámetros'!D16/(1+2^(-'⚙ Parámetros'!C16*(J13-'⚙ Parámetros'!B16))),'⚙ Parámetros'!G16/(1+2^(-'⚙ Parámetros'!F16*(J13-'⚙ Parámetros'!E16))),1)*J13+25/100*MAX('⚙ Parámetros'!D16/(1+2^(-'⚙ Parámetros'!C16*(K13-'⚙ Parámetros'!B16))),'⚙ Parámetros'!G16/(1+2^(-'⚙ Parámetros'!F16*(K13-'⚙ Parámetros'!E16))),1)*K13+20/100*MAX('⚙ Parámetros'!D16/(1+2^(-'⚙ Parámetros'!C16*(L13-'⚙ Parámetros'!B16))),'⚙ Parámetros'!G16/(1+2^(-'⚙ Parámetros'!F16*(L13-'⚙ Parámetros'!E16))),1)*L13+20/100*MAX('⚙ Parámetros'!D16/(1+2^(-'⚙ Parámetros'!C16*(M13-'⚙ Parámetros'!B16))),'⚙ Parámetros'!G16/(1+2^(-'⚙ Parámetros'!F16*(M13-'⚙ Parámetros'!E16))),1)*M13)/(35/100*MAX('⚙ Parámetros'!D16/(1+2^(-'⚙ Parámetros'!C16*(J13-'⚙ Parámetros'!B16))),'⚙ Parámetros'!G16/(1+2^(-'⚙ Parámetros'!F16*(J13-'⚙ Parámetros'!E16))),1)+25/100*MAX('⚙ Parámetros'!D16/(1+2^(-'⚙ Parámetros'!C16*(K13-'⚙ Parámetros'!B16))),'⚙ Parámetros'!G16/(1+2^(-'⚙ Parámetros'!F16*(K13-'⚙ Parámetros'!E16))),1)+20/100*MAX('⚙ Parámetros'!D16/(1+2^(-'⚙ Parámetros'!C16*(L13-'⚙ Parámetros'!B16))),'⚙ Parámetros'!G16/(1+2^(-'⚙ Parámetros'!F16*(L13-'⚙ Parámetros'!E16))),1)+20/100*MAX('⚙ Parámetros'!D16/(1+2^(-'⚙ Parámetros'!C16*(M13-'⚙ Parámetros'!B16))),'⚙ Parámetros'!G16/(1+2^(-'⚙ Parámetros'!F16*(M13-'⚙ Parámetros'!E16))),1)),0) -> 4.9411765 | AD13: =IFERROR((30/100*MAX('⚙ Parámetros'!D17/(1+2^(-'⚙ Parámetros'!C17*(N13-'⚙ Parámetros'!B17))),'⚙ Parámetros'!G17/(1+2^(-'⚙ Parámetros'!F17*(N13-'⚙ Parámetros'!E17))),1)*N13+25/100*MAX('⚙ Parámetros'!D17/(1+2^(-'⚙ Parámetros'!C17*(O13-'⚙ Parámetros'!B17))),'⚙ Parámetros'!G17/(1+2^(-'⚙ Parámetros'!F17*(O13-'⚙ Parámetros'!E17))),1)*O13+25/100*MAX('⚙ Parámetros'!D17/(1+2^(-'⚙ Parámetros'!C17*(P13-'⚙ Parámetros'!B17))),'⚙ Parámetros'!G17/(1+2^(-'⚙ Parámetros'!F17*(P13-'⚙ Parámetros'!E17))),1)*P13+20/100*MAX('⚙ Parámetros'!D17/(1+2^(-'⚙ Parámetros'!C17*(Q13-'⚙ Parámetros'!B17))),'⚙ Parámetros'!G17/(1+2^(-'⚙ Parámetros'!F17*(Q13-'⚙ Parámetros'!E17))),1)*Q13)/(30/100*MAX('⚙ Parámetros'!D17/(1+2^(-'⚙ Parámetros'!C17*(N13-'⚙ Parámetros'!B17))),'⚙ Parámetros'!G17/(1+2^(-'⚙ Parámetros'!F17*(N13-'⚙ Parámetros'!E17))),1)+25/100*MAX('⚙ Parámetros'!D17/(1+2^(-'⚙ Parámetros'!C17*(O13-'⚙ Parámetros'!B17))),'⚙ Parámetros'!G17/(1+2^(-'⚙ Parámetros'!F17*(O13-'⚙ Parámetros'!E17))),1)+25/100*MAX('⚙ Parámetros'!D17/(1+2^(-'⚙ Parámetros'!C17*(P13-'⚙ Parámetros'!B17))),'⚙ Parámetros'!G17/(1+2^(-'⚙ Parámetros'!F17*(P13-'⚙ Parámetros'!E17))),1)+20/100*MAX('⚙ Parámetros'!D17/(1+2^(-'⚙ Parámetros'!C17*(Q13-'⚙ Parámetros'!B17))),'⚙ Parámetros'!G17/(1+2^(-'⚙ Parámetros'!F17*(Q13-'⚙ Parámetros'!E17))),1)),0) -> 6.7777778 | AE13: =IFERROR((30/100*MAX('⚙ Parámetros'!D18/(1+2^(-'⚙ Parámetros'!C18*(R13-'⚙ Parámetros'!B18))),'⚙ Parámetros'!G18/(1+2^(-'⚙ Parámetros'!F18*(R13-'⚙ Parámetros'!E18))),1)*R13+30/100*MAX('⚙ Parámetros'!D18/(1+2^(-'⚙ Parámetros'!C18*(S13-'⚙ Parámetros'!B18))),'⚙ Parámetros'!G18/(1+2^(-'⚙ Parámetros'!F18*(S13-'⚙ Parámetros'!E18))),1)*S13+20/100*MAX('⚙ Parámetros'!D18/(1+2^(-'⚙ Parámetros'!C18*(T13-'⚙ Parámetros'!B18))),'⚙ Parámetros'!G18/(1+2^(-'⚙ Parámetros'!F18*(T13-'⚙ Parámetros'!E18))),1)*T13+20/100*MAX('⚙ Parámetros'!D18/(1+2^(-'⚙ Parámetros'!C18*(U13-'⚙ Parámetros'!B18))),'⚙ Parámetros'!G18/(1+2^(-'⚙ Parámetros'!F18*(U13-'⚙ Parámetros'!E18))),1)*U13)/(30/100*MAX('⚙ Parámetros'!D18/(1+2^(-'⚙ Parámetros'!C18*(R13-'⚙ Parámetros'!B18))),'⚙ Parámetros'!G18/(1+2^(-'⚙ Parámetros'!F18*(R13-'⚙ Parámetros'!E18))),1)+30/100*MAX('⚙ Parámetros'!D18/(1+2^(-'⚙ Parámetros'!C18*(S13-'⚙ Parámetros'!B18))),'⚙ Parámetros'!G18/(1+2^(-'⚙ Parámetros'!F18*(S13-'⚙ Parámetros'!E18))),1)+20/100*MAX('⚙ Parámetros'!D18/(1+2^(-'⚙ Parámetros'!C18*(T13-'⚙ Parámetros'!B18))),'⚙ Parámetros'!G18/(1+2^(-'⚙ Parámetros'!F18*(T13-'⚙ Parámetros'!E18))),1)+20/100*MAX('⚙ Parámetros'!D18/(1+2^(-'⚙ Parámetros'!C18*(U13-'⚙ Parámetros'!B18))),'⚙ Parámetros'!G18/(1+2^(-'⚙ Parámetros'!F18*(U13-'⚙ Parámetros'!E18))),1)),0) -> 8.180106 | AF13: =IFERROR((30/100*MAX('⚙ Parámetros'!D19/(1+2^(-'⚙ Parámetros'!C19*(V13-'⚙ Parámetros'!B19))),'⚙ Parámetros'!G19/(1+2^(-'⚙ Parámetros'!F19*(V13-'⚙ Parámetros'!E19))),1)*V13+35/100*MAX('⚙ Parámetros'!D19/(1+2^(-'⚙ Parámetros'!C19*(W13-'⚙ Parámetros'!B19))),'⚙ Parámetros'!G19/(1+2^(-'⚙ Parámetros'!F19*(W13-'⚙ Parámetros'!E19))),1)*W13+35/100*MAX('⚙ Parámetros'!D19/(1+2^(-'⚙ Parámetros'!C19*(X13-'⚙ Parámetros'!B19))),'⚙ Parámetros'!G19/(1+2^(-'⚙ Parámetros'!F19*(X13-'⚙ Parámetros'!E19))),1)*X13)/(30/100*MAX('⚙ Parámetros'!D19/(1+2^(-'⚙ Parámetros'!C19*(V13-'⚙ Parámetros'!B19))),'⚙ Parámetros'!G19/(1+2^(-'⚙ Parámetros'!F19*(V13-'⚙ Parámetros'!E19))),1)+35/100*MAX('⚙ Parámetros'!D19/(1+2^(-'⚙ Parámetros'!C19*(W13-'⚙ Parámetros'!B19))),'⚙ Parámetros'!G19/(1+2^(-'⚙ Parámetros'!F19*(W13-'⚙ Parámetros'!E19))),1)+35/100*MAX('⚙ Parámetros'!D19/(1+2^(-'⚙ Parámetros'!C19*(X13-'⚙ Parámetros'!B19))),'⚙ Parámetros'!G19/(1+2^(-'⚙ Parámetros'!F19*(X13-'⚙ Parámetros'!E19))),1)),0) -> 8.0351483 | AG13: =IFERROR((35/100*MAX('⚙ Parámetros'!D20/(1+2^(-'⚙ Parámetros'!C20*(Y13-'⚙ Parámetros'!B20))),'⚙ Parámetros'!G20/(1+2^(-'⚙ Parámetros'!F20*(Y13-'⚙ Parámetros'!E20))),1)*Y13+35/100*MAX('⚙ Parámetros'!D20/(1+2^(-'⚙ Parámetros'!C20*(Z13-'⚙ Parámetros'!B20))),'⚙ Parámetros'!G20/(1+2^(-'⚙ Parámetros'!F20*(Z13-'⚙ Parámetros'!E20))),1)*Z13+30/100*MAX('⚙ Parámetros'!D20/(1+2^(-'⚙ Parámetros'!C20*(AA13-'⚙ Parámetros'!B20))),'⚙ Parámetros'!G20/(1+2^(-'⚙ Parámetros'!F20*(AA13-'⚙ Parámetros'!E20))),1)*AA13)/(35/100*MAX('⚙ Parámetros'!D20/(1+2^(-'⚙ Parámetros'!C20*(Y13-'⚙ Parámetros'!B20))),'⚙ Parámetros'!G20/(1+2^(-'⚙ Parámetros'!F20*(Y13-'⚙ Parámetros'!E20))),1)+35/100*MAX('⚙ Parámetros'!D20/(1+2^(-'⚙ Parámetros'!C20*(Z13-'⚙ Parámetros'!B20))),'⚙ Parámetros'!G20/(1+2^(-'⚙ Parámetros'!F20*(Z13-'⚙ Parámetros'!E20))),1)+30/100*MAX('⚙ Parámetros'!D20/(1+2^(-'⚙ Parámetros'!C20*(AA13-'⚙ Parámetros'!B20))),'⚙ Parámetros'!G20/(1+2^(-'⚙ Parámetros'!F20*(AA13-'⚙ Parámetros'!E20))),1)),0) -> 3.7272727 | AH13: =('⚙ Parámetros'!B5/100*AB13+'⚙ Parámetros'!B6/100*AC13+'⚙ Parámetros'!B7/100*AD13+'⚙ Parámetros'!B8/100*AE13+'⚙ Parámetros'!B9/100*AF13+'⚙ Parámetros'!B10/100*AG13) -> 6.1419474 | AI13: =MIN(1+MAX(0,TODAY()-DATE(2024,9,13))/365*'⚙ Parámetros'!B33,'⚙ Parámetros'!B34) -> 1.25 | AJ13: =IFERROR(MIN(AH13*AI13,10),0) -> 7.6774342 | AK13: =IF(AB13>='⚙ Parámetros'!B23,"⚑ AUTO-PRIOR.(D1≥8)",IF(AJ13>='⚙ Parámetros'!B23,"PRIORITARIO",IF(AJ13>='⚙ Parámetros'!B24,"ALTA PRIORIDAD",IF(AJ13>='⚙ Parámetros'!B25,"PRIORIDAD MEDIA",IF(AJ13>='⚙ Parámetros'!B26,"BAJA PRIORIDAD","DESCARTAR"))))) -> ALTA PRIORIDAD | AL13: =IF(AB13>=8,"SÍ ⚑","—") -> — | AM13: 42 | AN13: =IF(AM13="","—",IF(AM13<'⚙ Parámetros'!B29,"🟢 Corto",IF(AM13<'⚙ Parámetros'!B30,"🟡 Medio","🔴 Largo"))) -> 🟡 Medio
A14: 10 | B14: MPG-LOG-066 Liberación de cargas y confirmación. Superbotón | C14: Supply chain y logística | D14: Joan Valverde | E14: 14/05/2026 | F14: 9 | G14: 1 | H14: 1 | I14: 9 | J14: 1 | K14: 8 | L14: 1 | M14: 3 | N14: 1 | O14: 8 | P14: 1 | Q14: 1 | R14: 5 | S14: 5 | T14: 5 | U14: 5 | V14: 5 | W14: 6 | X14: 3 | Y14: 4 | Z14: 2 | AA14: 5 | AB14: =IFERROR((30/100*MAX('⚙ Parámetros'!D15/(1+2^(-'⚙ Parámetros'!C15*(F14-'⚙ Parámetros'!B15))),'⚙ Parámetros'!G15/(1+2^(-'⚙ Parámetros'!F15*(F14-'⚙ Parámetros'!E15))),1)*F14+30/100*MAX('⚙ Parámetros'!D15/(1+2^(-'⚙ Parámetros'!C15*(G14-'⚙ Parámetros'!B15))),'⚙ Parámetros'!G15/(1+2^(-'⚙ Parámetros'!F15*(G14-'⚙ Parámetros'!E15))),1)*G14+20/100*MAX('⚙ Parámetros'!D15/(1+2^(-'⚙ Parámetros'!C15*(H14-'⚙ Parámetros'!B15))),'⚙ Parámetros'!G15/(1+2^(-'⚙ Parámetros'!F15*(H14-'⚙ Parámetros'!E15))),1)*H14+20/100*MAX('⚙ Parámetros'!D15/(1+2^(-'⚙ Parámetros'!C15*(I14-'⚙ Parámetros'!B15))),'⚙ Parámetros'!G15/(1+2^(-'⚙ Parámetros'!F15*(I14-'⚙ Parámetros'!E15))),1)*I14)/(30/100*MAX('⚙ Parámetros'!D15/(1+2^(-'⚙ Parámetros'!C15*(F14-'⚙ Parámetros'!B15))),'⚙ Parámetros'!G15/(1+2^(-'⚙ Parámetros'!F15*(F14-'⚙ Parámetros'!E15))),1)+30/100*MAX('⚙ Parámetros'!D15/(1+2^(-'⚙ Parámetros'!C15*(G14-'⚙ Parámetros'!B15))),'⚙ Parámetros'!G15/(1+2^(-'⚙ Parámetros'!F15*(G14-'⚙ Parámetros'!E15))),1)+20/100*MAX('⚙ Parámetros'!D15/(1+2^(-'⚙ Parámetros'!C15*(H14-'⚙ Parámetros'!B15))),'⚙ Parámetros'!G15/(1+2^(-'⚙ Parámetros'!F15*(H14-'⚙ Parámetros'!E15))),1)+20/100*MAX('⚙ Parámetros'!D15/(1+2^(-'⚙ Parámetros'!C15*(I14-'⚙ Parámetros'!B15))),'⚙ Parámetros'!G15/(1+2^(-'⚙ Parámetros'!F15*(I14-'⚙ Parámetros'!E15))),1)),0) -> 8.1552795 | AC14: =IFERROR((35/100*MAX('⚙ Parámetros'!D16/(1+2^(-'⚙ Parámetros'!C16*(J14-'⚙ Parámetros'!B16))),'⚙ Parámetros'!G16/(1+2^(-'⚙ Parámetros'!F16*(J14-'⚙ Parámetros'!E16))),1)*J14+25/100*MAX('⚙ Parámetros'!D16/(1+2^(-'⚙ Parámetros'!C16*(K14-'⚙ Parámetros'!B16))),'⚙ Parámetros'!G16/(1+2^(-'⚙ Parámetros'!F16*(K14-'⚙ Parámetros'!E16))),1)*K14+20/100*MAX('⚙ Parámetros'!D16/(1+2^(-'⚙ Parámetros'!C16*(L14-'⚙ Parámetros'!B16))),'⚙ Parámetros'!G16/(1+2^(-'⚙ Parámetros'!F16*(L14-'⚙ Parámetros'!E16))),1)*L14+20/100*MAX('⚙ Parámetros'!D16/(1+2^(-'⚙ Parámetros'!C16*(M14-'⚙ Parámetros'!B16))),'⚙ Parámetros'!G16/(1+2^(-'⚙ Parámetros'!F16*(M14-'⚙ Parámetros'!E16))),1)*M14)/(35/100*MAX('⚙ Parámetros'!D16/(1+2^(-'⚙ Parámetros'!C16*(J14-'⚙ Parámetros'!B16))),'⚙ Parámetros'!G16/(1+2^(-'⚙ Parámetros'!F16*(J14-'⚙ Parámetros'!E16))),1)+25/100*MAX('⚙ Parámetros'!D16/(1+2^(-'⚙ Parámetros'!C16*(K14-'⚙ Parámetros'!B16))),'⚙ Parámetros'!G16/(1+2^(-'⚙ Parámetros'!F16*(K14-'⚙ Parámetros'!E16))),1)+20/100*MAX('⚙ Parámetros'!D16/(1+2^(-'⚙ Parámetros'!C16*(L14-'⚙ Parámetros'!B16))),'⚙ Parámetros'!G16/(1+2^(-'⚙ Parámetros'!F16*(L14-'⚙ Parámetros'!E16))),1)+20/100*MAX('⚙ Parámetros'!D16/(1+2^(-'⚙ Parámetros'!C16*(M14-'⚙ Parámetros'!B16))),'⚙ Parámetros'!G16/(1+2^(-'⚙ Parámetros'!F16*(M14-'⚙ Parámetros'!E16))),1)),0) -> 5.4133333 | AD14: =IFERROR((30/100*MAX('⚙ Parámetros'!D17/(1+2^(-'⚙ Parámetros'!C17*(N14-'⚙ Parámetros'!B17))),'⚙ Parámetros'!G17/(1+2^(-'⚙ Parámetros'!F17*(N14-'⚙ Parámetros'!E17))),1)*N14+25/100*MAX('⚙ Parámetros'!D17/(1+2^(-'⚙ Parámetros'!C17*(O14-'⚙ Parámetros'!B17))),'⚙ Parámetros'!G17/(1+2^(-'⚙ Parámetros'!F17*(O14-'⚙ Parámetros'!E17))),1)*O14+25/100*MAX('⚙ Parámetros'!D17/(1+2^(-'⚙ Parámetros'!C17*(P14-'⚙ Parámetros'!B17))),'⚙ Parámetros'!G17/(1+2^(-'⚙ Parámetros'!F17*(P14-'⚙ Parámetros'!E17))),1)*P14+20/100*MAX('⚙ Parámetros'!D17/(1+2^(-'⚙ Parámetros'!C17*(Q14-'⚙ Parámetros'!B17))),'⚙ Parámetros'!G17/(1+2^(-'⚙ Parámetros'!F17*(Q14-'⚙ Parámetros'!E17))),1)*Q14)/(30/100*MAX('⚙ Parámetros'!D17/(1+2^(-'⚙ Parámetros'!C17*(N14-'⚙ Parámetros'!B17))),'⚙ Parámetros'!G17/(1+2^(-'⚙ Parámetros'!F17*(N14-'⚙ Parámetros'!E17))),1)+25/100*MAX('⚙ Parámetros'!D17/(1+2^(-'⚙ Parámetros'!C17*(O14-'⚙ Parámetros'!B17))),'⚙ Parámetros'!G17/(1+2^(-'⚙ Parámetros'!F17*(O14-'⚙ Parámetros'!E17))),1)+25/100*MAX('⚙ Parámetros'!D17/(1+2^(-'⚙ Parámetros'!C17*(P14-'⚙ Parámetros'!B17))),'⚙ Parámetros'!G17/(1+2^(-'⚙ Parámetros'!F17*(P14-'⚙ Parámetros'!E17))),1)+20/100*MAX('⚙ Parámetros'!D17/(1+2^(-'⚙ Parámetros'!C17*(Q14-'⚙ Parámetros'!B17))),'⚙ Parámetros'!G17/(1+2^(-'⚙ Parámetros'!F17*(Q14-'⚙ Parámetros'!E17))),1)),0) -> 5 | AE14: =IFERROR((30/100*MAX('⚙ Parámetros'!D18/(1+2^(-'⚙ Parámetros'!C18*(R14-'⚙ Parámetros'!B18))),'⚙ Parámetros'!G18/(1+2^(-'⚙ Parámetros'!F18*(R14-'⚙ Parámetros'!E18))),1)*R14+30/100*MAX('⚙ Parámetros'!D18/(1+2^(-'⚙ Parámetros'!C18*(S14-'⚙ Parámetros'!B18))),'⚙ Parámetros'!G18/(1+2^(-'⚙ Parámetros'!F18*(S14-'⚙ Parámetros'!E18))),1)*S14+20/100*MAX('⚙ Parámetros'!D18/(1+2^(-'⚙ Parámetros'!C18*(T14-'⚙ Parámetros'!B18))),'⚙ Parámetros'!G18/(1+2^(-'⚙ Parámetros'!F18*(T14-'⚙ Parámetros'!E18))),1)*T14+20/100*MAX('⚙ Parámetros'!D18/(1+2^(-'⚙ Parámetros'!C18*(U14-'⚙ Parámetros'!B18))),'⚙ Parámetros'!G18/(1+2^(-'⚙ Parámetros'!F18*(U14-'⚙ Parámetros'!E18))),1)*U14)/(30/100*MAX('⚙ Parámetros'!D18/(1+2^(-'⚙ Parámetros'!C18*(R14-'⚙ Parámetros'!B18))),'⚙ Parámetros'!G18/(1+2^(-'⚙ Parámetros'!F18*(R14-'⚙ Parámetros'!E18))),1)+30/100*MAX('⚙ Parámetros'!D18/(1+2^(-'⚙ Parámetros'!C18*(S14-'⚙ Parámetros'!B18))),'⚙ Parámetros'!G18/(1+2^(-'⚙ Parámetros'!F18*(S14-'⚙ Parámetros'!E18))),1)+20/100*MAX('⚙ Parámetros'!D18/(1+2^(-'⚙ Parámetros'!C18*(T14-'⚙ Parámetros'!B18))),'⚙ Parámetros'!G18/(1+2^(-'⚙ Parámetros'!F18*(T14-'⚙ Parámetros'!E18))),1)+20/100*MAX('⚙ Parámetros'!D18/(1+2^(-'⚙ Parámetros'!C18*(U14-'⚙ Parámetros'!B18))),'⚙ Parámetros'!G18/(1+2^(-'⚙ Parámetros'!F18*(U14-'⚙ Parámetros'!E18))),1)),0) -> 5 | AF14: =IFERROR((30/100*MAX('⚙ Parámetros'!D19/(1+2^(-'⚙ Parámetros'!C19*(V14-'⚙ Parámetros'!B19))),'⚙ Parámetros'!G19/(1+2^(-'⚙ Parámetros'!F19*(V14-'⚙ Parámetros'!E19))),1)*V14+35/100*MAX('⚙ Parámetros'!D19/(1+2^(-'⚙ Parámetros'!C19*(W14-'⚙ Parámetros'!B19))),'⚙ Parámetros'!G19/(1+2^(-'⚙ Parámetros'!F19*(W14-'⚙ Parámetros'!E19))),1)*W14+35/100*MAX('⚙ Parámetros'!D19/(1+2^(-'⚙ Parámetros'!C19*(X14-'⚙ Parámetros'!B19))),'⚙ Parámetros'!G19/(1+2^(-'⚙ Parámetros'!F19*(X14-'⚙ Parámetros'!E19))),1)*X14)/(30/100*MAX('⚙ Parámetros'!D19/(1+2^(-'⚙ Parámetros'!C19*(V14-'⚙ Parámetros'!B19))),'⚙ Parámetros'!G19/(1+2^(-'⚙ Parámetros'!F19*(V14-'⚙ Parámetros'!E19))),1)+35/100*MAX('⚙ Parámetros'!D19/(1+2^(-'⚙ Parámetros'!C19*(W14-'⚙ Parámetros'!B19))),'⚙ Parámetros'!G19/(1+2^(-'⚙ Parámetros'!F19*(W14-'⚙ Parámetros'!E19))),1)+35/100*MAX('⚙ Parámetros'!D19/(1+2^(-'⚙ Parámetros'!C19*(X14-'⚙ Parámetros'!B19))),'⚙ Parámetros'!G19/(1+2^(-'⚙ Parámetros'!F19*(X14-'⚙ Parámetros'!E19))),1)),0) -> 5.0782123 | AG14: =IFERROR((35/100*MAX('⚙ Parámetros'!D20/(1+2^(-'⚙ Parámetros'!C20*(Y14-'⚙ Parámetros'!B20))),'⚙ Parámetros'!G20/(1+2^(-'⚙ Parámetros'!F20*(Y14-'⚙ Parámetros'!E20))),1)*Y14+35/100*MAX('⚙ Parámetros'!D20/(1+2^(-'⚙ Parámetros'!C20*(Z14-'⚙ Parámetros'!B20))),'⚙ Parámetros'!G20/(1+2^(-'⚙ Parámetros'!F20*(Z14-'⚙ Parámetros'!E20))),1)*Z14+30/100*MAX('⚙ Parámetros'!D20/(1+2^(-'⚙ Parámetros'!C20*(AA14-'⚙ Parámetros'!B20))),'⚙ Parámetros'!G20/(1+2^(-'⚙ Parámetros'!F20*(AA14-'⚙ Parámetros'!E20))),1)*AA14)/(35/100*MAX('⚙ Parámetros'!D20/(1+2^(-'⚙ Parámetros'!C20*(Y14-'⚙ Parámetros'!B20))),'⚙ Parámetros'!G20/(1+2^(-'⚙ Parámetros'!F20*(Y14-'⚙ Parámetros'!E20))),1)+35/100*MAX('⚙ Parámetros'!D20/(1+2^(-'⚙ Parámetros'!C20*(Z14-'⚙ Parámetros'!B20))),'⚙ Parámetros'!G20/(1+2^(-'⚙ Parámetros'!F20*(Z14-'⚙ Parámetros'!E20))),1)+30/100*MAX('⚙ Parámetros'!D20/(1+2^(-'⚙ Parámetros'!C20*(AA14-'⚙ Parámetros'!B20))),'⚙ Parámetros'!G20/(1+2^(-'⚙ Parámetros'!F20*(AA14-'⚙ Parámetros'!E20))),1)),0) -> 3.7272727 | AH14: =('⚙ Parámetros'!B5/100*AB14+'⚙ Parámetros'!B6/100*AC14+'⚙ Parámetros'!B7/100*AD14+'⚙ Parámetros'!B8/100*AE14+'⚙ Parámetros'!B9/100*AF14+'⚙ Parámetros'!B10/100*AG14) -> 5.9352536 | AI14: =MIN(1+MAX(0,TODAY()-DATE(2026,5,14))/365*'⚙ Parámetros'!B33,'⚙ Parámetros'!B34) -> 1.0119178 | AJ14: =IFERROR(MIN(AH14*AI14,10),0) -> 6.0059888 | AK14: =IF(AB14>='⚙ Parámetros'!B23,"⚑ AUTO-PRIOR.(D1≥8)",IF(AJ14>='⚙ Parámetros'!B23,"PRIORITARIO",IF(AJ14>='⚙ Parámetros'!B24,"ALTA PRIORIDAD",IF(AJ14>='⚙ Parámetros'!B25,"PRIORIDAD MEDIA",IF(AJ14>='⚙ Parámetros'!B26,"BAJA PRIORIDAD","DESCARTAR"))))) -> PRIORIDAD MEDIA | AL14: =IF(AB14>=8,"SÍ ⚑","—") -> SÍ ⚑ | AM14: 35 | AN14: =IF(AM14="","—",IF(AM14<'⚙ Parámetros'!B29,"🟢 Corto",IF(AM14<'⚙ Parámetros'!B30,"🟡 Medio","🔴 Largo"))) -> 🟡 Medio
A15: 11 | B15: MPG-VTA-006_02_02 Endpoint getCustomers | C15: Ventas y marketing | D15: Marc Bometon | E15: 25/03/2026 | F15: 1 | G15: 1 | H15: 5 | I15: 1 | J15: 10 | K15: 9 | L15: 8 | M15: 9 | N15: 8 | O15: 1 | P15: 7 | Q15: 6 | R15: 9 | S15: 9 | T15: 5 | U15: 5 | V15: 7 | W15: 6 | X15: 5 | Y15: 5 | Z15: 2 | AA15: 8 | AB15: =IFERROR((30/100*MAX('⚙ Parámetros'!D15/(1+2^(-'⚙ Parámetros'!C15*(F15-'⚙ Parámetros'!B15))),'⚙ Parámetros'!G15/(1+2^(-'⚙ Parámetros'!F15*(F15-'⚙ Parámetros'!E15))),1)*F15+30/100*MAX('⚙ Parámetros'!D15/(1+2^(-'⚙ Parámetros'!C15*(G15-'⚙ Parámetros'!B15))),'⚙ Parámetros'!G15/(1+2^(-'⚙ Parámetros'!F15*(G15-'⚙ Parámetros'!E15))),1)*G15+20/100*MAX('⚙ Parámetros'!D15/(1+2^(-'⚙ Parámetros'!C15*(H15-'⚙ Parámetros'!B15))),'⚙ Parámetros'!G15/(1+2^(-'⚙ Parámetros'!F15*(H15-'⚙ Parámetros'!E15))),1)*H15+20/100*MAX('⚙ Parámetros'!D15/(1+2^(-'⚙ Parámetros'!C15*(I15-'⚙ Parámetros'!B15))),'⚙ Parámetros'!G15/(1+2^(-'⚙ Parámetros'!F15*(I15-'⚙ Parámetros'!E15))),1)*I15)/(30/100*MAX('⚙ Parámetros'!D15/(1+2^(-'⚙ Parámetros'!C15*(F15-'⚙ Parámetros'!B15))),'⚙ Parámetros'!G15/(1+2^(-'⚙ Parámetros'!F15*(F15-'⚙ Parámetros'!E15))),1)+30/100*MAX('⚙ Parámetros'!D15/(1+2^(-'⚙ Parámetros'!C15*(G15-'⚙ Parámetros'!B15))),'⚙ Parámetros'!G15/(1+2^(-'⚙ Parámetros'!F15*(G15-'⚙ Parámetros'!E15))),1)+20/100*MAX('⚙ Parámetros'!D15/(1+2^(-'⚙ Parámetros'!C15*(H15-'⚙ Parámetros'!B15))),'⚙ Parámetros'!G15/(1+2^(-'⚙ Parámetros'!F15*(H15-'⚙ Parámetros'!E15))),1)+20/100*MAX('⚙ Parámetros'!D15/(1+2^(-'⚙ Parámetros'!C15*(I15-'⚙ Parámetros'!B15))),'⚙ Parámetros'!G15/(1+2^(-'⚙ Parámetros'!F15*(I15-'⚙ Parámetros'!E15))),1)),0) -> 2.1428571 | AC15: =IFERROR((35/100*MAX('⚙ Parámetros'!D16/(1+2^(-'⚙ Parámetros'!C16*(J15-'⚙ Parámetros'!B16))),'⚙ Parámetros'!G16/(1+2^(-'⚙ Parámetros'!F16*(J15-'⚙ Parámetros'!E16))),1)*J15+25/100*MAX('⚙ Parámetros'!D16/(1+2^(-'⚙ Parámetros'!C16*(K15-'⚙ Parámetros'!B16))),'⚙ Parámetros'!G16/(1+2^(-'⚙ Parámetros'!F16*(K15-'⚙ Parámetros'!E16))),1)*K15+20/100*MAX('⚙ Parámetros'!D16/(1+2^(-'⚙ Parámetros'!C16*(L15-'⚙ Parámetros'!B16))),'⚙ Parámetros'!G16/(1+2^(-'⚙ Parámetros'!F16*(L15-'⚙ Parámetros'!E16))),1)*L15+20/100*MAX('⚙ Parámetros'!D16/(1+2^(-'⚙ Parámetros'!C16*(M15-'⚙ Parámetros'!B16))),'⚙ Parámetros'!G16/(1+2^(-'⚙ Parámetros'!F16*(M15-'⚙ Parámetros'!E16))),1)*M15)/(35/100*MAX('⚙ Parámetros'!D16/(1+2^(-'⚙ Parámetros'!C16*(J15-'⚙ Parámetros'!B16))),'⚙ Parámetros'!G16/(1+2^(-'⚙ Parámetros'!F16*(J15-'⚙ Parámetros'!E16))),1)+25/100*MAX('⚙ Parámetros'!D16/(1+2^(-'⚙ Parámetros'!C16*(K15-'⚙ Parámetros'!B16))),'⚙ Parámetros'!G16/(1+2^(-'⚙ Parámetros'!F16*(K15-'⚙ Parámetros'!E16))),1)+20/100*MAX('⚙ Parámetros'!D16/(1+2^(-'⚙ Parámetros'!C16*(L15-'⚙ Parámetros'!B16))),'⚙ Parámetros'!G16/(1+2^(-'⚙ Parámetros'!F16*(L15-'⚙ Parámetros'!E16))),1)+20/100*MAX('⚙ Parámetros'!D16/(1+2^(-'⚙ Parámetros'!C16*(M15-'⚙ Parámetros'!B16))),'⚙ Parámetros'!G16/(1+2^(-'⚙ Parámetros'!F16*(M15-'⚙ Parámetros'!E16))),1)),0) -> 9.290611 | AD15: =IFERROR((30/100*MAX('⚙ Parámetros'!D17/(1+2^(-'⚙ Parámetros'!C17*(N15-'⚙ Parámetros'!B17))),'⚙ Parámetros'!G17/(1+2^(-'⚙ Parámetros'!F17*(N15-'⚙ Parámetros'!E17))),1)*N15+25/100*MAX('⚙ Parámetros'!D17/(1+2^(-'⚙ Parámetros'!C17*(O15-'⚙ Parámetros'!B17))),'⚙ Parámetros'!G17/(1+2^(-'⚙ Parámetros'!F17*(O15-'⚙ Parámetros'!E17))),1)*O15+25/100*MAX('⚙ Parámetros'!D17/(1+2^(-'⚙ Parámetros'!C17*(P15-'⚙ Parámetros'!B17))),'⚙ Parámetros'!G17/(1+2^(-'⚙ Parámetros'!F17*(P15-'⚙ Parámetros'!E17))),1)*P15+20/100*MAX('⚙ Parámetros'!D17/(1+2^(-'⚙ Parámetros'!C17*(Q15-'⚙ Parámetros'!B17))),'⚙ Parámetros'!G17/(1+2^(-'⚙ Parámetros'!F17*(Q15-'⚙ Parámetros'!E17))),1)*Q15)/(30/100*MAX('⚙ Parámetros'!D17/(1+2^(-'⚙ Parámetros'!C17*(N15-'⚙ Parámetros'!B17))),'⚙ Parámetros'!G17/(1+2^(-'⚙ Parámetros'!F17*(N15-'⚙ Parámetros'!E17))),1)+25/100*MAX('⚙ Parámetros'!D17/(1+2^(-'⚙ Parámetros'!C17*(O15-'⚙ Parámetros'!B17))),'⚙ Parámetros'!G17/(1+2^(-'⚙ Parámetros'!F17*(O15-'⚙ Parámetros'!E17))),1)+25/100*MAX('⚙ Parámetros'!D17/(1+2^(-'⚙ Parámetros'!C17*(P15-'⚙ Parámetros'!B17))),'⚙ Parámetros'!G17/(1+2^(-'⚙ Parámetros'!F17*(P15-'⚙ Parámetros'!E17))),1)+20/100*MAX('⚙ Parámetros'!D17/(1+2^(-'⚙ Parámetros'!C17*(Q15-'⚙ Parámetros'!B17))),'⚙ Parámetros'!G17/(1+2^(-'⚙ Parámetros'!F17*(Q15-'⚙ Parámetros'!E17))),1)),0) -> 6.6996149 | AE15: =IFERROR((30/100*MAX('⚙ Parámetros'!D18/(1+2^(-'⚙ Parámetros'!C18*(R15-'⚙ Parámetros'!B18))),'⚙ Parámetros'!G18/(1+2^(-'⚙ Parámetros'!F18*(R15-'⚙ Parámetros'!E18))),1)*R15+30/100*MAX('⚙ Parámetros'!D18/(1+2^(-'⚙ Parámetros'!C18*(S15-'⚙ Parámetros'!B18))),'⚙ Parámetros'!G18/(1+2^(-'⚙ Parámetros'!F18*(S15-'⚙ Parámetros'!E18))),1)*S15+20/100*MAX('⚙ Parámetros'!D18/(1+2^(-'⚙ Parámetros'!C18*(T15-'⚙ Parámetros'!B18))),'⚙ Parámetros'!G18/(1+2^(-'⚙ Parámetros'!F18*(T15-'⚙ Parámetros'!E18))),1)*T15+20/100*MAX('⚙ Parámetros'!D18/(1+2^(-'⚙ Parámetros'!C18*(U15-'⚙ Parámetros'!B18))),'⚙ Parámetros'!G18/(1+2^(-'⚙ Parámetros'!F18*(U15-'⚙ Parámetros'!E18))),1)*U15)/(30/100*MAX('⚙ Parámetros'!D18/(1+2^(-'⚙ Parámetros'!C18*(R15-'⚙ Parámetros'!B18))),'⚙ Parámetros'!G18/(1+2^(-'⚙ Parámetros'!F18*(R15-'⚙ Parámetros'!E18))),1)+30/100*MAX('⚙ Parámetros'!D18/(1+2^(-'⚙ Parámetros'!C18*(S15-'⚙ Parámetros'!B18))),'⚙ Parámetros'!G18/(1+2^(-'⚙ Parámetros'!F18*(S15-'⚙ Parámetros'!E18))),1)+20/100*MAX('⚙ Parámetros'!D18/(1+2^(-'⚙ Parámetros'!C18*(T15-'⚙ Parámetros'!B18))),'⚙ Parámetros'!G18/(1+2^(-'⚙ Parámetros'!F18*(T15-'⚙ Parámetros'!E18))),1)+20/100*MAX('⚙ Parámetros'!D18/(1+2^(-'⚙ Parámetros'!C18*(U15-'⚙ Parámetros'!B18))),'⚙ Parámetros'!G18/(1+2^(-'⚙ Parámetros'!F18*(U15-'⚙ Parámetros'!E18))),1)),0) -> 8.180106 | AF15: =IFERROR((30/100*MAX('⚙ Parámetros'!D19/(1+2^(-'⚙ Parámetros'!C19*(V15-'⚙ Parámetros'!B19))),'⚙ Parámetros'!G19/(1+2^(-'⚙ Parámetros'!F19*(V15-'⚙ Parámetros'!E19))),1)*V15+35/100*MAX('⚙ Parámetros'!D19/(1+2^(-'⚙ Parámetros'!C19*(W15-'⚙ Parámetros'!B19))),'⚙ Parámetros'!G19/(1+2^(-'⚙ Parámetros'!F19*(W15-'⚙ Parámetros'!E19))),1)*W15+35/100*MAX('⚙ Parámetros'!D19/(1+2^(-'⚙ Parámetros'!C19*(X15-'⚙ Parámetros'!B19))),'⚙ Parámetros'!G19/(1+2^(-'⚙ Parámetros'!F19*(X15-'⚙ Parámetros'!E19))),1)*X15)/(30/100*MAX('⚙ Parámetros'!D19/(1+2^(-'⚙ Parámetros'!C19*(V15-'⚙ Parámetros'!B19))),'⚙ Parámetros'!G19/(1+2^(-'⚙ Parámetros'!F19*(V15-'⚙ Parámetros'!E19))),1)+35/100*MAX('⚙ Parámetros'!D19/(1+2^(-'⚙ Parámetros'!C19*(W15-'⚙ Parámetros'!B19))),'⚙ Parámetros'!G19/(1+2^(-'⚙ Parámetros'!F19*(W15-'⚙ Parámetros'!E19))),1)+35/100*MAX('⚙ Parámetros'!D19/(1+2^(-'⚙ Parámetros'!C19*(X15-'⚙ Parámetros'!B19))),'⚙ Parámetros'!G19/(1+2^(-'⚙ Parámetros'!F19*(X15-'⚙ Parámetros'!E19))),1)),0) -> 6.042735 | AG15: =IFERROR((35/100*MAX('⚙ Parámetros'!D20/(1+2^(-'⚙ Parámetros'!C20*(Y15-'⚙ Parámetros'!B20))),'⚙ Parámetros'!G20/(1+2^(-'⚙ Parámetros'!F20*(Y15-'⚙ Parámetros'!E20))),1)*Y15+35/100*MAX('⚙ Parámetros'!D20/(1+2^(-'⚙ Parámetros'!C20*(Z15-'⚙ Parámetros'!B20))),'⚙ Parámetros'!G20/(1+2^(-'⚙ Parámetros'!F20*(Z15-'⚙ Parámetros'!E20))),1)*Z15+30/100*MAX('⚙ Parámetros'!D20/(1+2^(-'⚙ Parámetros'!C20*(AA15-'⚙ Parámetros'!B20))),'⚙ Parámetros'!G20/(1+2^(-'⚙ Parámetros'!F20*(AA15-'⚙ Parámetros'!E20))),1)*AA15)/(35/100*MAX('⚙ Parámetros'!D20/(1+2^(-'⚙ Parámetros'!C20*(Y15-'⚙ Parámetros'!B20))),'⚙ Parámetros'!G20/(1+2^(-'⚙ Parámetros'!F20*(Y15-'⚙ Parámetros'!E20))),1)+35/100*MAX('⚙ Parámetros'!D20/(1+2^(-'⚙ Parámetros'!C20*(Z15-'⚙ Parámetros'!B20))),'⚙ Parámetros'!G20/(1+2^(-'⚙ Parámetros'!F20*(Z15-'⚙ Parámetros'!E20))),1)+30/100*MAX('⚙ Parámetros'!D20/(1+2^(-'⚙ Parámetros'!C20*(AA15-'⚙ Parámetros'!B20))),'⚙ Parámetros'!G20/(1+2^(-'⚙ Parámetros'!F20*(AA15-'⚙ Parámetros'!E20))),1)),0) -> 5.961165 | AH15: =('⚙ Parámetros'!B5/100*AB15+'⚙ Parámetros'!B6/100*AC15+'⚙ Parámetros'!B7/100*AD15+'⚙ Parámetros'!B8/100*AE15+'⚙ Parámetros'!B9/100*AF15+'⚙ Parámetros'!B10/100*AG15) -> 5.9036818 | AI15: =MIN(1+MAX(0,TODAY()-DATE(2026,3,25))/365*'⚙ Parámetros'!B33,'⚙ Parámetros'!B34) -> 1.0324658 | AJ15: =IFERROR(MIN(AH15*AI15,10),0) -> 6.0953492 | AK15: =IF(AB15>='⚙ Parámetros'!B23,"⚑ AUTO-PRIOR.(D1≥8)",IF(AJ15>='⚙ Parámetros'!B23,"PRIORITARIO",IF(AJ15>='⚙ Parámetros'!B24,"ALTA PRIORIDAD",IF(AJ15>='⚙ Parámetros'!B25,"PRIORIDAD MEDIA",IF(AJ15>='⚙ Parámetros'!B26,"BAJA PRIORIDAD","DESCARTAR"))))) -> PRIORIDAD MEDIA | AL15: =IF(AB15>=8,"SÍ ⚑","—") -> — | AM15: 38 | AN15: =IF(AM15="","—",IF(AM15<'⚙ Parámetros'!B29,"🟢 Corto",IF(AM15<'⚙ Parámetros'!B30,"🟡 Medio","🔴 Largo"))) -> 🟡 Medio
A16: 12 | B16: MPG-VTA-024 Tarjeta regalo ecom | C16: Ventas y marketing | D16: Judit Sanchez | E16: 15/07/2025 | F16: 1 | G16: 1 | H16: 5 | I16: 1 | J16: 10 | K16: 9 | L16: 8 | M16: 9 | N16: 8 | O16: 1 | P16: 7 | Q16: 6 | R16: 9 | S16: 9 | T16: 5 | U16: 5 | V16: 7 | W16: 6 | X16: 5 | Y16: 5 | Z16: 2 | AA16: 8 | AB16: =IFERROR((30/100*MAX('⚙ Parámetros'!D15/(1+2^(-'⚙ Parámetros'!C15*(F16-'⚙ Parámetros'!B15))),'⚙ Parámetros'!G15/(1+2^(-'⚙ Parámetros'!F15*(F16-'⚙ Parámetros'!E15))),1)*F16+30/100*MAX('⚙ Parámetros'!D15/(1+2^(-'⚙ Parámetros'!C15*(G16-'⚙ Parámetros'!B15))),'⚙ Parámetros'!G15/(1+2^(-'⚙ Parámetros'!F15*(G16-'⚙ Parámetros'!E15))),1)*G16+20/100*MAX('⚙ Parámetros'!D15/(1+2^(-'⚙ Parámetros'!C15*(H16-'⚙ Parámetros'!B15))),'⚙ Parámetros'!G15/(1+2^(-'⚙ Parámetros'!F15*(H16-'⚙ Parámetros'!E15))),1)*H16+20/100*MAX('⚙ Parámetros'!D15/(1+2^(-'⚙ Parámetros'!C15*(I16-'⚙ Parámetros'!B15))),'⚙ Parámetros'!G15/(1+2^(-'⚙ Parámetros'!F15*(I16-'⚙ Parámetros'!E15))),1)*I16)/(30/100*MAX('⚙ Parámetros'!D15/(1+2^(-'⚙ Parámetros'!C15*(F16-'⚙ Parámetros'!B15))),'⚙ Parámetros'!G15/(1+2^(-'⚙ Parámetros'!F15*(F16-'⚙ Parámetros'!E15))),1)+30/100*MAX('⚙ Parámetros'!D15/(1+2^(-'⚙ Parámetros'!C15*(G16-'⚙ Parámetros'!B15))),'⚙ Parámetros'!G15/(1+2^(-'⚙ Parámetros'!F15*(G16-'⚙ Parámetros'!E15))),1)+20/100*MAX('⚙ Parámetros'!D15/(1+2^(-'⚙ Parámetros'!C15*(H16-'⚙ Parámetros'!B15))),'⚙ Parámetros'!G15/(1+2^(-'⚙ Parámetros'!F15*(H16-'⚙ Parámetros'!E15))),1)+20/100*MAX('⚙ Parámetros'!D15/(1+2^(-'⚙ Parámetros'!C15*(I16-'⚙ Parámetros'!B15))),'⚙ Parámetros'!G15/(1+2^(-'⚙ Parámetros'!F15*(I16-'⚙ Parámetros'!E15))),1)),0) -> 2.1428571 | AC16: =IFERROR((35/100*MAX('⚙ Parámetros'!D16/(1+2^(-'⚙ Parámetros'!C16*(J16-'⚙ Parámetros'!B16))),'⚙ Parámetros'!G16/(1+2^(-'⚙ Parámetros'!F16*(J16-'⚙ Parámetros'!E16))),1)*J16+25/100*MAX('⚙ Parámetros'!D16/(1+2^(-'⚙ Parámetros'!C16*(K16-'⚙ Parámetros'!B16))),'⚙ Parámetros'!G16/(1+2^(-'⚙ Parámetros'!F16*(K16-'⚙ Parámetros'!E16))),1)*K16+20/100*MAX('⚙ Parámetros'!D16/(1+2^(-'⚙ Parámetros'!C16*(L16-'⚙ Parámetros'!B16))),'⚙ Parámetros'!G16/(1+2^(-'⚙ Parámetros'!F16*(L16-'⚙ Parámetros'!E16))),1)*L16+20/100*MAX('⚙ Parámetros'!D16/(1+2^(-'⚙ Parámetros'!C16*(M16-'⚙ Parámetros'!B16))),'⚙ Parámetros'!G16/(1+2^(-'⚙ Parámetros'!F16*(M16-'⚙ Parámetros'!E16))),1)*M16)/(35/100*MAX('⚙ Parámetros'!D16/(1+2^(-'⚙ Parámetros'!C16*(J16-'⚙ Parámetros'!B16))),'⚙ Parámetros'!G16/(1+2^(-'⚙ Parámetros'!F16*(J16-'⚙ Parámetros'!E16))),1)+25/100*MAX('⚙ Parámetros'!D16/(1+2^(-'⚙ Parámetros'!C16*(K16-'⚙ Parámetros'!B16))),'⚙ Parámetros'!G16/(1+2^(-'⚙ Parámetros'!F16*(K16-'⚙ Parámetros'!E16))),1)+20/100*MAX('⚙ Parámetros'!D16/(1+2^(-'⚙ Parámetros'!C16*(L16-'⚙ Parámetros'!B16))),'⚙ Parámetros'!G16/(1+2^(-'⚙ Parámetros'!F16*(L16-'⚙ Parámetros'!E16))),1)+20/100*MAX('⚙ Parámetros'!D16/(1+2^(-'⚙ Parámetros'!C16*(M16-'⚙ Parámetros'!B16))),'⚙ Parámetros'!G16/(1+2^(-'⚙ Parámetros'!F16*(M16-'⚙ Parámetros'!E16))),1)),0) -> 9.290611 | AD16: =IFERROR((30/100*MAX('⚙ Parámetros'!D17/(1+2^(-'⚙ Parámetros'!C17*(N16-'⚙ Parámetros'!B17))),'⚙ Parámetros'!G17/(1+2^(-'⚙ Parámetros'!F17*(N16-'⚙ Parámetros'!E17))),1)*N16+25/100*MAX('⚙ Parámetros'!D17/(1+2^(-'⚙ Parámetros'!C17*(O16-'⚙ Parámetros'!B17))),'⚙ Parámetros'!G17/(1+2^(-'⚙ Parámetros'!F17*(O16-'⚙ Parámetros'!E17))),1)*O16+25/100*MAX('⚙ Parámetros'!D17/(1+2^(-'⚙ Parámetros'!C17*(P16-'⚙ Parámetros'!B17))),'⚙ Parámetros'!G17/(1+2^(-'⚙ Parámetros'!F17*(P16-'⚙ Parámetros'!E17))),1)*P16+20/100*MAX('⚙ Parámetros'!D17/(1+2^(-'⚙ Parámetros'!C17*(Q16-'⚙ Parámetros'!B17))),'⚙ Parámetros'!G17/(1+2^(-'⚙ Parámetros'!F17*(Q16-'⚙ Parámetros'!E17))),1)*Q16)/(30/100*MAX('⚙ Parámetros'!D17/(1+2^(-'⚙ Parámetros'!C17*(N16-'⚙ Parámetros'!B17))),'⚙ Parámetros'!G17/(1+2^(-'⚙ Parámetros'!F17*(N16-'⚙ Parámetros'!E17))),1)+25/100*MAX('⚙ Parámetros'!D17/(1+2^(-'⚙ Parámetros'!C17*(O16-'⚙ Parámetros'!B17))),'⚙ Parámetros'!G17/(1+2^(-'⚙ Parámetros'!F17*(O16-'⚙ Parámetros'!E17))),1)+25/100*MAX('⚙ Parámetros'!D17/(1+2^(-'⚙ Parámetros'!C17*(P16-'⚙ Parámetros'!B17))),'⚙ Parámetros'!G17/(1+2^(-'⚙ Parámetros'!F17*(P16-'⚙ Parámetros'!E17))),1)+20/100*MAX('⚙ Parámetros'!D17/(1+2^(-'⚙ Parámetros'!C17*(Q16-'⚙ Parámetros'!B17))),'⚙ Parámetros'!G17/(1+2^(-'⚙ Parámetros'!F17*(Q16-'⚙ Parámetros'!E17))),1)),0) -> 6.6996149 | AE16: =IFERROR((30/100*MAX('⚙ Parámetros'!D18/(1+2^(-'⚙ Parámetros'!C18*(R16-'⚙ Parámetros'!B18))),'⚙ Parámetros'!G18/(1+2^(-'⚙ Parámetros'!F18*(R16-'⚙ Parámetros'!E18))),1)*R16+30/100*MAX('⚙ Parámetros'!D18/(1+2^(-'⚙ Parámetros'!C18*(S16-'⚙ Parámetros'!B18))),'⚙ Parámetros'!G18/(1+2^(-'⚙ Parámetros'!F18*(S16-'⚙ Parámetros'!E18))),1)*S16+20/100*MAX('⚙ Parámetros'!D18/(1+2^(-'⚙ Parámetros'!C18*(T16-'⚙ Parámetros'!B18))),'⚙ Parámetros'!G18/(1+2^(-'⚙ Parámetros'!F18*(T16-'⚙ Parámetros'!E18))),1)*T16+20/100*MAX('⚙ Parámetros'!D18/(1+2^(-'⚙ Parámetros'!C18*(U16-'⚙ Parámetros'!B18))),'⚙ Parámetros'!G18/(1+2^(-'⚙ Parámetros'!F18*(U16-'⚙ Parámetros'!E18))),1)*U16)/(30/100*MAX('⚙ Parámetros'!D18/(1+2^(-'⚙ Parámetros'!C18*(R16-'⚙ Parámetros'!B18))),'⚙ Parámetros'!G18/(1+2^(-'⚙ Parámetros'!F18*(R16-'⚙ Parámetros'!E18))),1)+30/100*MAX('⚙ Parámetros'!D18/(1+2^(-'⚙ Parámetros'!C18*(S16-'⚙ Parámetros'!B18))),'⚙ Parámetros'!G18/(1+2^(-'⚙ Parámetros'!F18*(S16-'⚙ Parámetros'!E18))),1)+20/100*MAX('⚙ Parámetros'!D18/(1+2^(-'⚙ Parámetros'!C18*(T16-'⚙ Parámetros'!B18))),'⚙ Parámetros'!G18/(1+2^(-'⚙ Parámetros'!F18*(T16-'⚙ Parámetros'!E18))),1)+20/100*MAX('⚙ Parámetros'!D18/(1+2^(-'⚙ Parámetros'!C18*(U16-'⚙ Parámetros'!B18))),'⚙ Parámetros'!G18/(1+2^(-'⚙ Parámetros'!F18*(U16-'⚙ Parámetros'!E18))),1)),0) -> 8.180106 | AF16: =IFERROR((30/100*MAX('⚙ Parámetros'!D19/(1+2^(-'⚙ Parámetros'!C19*(V16-'⚙ Parámetros'!B19))),'⚙ Parámetros'!G19/(1+2^(-'⚙ Parámetros'!F19*(V16-'⚙ Parámetros'!E19))),1)*V16+35/100*MAX('⚙ Parámetros'!D19/(1+2^(-'⚙ Parámetros'!C19*(W16-'⚙ Parámetros'!B19))),'⚙ Parámetros'!G19/(1+2^(-'⚙ Parámetros'!F19*(W16-'⚙ Parámetros'!E19))),1)*W16+35/100*MAX('⚙ Parámetros'!D19/(1+2^(-'⚙ Parámetros'!C19*(X16-'⚙ Parámetros'!B19))),'⚙ Parámetros'!G19/(1+2^(-'⚙ Parámetros'!F19*(X16-'⚙ Parámetros'!E19))),1)*X16)/(30/100*MAX('⚙ Parámetros'!D19/(1+2^(-'⚙ Parámetros'!C19*(V16-'⚙ Parámetros'!B19))),'⚙ Parámetros'!G19/(1+2^(-'⚙ Parámetros'!F19*(V16-'⚙ Parámetros'!E19))),1)+35/100*MAX('⚙ Parámetros'!D19/(1+2^(-'⚙ Parámetros'!C19*(W16-'⚙ Parámetros'!B19))),'⚙ Parámetros'!G19/(1+2^(-'⚙ Parámetros'!F19*(W16-'⚙ Parámetros'!E19))),1)+35/100*MAX('⚙ Parámetros'!D19/(1+2^(-'⚙ Parámetros'!C19*(X16-'⚙ Parámetros'!B19))),'⚙ Parámetros'!G19/(1+2^(-'⚙ Parámetros'!F19*(X16-'⚙ Parámetros'!E19))),1)),0) -> 6.042735 | AG16: =IFERROR((35/100*MAX('⚙ Parámetros'!D20/(1+2^(-'⚙ Parámetros'!C20*(Y16-'⚙ Parámetros'!B20))),'⚙ Parámetros'!G20/(1+2^(-'⚙ Parámetros'!F20*(Y16-'⚙ Parámetros'!E20))),1)*Y16+35/100*MAX('⚙ Parámetros'!D20/(1+2^(-'⚙ Parámetros'!C20*(Z16-'⚙ Parámetros'!B20))),'⚙ Parámetros'!G20/(1+2^(-'⚙ Parámetros'!F20*(Z16-'⚙ Parámetros'!E20))),1)*Z16+30/100*MAX('⚙ Parámetros'!D20/(1+2^(-'⚙ Parámetros'!C20*(AA16-'⚙ Parámetros'!B20))),'⚙ Parámetros'!G20/(1+2^(-'⚙ Parámetros'!F20*(AA16-'⚙ Parámetros'!E20))),1)*AA16)/(35/100*MAX('⚙ Parámetros'!D20/(1+2^(-'⚙ Parámetros'!C20*(Y16-'⚙ Parámetros'!B20))),'⚙ Parámetros'!G20/(1+2^(-'⚙ Parámetros'!F20*(Y16-'⚙ Parámetros'!E20))),1)+35/100*MAX('⚙ Parámetros'!D20/(1+2^(-'⚙ Parámetros'!C20*(Z16-'⚙ Parámetros'!B20))),'⚙ Parámetros'!G20/(1+2^(-'⚙ Parámetros'!F20*(Z16-'⚙ Parámetros'!E20))),1)+30/100*MAX('⚙ Parámetros'!D20/(1+2^(-'⚙ Parámetros'!C20*(AA16-'⚙ Parámetros'!B20))),'⚙ Parámetros'!G20/(1+2^(-'⚙ Parámetros'!F20*(AA16-'⚙ Parámetros'!E20))),1)),0) -> 5.961165 | AH16: =('⚙ Parámetros'!B5/100*AB16+'⚙ Parámetros'!B6/100*AC16+'⚙ Parámetros'!B7/100*AD16+'⚙ Parámetros'!B8/100*AE16+'⚙ Parámetros'!B9/100*AF16+'⚙ Parámetros'!B10/100*AG16) -> 5.9036818 | AI16: =MIN(1+MAX(0,TODAY()-DATE(2025,7,15))/365*'⚙ Parámetros'!B33,'⚙ Parámetros'!B34) -> 1.1364384 | AJ16: =IFERROR(MIN(AH16*AI16,10),0) -> 6.7091704 | AK16: =IF(AB16>='⚙ Parámetros'!B23,"⚑ AUTO-PRIOR.(D1≥8)",IF(AJ16>='⚙ Parámetros'!B23,"PRIORITARIO",IF(AJ16>='⚙ Parámetros'!B24,"ALTA PRIORIDAD",IF(AJ16>='⚙ Parámetros'!B25,"PRIORIDAD MEDIA",IF(AJ16>='⚙ Parámetros'!B26,"BAJA PRIORIDAD","DESCARTAR"))))) -> PRIORIDAD MEDIA | AL16: =IF(AB16>=8,"SÍ ⚑","—") -> — | AM16: 30 | AN16: =IF(AM16="","—",IF(AM16<'⚙ Parámetros'!B29,"🟢 Corto",IF(AM16<'⚙ Parámetros'!B30,"🟡 Medio","🔴 Largo"))) -> 🟡 Medio
A17: 13 | B17: MPG-CAL-002_01 Cambio para muestreo Military estándar | C17: Regulatorio y calidad | D17: Silvia Martin | E17: 14/01/2026 | F17: 8 | G17: 5 | H17: 1 | I17: 8 | J17: 1 | K17: 1 | L17: 8 | M17: 3 | N17: 7 | O17: 1 | P17: 1 | Q17: 8 | R17: 5 | S17: 5 | T17: 5 | U17: 5 | V17: 5 | W17: 6 | X17: 6 | Y17: 4 | Z17: 2 | AA17: 5 | AB17: =IFERROR((30/100*MAX('⚙ Parámetros'!D15/(1+2^(-'⚙ Parámetros'!C15*(F17-'⚙ Parámetros'!B15))),'⚙ Parámetros'!G15/(1+2^(-'⚙ Parámetros'!F15*(F17-'⚙ Parámetros'!E15))),1)*F17+30/100*MAX('⚙ Parámetros'!D15/(1+2^(-'⚙ Parámetros'!C15*(G17-'⚙ Parámetros'!B15))),'⚙ Parámetros'!G15/(1+2^(-'⚙ Parámetros'!F15*(G17-'⚙ Parámetros'!E15))),1)*G17+20/100*MAX('⚙ Parámetros'!D15/(1+2^(-'⚙ Parámetros'!C15*(H17-'⚙ Parámetros'!B15))),'⚙ Parámetros'!G15/(1+2^(-'⚙ Parámetros'!F15*(H17-'⚙ Parámetros'!E15))),1)*H17+20/100*MAX('⚙ Parámetros'!D15/(1+2^(-'⚙ Parámetros'!C15*(I17-'⚙ Parámetros'!B15))),'⚙ Parámetros'!G15/(1+2^(-'⚙ Parámetros'!F15*(I17-'⚙ Parámetros'!E15))),1)*I17)/(30/100*MAX('⚙ Parámetros'!D15/(1+2^(-'⚙ Parámetros'!C15*(F17-'⚙ Parámetros'!B15))),'⚙ Parámetros'!G15/(1+2^(-'⚙ Parámetros'!F15*(F17-'⚙ Parámetros'!E15))),1)+30/100*MAX('⚙ Parámetros'!D15/(1+2^(-'⚙ Parámetros'!C15*(G17-'⚙ Parámetros'!B15))),'⚙ Parámetros'!G15/(1+2^(-'⚙ Parámetros'!F15*(G17-'⚙ Parámetros'!E15))),1)+20/100*MAX('⚙ Parámetros'!D15/(1+2^(-'⚙ Parámetros'!C15*(H17-'⚙ Parámetros'!B15))),'⚙ Parámetros'!G15/(1+2^(-'⚙ Parámetros'!F15*(H17-'⚙ Parámetros'!E15))),1)+20/100*MAX('⚙ Parámetros'!D15/(1+2^(-'⚙ Parámetros'!C15*(I17-'⚙ Parámetros'!B15))),'⚙ Parámetros'!G15/(1+2^(-'⚙ Parámetros'!F15*(I17-'⚙ Parámetros'!E15))),1)),0) -> 7.3364486 | AC17: =IFERROR((35/100*MAX('⚙ Parámetros'!D16/(1+2^(-'⚙ Parámetros'!C16*(J17-'⚙ Parámetros'!B16))),'⚙ Parámetros'!G16/(1+2^(-'⚙ Parámetros'!F16*(J17-'⚙ Parámetros'!E16))),1)*J17+25/100*MAX('⚙ Parámetros'!D16/(1+2^(-'⚙ Parámetros'!C16*(K17-'⚙ Parámetros'!B16))),'⚙ Parámetros'!G16/(1+2^(-'⚙ Parámetros'!F16*(K17-'⚙ Parámetros'!E16))),1)*K17+20/100*MAX('⚙ Parámetros'!D16/(1+2^(-'⚙ Parámetros'!C16*(L17-'⚙ Parámetros'!B16))),'⚙ Parámetros'!G16/(1+2^(-'⚙ Parámetros'!F16*(L17-'⚙ Parámetros'!E16))),1)*L17+20/100*MAX('⚙ Parámetros'!D16/(1+2^(-'⚙ Parámetros'!C16*(M17-'⚙ Parámetros'!B16))),'⚙ Parámetros'!G16/(1+2^(-'⚙ Parámetros'!F16*(M17-'⚙ Parámetros'!E16))),1)*M17)/(35/100*MAX('⚙ Parámetros'!D16/(1+2^(-'⚙ Parámetros'!C16*(J17-'⚙ Parámetros'!B16))),'⚙ Parámetros'!G16/(1+2^(-'⚙ Parámetros'!F16*(J17-'⚙ Parámetros'!E16))),1)+25/100*MAX('⚙ Parámetros'!D16/(1+2^(-'⚙ Parámetros'!C16*(K17-'⚙ Parámetros'!B16))),'⚙ Parámetros'!G16/(1+2^(-'⚙ Parámetros'!F16*(K17-'⚙ Parámetros'!E16))),1)+20/100*MAX('⚙ Parámetros'!D16/(1+2^(-'⚙ Parámetros'!C16*(L17-'⚙ Parámetros'!B16))),'⚙ Parámetros'!G16/(1+2^(-'⚙ Parámetros'!F16*(L17-'⚙ Parámetros'!E16))),1)+20/100*MAX('⚙ Parámetros'!D16/(1+2^(-'⚙ Parámetros'!C16*(M17-'⚙ Parámetros'!B16))),'⚙ Parámetros'!G16/(1+2^(-'⚙ Parámetros'!F16*(M17-'⚙ Parámetros'!E16))),1)),0) -> 4.9411765 | AD17: =IFERROR((30/100*MAX('⚙ Parámetros'!D17/(1+2^(-'⚙ Parámetros'!C17*(N17-'⚙ Parámetros'!B17))),'⚙ Parámetros'!G17/(1+2^(-'⚙ Parámetros'!F17*(N17-'⚙ Parámetros'!E17))),1)*N17+25/100*MAX('⚙ Parámetros'!D17/(1+2^(-'⚙ Parámetros'!C17*(O17-'⚙ Parámetros'!B17))),'⚙ Parámetros'!G17/(1+2^(-'⚙ Parámetros'!F17*(O17-'⚙ Parámetros'!E17))),1)*O17+25/100*MAX('⚙ Parámetros'!D17/(1+2^(-'⚙ Parámetros'!C17*(P17-'⚙ Parámetros'!B17))),'⚙ Parámetros'!G17/(1+2^(-'⚙ Parámetros'!F17*(P17-'⚙ Parámetros'!E17))),1)*P17+20/100*MAX('⚙ Parámetros'!D17/(1+2^(-'⚙ Parámetros'!C17*(Q17-'⚙ Parámetros'!B17))),'⚙ Parámetros'!G17/(1+2^(-'⚙ Parámetros'!F17*(Q17-'⚙ Parámetros'!E17))),1)*Q17)/(30/100*MAX('⚙ Parámetros'!D17/(1+2^(-'⚙ Parámetros'!C17*(N17-'⚙ Parámetros'!B17))),'⚙ Parámetros'!G17/(1+2^(-'⚙ Parámetros'!F17*(N17-'⚙ Parámetros'!E17))),1)+25/100*MAX('⚙ Parámetros'!D17/(1+2^(-'⚙ Parámetros'!C17*(O17-'⚙ Parámetros'!B17))),'⚙ Parámetros'!G17/(1+2^(-'⚙ Parámetros'!F17*(O17-'⚙ Parámetros'!E17))),1)+25/100*MAX('⚙ Parámetros'!D17/(1+2^(-'⚙ Parámetros'!C17*(P17-'⚙ Parámetros'!B17))),'⚙ Parámetros'!G17/(1+2^(-'⚙ Parámetros'!F17*(P17-'⚙ Parámetros'!E17))),1)+20/100*MAX('⚙ Parámetros'!D17/(1+2^(-'⚙ Parámetros'!C17*(Q17-'⚙ Parámetros'!B17))),'⚙ Parámetros'!G17/(1+2^(-'⚙ Parámetros'!F17*(Q17-'⚙ Parámetros'!E17))),1)),0) -> 5.952381 | AE17: =IFERROR((30/100*MAX('⚙ Parámetros'!D18/(1+2^(-'⚙ Parámetros'!C18*(R17-'⚙ Parámetros'!B18))),'⚙ Parámetros'!G18/(1+2^(-'⚙ Parámetros'!F18*(R17-'⚙ Parámetros'!E18))),1)*R17+30/100*MAX('⚙ Parámetros'!D18/(1+2^(-'⚙ Parámetros'!C18*(S17-'⚙ Parámetros'!B18))),'⚙ Parámetros'!G18/(1+2^(-'⚙ Parámetros'!F18*(S17-'⚙ Parámetros'!E18))),1)*S17+20/100*MAX('⚙ Parámetros'!D18/(1+2^(-'⚙ Parámetros'!C18*(T17-'⚙ Parámetros'!B18))),'⚙ Parámetros'!G18/(1+2^(-'⚙ Parámetros'!F18*(T17-'⚙ Parámetros'!E18))),1)*T17+20/100*MAX('⚙ Parámetros'!D18/(1+2^(-'⚙ Parámetros'!C18*(U17-'⚙ Parámetros'!B18))),'⚙ Parámetros'!G18/(1+2^(-'⚙ Parámetros'!F18*(U17-'⚙ Parámetros'!E18))),1)*U17)/(30/100*MAX('⚙ Parámetros'!D18/(1+2^(-'⚙ Parámetros'!C18*(R17-'⚙ Parámetros'!B18))),'⚙ Parámetros'!G18/(1+2^(-'⚙ Parámetros'!F18*(R17-'⚙ Parámetros'!E18))),1)+30/100*MAX('⚙ Parámetros'!D18/(1+2^(-'⚙ Parámetros'!C18*(S17-'⚙ Parámetros'!B18))),'⚙ Parámetros'!G18/(1+2^(-'⚙ Parámetros'!F18*(S17-'⚙ Parámetros'!E18))),1)+20/100*MAX('⚙ Parámetros'!D18/(1+2^(-'⚙ Parámetros'!C18*(T17-'⚙ Parámetros'!B18))),'⚙ Parámetros'!G18/(1+2^(-'⚙ Parámetros'!F18*(T17-'⚙ Parámetros'!E18))),1)+20/100*MAX('⚙ Parámetros'!D18/(1+2^(-'⚙ Parámetros'!C18*(U17-'⚙ Parámetros'!B18))),'⚙ Parámetros'!G18/(1+2^(-'⚙ Parámetros'!F18*(U17-'⚙ Parámetros'!E18))),1)),0) -> 5 | AF17: =IFERROR((30/100*MAX('⚙ Parámetros'!D19/(1+2^(-'⚙ Parámetros'!C19*(V17-'⚙ Parámetros'!B19))),'⚙ Parámetros'!G19/(1+2^(-'⚙ Parámetros'!F19*(V17-'⚙ Parámetros'!E19))),1)*V17+35/100*MAX('⚙ Parámetros'!D19/(1+2^(-'⚙ Parámetros'!C19*(W17-'⚙ Parámetros'!B19))),'⚙ Parámetros'!G19/(1+2^(-'⚙ Parámetros'!F19*(W17-'⚙ Parámetros'!E19))),1)*W17+35/100*MAX('⚙ Parámetros'!D19/(1+2^(-'⚙ Parámetros'!C19*(X17-'⚙ Parámetros'!B19))),'⚙ Parámetros'!G19/(1+2^(-'⚙ Parámetros'!F19*(X17-'⚙ Parámetros'!E19))),1)*X17)/(30/100*MAX('⚙ Parámetros'!D19/(1+2^(-'⚙ Parámetros'!C19*(V17-'⚙ Parámetros'!B19))),'⚙ Parámetros'!G19/(1+2^(-'⚙ Parámetros'!F19*(V17-'⚙ Parámetros'!E19))),1)+35/100*MAX('⚙ Parámetros'!D19/(1+2^(-'⚙ Parámetros'!C19*(W17-'⚙ Parámetros'!B19))),'⚙ Parámetros'!G19/(1+2^(-'⚙ Parámetros'!F19*(W17-'⚙ Parámetros'!E19))),1)+35/100*MAX('⚙ Parámetros'!D19/(1+2^(-'⚙ Parámetros'!C19*(X17-'⚙ Parámetros'!B19))),'⚙ Parámetros'!G19/(1+2^(-'⚙ Parámetros'!F19*(X17-'⚙ Parámetros'!E19))),1)),0) -> 5.7368421 | AG17: =IFERROR((35/100*MAX('⚙ Parámetros'!D20/(1+2^(-'⚙ Parámetros'!C20*(Y17-'⚙ Parámetros'!B20))),'⚙ Parámetros'!G20/(1+2^(-'⚙ Parámetros'!F20*(Y17-'⚙ Parámetros'!E20))),1)*Y17+35/100*MAX('⚙ Parámetros'!D20/(1+2^(-'⚙ Parámetros'!C20*(Z17-'⚙ Parámetros'!B20))),'⚙ Parámetros'!G20/(1+2^(-'⚙ Parámetros'!F20*(Z17-'⚙ Parámetros'!E20))),1)*Z17+30/100*MAX('⚙ Parámetros'!D20/(1+2^(-'⚙ Parámetros'!C20*(AA17-'⚙ Parámetros'!B20))),'⚙ Parámetros'!G20/(1+2^(-'⚙ Parámetros'!F20*(AA17-'⚙ Parámetros'!E20))),1)*AA17)/(35/100*MAX('⚙ Parámetros'!D20/(1+2^(-'⚙ Parámetros'!C20*(Y17-'⚙ Parámetros'!B20))),'⚙ Parámetros'!G20/(1+2^(-'⚙ Parámetros'!F20*(Y17-'⚙ Parámetros'!E20))),1)+35/100*MAX('⚙ Parámetros'!D20/(1+2^(-'⚙ Parámetros'!C20*(Z17-'⚙ Parámetros'!B20))),'⚙ Parámetros'!G20/(1+2^(-'⚙ Parámetros'!F20*(Z17-'⚙ Parámetros'!E20))),1)+30/100*MAX('⚙ Parámetros'!D20/(1+2^(-'⚙ Parámetros'!C20*(AA17-'⚙ Parámetros'!B20))),'⚙ Parámetros'!G20/(1+2^(-'⚙ Parámetros'!F20*(AA17-'⚙ Parámetros'!E20))),1)),0) -> 3.7272727 | AH17: =('⚙ Parámetros'!B5/100*AB17+'⚙ Parámetros'!B6/100*AC17+'⚙ Parámetros'!B7/100*AD17+'⚙ Parámetros'!B8/100*AE17+'⚙ Parámetros'!B9/100*AF17+'⚙ Parámetros'!B10/100*AG17) -> 5.8515121 | AI17: =MIN(1+MAX(0,TODAY()-DATE(2026,1,14))/365*'⚙ Parámetros'!B33,'⚙ Parámetros'!B34) -> 1.0612329 | AJ17: =IFERROR(MIN(AH17*AI17,10),0) -> 6.209817 | AK17: =IF(AB17>='⚙ Parámetros'!B23,"⚑ AUTO-PRIOR.(D1≥8)",IF(AJ17>='⚙ Parámetros'!B23,"PRIORITARIO",IF(AJ17>='⚙ Parámetros'!B24,"ALTA PRIORIDAD",IF(AJ17>='⚙ Parámetros'!B25,"PRIORIDAD MEDIA",IF(AJ17>='⚙ Parámetros'!B26,"BAJA PRIORIDAD","DESCARTAR"))))) -> PRIORIDAD MEDIA | AL17: =IF(AB17>=8,"SÍ ⚑","—") -> — | AM17: 38 | AN17: =IF(AM17="","—",IF(AM17<'⚙ Parámetros'!B29,"🟢 Corto",IF(AM17<'⚙ Parámetros'!B30,"🟡 Medio","🔴 Largo"))) -> 🟡 Medio
A18: 14 | B18: MPG-LOG-068 Notas de advertencia y peligro. Intralogística | C18: Supply chain y logística | D18: Joan Valverde | E18: 07/05/2026 | F18: 8 | G18: 9 | H18: 1 | I18: 8 | J18: 1 | K18: 1 | L18: 8 | M18: 3 | N18: 1 | O18: 1 | P18: 1 | Q18: 8 | R18: 5 | S18: 5 | T18: 5 | U18: 5 | V18: 5 | W18: 6 | X18: 6 | Y18: 4 | Z18: 2 | AA18: 5 | AB18: =IFERROR((30/100*MAX('⚙ Parámetros'!D15/(1+2^(-'⚙ Parámetros'!C15*(F18-'⚙ Parámetros'!B15))),'⚙ Parámetros'!G15/(1+2^(-'⚙ Parámetros'!F15*(F18-'⚙ Parámetros'!E15))),1)*F18+30/100*MAX('⚙ Parámetros'!D15/(1+2^(-'⚙ Parámetros'!C15*(G18-'⚙ Parámetros'!B15))),'⚙ Parámetros'!G15/(1+2^(-'⚙ Parámetros'!F15*(G18-'⚙ Parámetros'!E15))),1)*G18+20/100*MAX('⚙ Parámetros'!D15/(1+2^(-'⚙ Parámetros'!C15*(H18-'⚙ Parámetros'!B15))),'⚙ Parámetros'!G15/(1+2^(-'⚙ Parámetros'!F15*(H18-'⚙ Parámetros'!E15))),1)*H18+20/100*MAX('⚙ Parámetros'!D15/(1+2^(-'⚙ Parámetros'!C15*(I18-'⚙ Parámetros'!B15))),'⚙ Parámetros'!G15/(1+2^(-'⚙ Parámetros'!F15*(I18-'⚙ Parámetros'!E15))),1)*I18)/(30/100*MAX('⚙ Parámetros'!D15/(1+2^(-'⚙ Parámetros'!C15*(F18-'⚙ Parámetros'!B15))),'⚙ Parámetros'!G15/(1+2^(-'⚙ Parámetros'!F15*(F18-'⚙ Parámetros'!E15))),1)+30/100*MAX('⚙ Parámetros'!D15/(1+2^(-'⚙ Parámetros'!C15*(G18-'⚙ Parámetros'!B15))),'⚙ Parámetros'!G15/(1+2^(-'⚙ Parámetros'!F15*(G18-'⚙ Parámetros'!E15))),1)+20/100*MAX('⚙ Parámetros'!D15/(1+2^(-'⚙ Parámetros'!C15*(H18-'⚙ Parámetros'!B15))),'⚙ Parámetros'!G15/(1+2^(-'⚙ Parámetros'!F15*(H18-'⚙ Parámetros'!E15))),1)+20/100*MAX('⚙ Parámetros'!D15/(1+2^(-'⚙ Parámetros'!C15*(I18-'⚙ Parámetros'!B15))),'⚙ Parámetros'!G15/(1+2^(-'⚙ Parámetros'!F15*(I18-'⚙ Parámetros'!E15))),1)),0) -> 8.1799629 | AC18: =IFERROR((35/100*MAX('⚙ Parámetros'!D16/(1+2^(-'⚙ Parámetros'!C16*(J18-'⚙ Parámetros'!B16))),'⚙ Parámetros'!G16/(1+2^(-'⚙ Parámetros'!F16*(J18-'⚙ Parámetros'!E16))),1)*J18+25/100*MAX('⚙ Parámetros'!D16/(1+2^(-'⚙ Parámetros'!C16*(K18-'⚙ Parámetros'!B16))),'⚙ Parámetros'!G16/(1+2^(-'⚙ Parámetros'!F16*(K18-'⚙ Parámetros'!E16))),1)*K18+20/100*MAX('⚙ Parámetros'!D16/(1+2^(-'⚙ Parámetros'!C16*(L18-'⚙ Parámetros'!B16))),'⚙ Parámetros'!G16/(1+2^(-'⚙ Parámetros'!F16*(L18-'⚙ Parámetros'!E16))),1)*L18+20/100*MAX('⚙ Parámetros'!D16/(1+2^(-'⚙ Parámetros'!C16*(M18-'⚙ Parámetros'!B16))),'⚙ Parámetros'!G16/(1+2^(-'⚙ Parámetros'!F16*(M18-'⚙ Parámetros'!E16))),1)*M18)/(35/100*MAX('⚙ Parámetros'!D16/(1+2^(-'⚙ Parámetros'!C16*(J18-'⚙ Parámetros'!B16))),'⚙ Parámetros'!G16/(1+2^(-'⚙ Parámetros'!F16*(J18-'⚙ Parámetros'!E16))),1)+25/100*MAX('⚙ Parámetros'!D16/(1+2^(-'⚙ Parámetros'!C16*(K18-'⚙ Parámetros'!B16))),'⚙ Parámetros'!G16/(1+2^(-'⚙ Parámetros'!F16*(K18-'⚙ Parámetros'!E16))),1)+20/100*MAX('⚙ Parámetros'!D16/(1+2^(-'⚙ Parámetros'!C16*(L18-'⚙ Parámetros'!B16))),'⚙ Parámetros'!G16/(1+2^(-'⚙ Parámetros'!F16*(L18-'⚙ Parámetros'!E16))),1)+20/100*MAX('⚙ Parámetros'!D16/(1+2^(-'⚙ Parámetros'!C16*(M18-'⚙ Parámetros'!B16))),'⚙ Parámetros'!G16/(1+2^(-'⚙ Parámetros'!F16*(M18-'⚙ Parámetros'!E16))),1)),0) -> 4.9411765 | AD18: =IFERROR((30/100*MAX('⚙ Parámetros'!D17/(1+2^(-'⚙ Parámetros'!C17*(N18-'⚙ Parámetros'!B17))),'⚙ Parámetros'!G17/(1+2^(-'⚙ Parámetros'!F17*(N18-'⚙ Parámetros'!E17))),1)*N18+25/100*MAX('⚙ Parámetros'!D17/(1+2^(-'⚙ Parámetros'!C17*(O18-'⚙ Parámetros'!B17))),'⚙ Parámetros'!G17/(1+2^(-'⚙ Parámetros'!F17*(O18-'⚙ Parámetros'!E17))),1)*O18+25/100*MAX('⚙ Parámetros'!D17/(1+2^(-'⚙ Parámetros'!C17*(P18-'⚙ Parámetros'!B17))),'⚙ Parámetros'!G17/(1+2^(-'⚙ Parámetros'!F17*(P18-'⚙ Parámetros'!E17))),1)*P18+20/100*MAX('⚙ Parámetros'!D17/(1+2^(-'⚙ Parámetros'!C17*(Q18-'⚙ Parámetros'!B17))),'⚙ Parámetros'!G17/(1+2^(-'⚙ Parámetros'!F17*(Q18-'⚙ Parámetros'!E17))),1)*Q18)/(30/100*MAX('⚙ Parámetros'!D17/(1+2^(-'⚙ Parámetros'!C17*(N18-'⚙ Parámetros'!B17))),'⚙ Parámetros'!G17/(1+2^(-'⚙ Parámetros'!F17*(N18-'⚙ Parámetros'!E17))),1)+25/100*MAX('⚙ Parámetros'!D17/(1+2^(-'⚙ Parámetros'!C17*(O18-'⚙ Parámetros'!B17))),'⚙ Parámetros'!G17/(1+2^(-'⚙ Parámetros'!F17*(O18-'⚙ Parámetros'!E17))),1)+25/100*MAX('⚙ Parámetros'!D17/(1+2^(-'⚙ Parámetros'!C17*(P18-'⚙ Parámetros'!B17))),'⚙ Parámetros'!G17/(1+2^(-'⚙ Parámetros'!F17*(P18-'⚙ Parámetros'!E17))),1)+20/100*MAX('⚙ Parámetros'!D17/(1+2^(-'⚙ Parámetros'!C17*(Q18-'⚙ Parámetros'!B17))),'⚙ Parámetros'!G17/(1+2^(-'⚙ Parámetros'!F17*(Q18-'⚙ Parámetros'!E17))),1)),0) -> 4.5 | AE18: =IFERROR((30/100*MAX('⚙ Parámetros'!D18/(1+2^(-'⚙ Parámetros'!C18*(R18-'⚙ Parámetros'!B18))),'⚙ Parámetros'!G18/(1+2^(-'⚙ Parámetros'!F18*(R18-'⚙ Parámetros'!E18))),1)*R18+30/100*MAX('⚙ Parámetros'!D18/(1+2^(-'⚙ Parámetros'!C18*(S18-'⚙ Parámetros'!B18))),'⚙ Parámetros'!G18/(1+2^(-'⚙ Parámetros'!F18*(S18-'⚙ Parámetros'!E18))),1)*S18+20/100*MAX('⚙ Parámetros'!D18/(1+2^(-'⚙ Parámetros'!C18*(T18-'⚙ Parámetros'!B18))),'⚙ Parámetros'!G18/(1+2^(-'⚙ Parámetros'!F18*(T18-'⚙ Parámetros'!E18))),1)*T18+20/100*MAX('⚙ Parámetros'!D18/(1+2^(-'⚙ Parámetros'!C18*(U18-'⚙ Parámetros'!B18))),'⚙ Parámetros'!G18/(1+2^(-'⚙ Parámetros'!F18*(U18-'⚙ Parámetros'!E18))),1)*U18)/(30/100*MAX('⚙ Parámetros'!D18/(1+2^(-'⚙ Parámetros'!C18*(R18-'⚙ Parámetros'!B18))),'⚙ Parámetros'!G18/(1+2^(-'⚙ Parámetros'!F18*(R18-'⚙ Parámetros'!E18))),1)+30/100*MAX('⚙ Parámetros'!D18/(1+2^(-'⚙ Parámetros'!C18*(S18-'⚙ Parámetros'!B18))),'⚙ Parámetros'!G18/(1+2^(-'⚙ Parámetros'!F18*(S18-'⚙ Parámetros'!E18))),1)+20/100*MAX('⚙ Parámetros'!D18/(1+2^(-'⚙ Parámetros'!C18*(T18-'⚙ Parámetros'!B18))),'⚙ Parámetros'!G18/(1+2^(-'⚙ Parámetros'!F18*(T18-'⚙ Parámetros'!E18))),1)+20/100*MAX('⚙ Parámetros'!D18/(1+2^(-'⚙ Parámetros'!C18*(U18-'⚙ Parámetros'!B18))),'⚙ Parámetros'!G18/(1+2^(-'⚙ Parámetros'!F18*(U18-'⚙ Parámetros'!E18))),1)),0) -> 5 | AF18: =IFERROR((30/100*MAX('⚙ Parámetros'!D19/(1+2^(-'⚙ Parámetros'!C19*(V18-'⚙ Parámetros'!B19))),'⚙ Parámetros'!G19/(1+2^(-'⚙ Parámetros'!F19*(V18-'⚙ Parámetros'!E19))),1)*V18+35/100*MAX('⚙ Parámetros'!D19/(1+2^(-'⚙ Parámetros'!C19*(W18-'⚙ Parámetros'!B19))),'⚙ Parámetros'!G19/(1+2^(-'⚙ Parámetros'!F19*(W18-'⚙ Parámetros'!E19))),1)*W18+35/100*MAX('⚙ Parámetros'!D19/(1+2^(-'⚙ Parámetros'!C19*(X18-'⚙ Parámetros'!B19))),'⚙ Parámetros'!G19/(1+2^(-'⚙ Parámetros'!F19*(X18-'⚙ Parámetros'!E19))),1)*X18)/(30/100*MAX('⚙ Parámetros'!D19/(1+2^(-'⚙ Parámetros'!C19*(V18-'⚙ Parámetros'!B19))),'⚙ Parámetros'!G19/(1+2^(-'⚙ Parámetros'!F19*(V18-'⚙ Parámetros'!E19))),1)+35/100*MAX('⚙ Parámetros'!D19/(1+2^(-'⚙ Parámetros'!C19*(W18-'⚙ Parámetros'!B19))),'⚙ Parámetros'!G19/(1+2^(-'⚙ Parámetros'!F19*(W18-'⚙ Parámetros'!E19))),1)+35/100*MAX('⚙ Parámetros'!D19/(1+2^(-'⚙ Parámetros'!C19*(X18-'⚙ Parámetros'!B19))),'⚙ Parámetros'!G19/(1+2^(-'⚙ Parámetros'!F19*(X18-'⚙ Parámetros'!E19))),1)),0) -> 5.7368421 | AG18: =IFERROR((35/100*MAX('⚙ Parámetros'!D20/(1+2^(-'⚙ Parámetros'!C20*(Y18-'⚙ Parámetros'!B20))),'⚙ Parámetros'!G20/(1+2^(-'⚙ Parámetros'!F20*(Y18-'⚙ Parámetros'!E20))),1)*Y18+35/100*MAX('⚙ Parámetros'!D20/(1+2^(-'⚙ Parámetros'!C20*(Z18-'⚙ Parámetros'!B20))),'⚙ Parámetros'!G20/(1+2^(-'⚙ Parámetros'!F20*(Z18-'⚙ Parámetros'!E20))),1)*Z18+30/100*MAX('⚙ Parámetros'!D20/(1+2^(-'⚙ Parámetros'!C20*(AA18-'⚙ Parámetros'!B20))),'⚙ Parámetros'!G20/(1+2^(-'⚙ Parámetros'!F20*(AA18-'⚙ Parámetros'!E20))),1)*AA18)/(35/100*MAX('⚙ Parámetros'!D20/(1+2^(-'⚙ Parámetros'!C20*(Y18-'⚙ Parámetros'!B20))),'⚙ Parámetros'!G20/(1+2^(-'⚙ Parámetros'!F20*(Y18-'⚙ Parámetros'!E20))),1)+35/100*MAX('⚙ Parámetros'!D20/(1+2^(-'⚙ Parámetros'!C20*(Z18-'⚙ Parámetros'!B20))),'⚙ Parámetros'!G20/(1+2^(-'⚙ Parámetros'!F20*(Z18-'⚙ Parámetros'!E20))),1)+30/100*MAX('⚙ Parámetros'!D20/(1+2^(-'⚙ Parámetros'!C20*(AA18-'⚙ Parámetros'!B20))),'⚙ Parámetros'!G20/(1+2^(-'⚙ Parámetros'!F20*(AA18-'⚙ Parámetros'!E20))),1)),0) -> 3.7272727 | AH18: =('⚙ Parámetros'!B5/100*AB18+'⚙ Parámetros'!B6/100*AC18+'⚙ Parámetros'!B7/100*AD18+'⚙ Parámetros'!B8/100*AE18+'⚙ Parámetros'!B9/100*AF18+'⚙ Parámetros'!B10/100*AG18) -> 5.8140902 | AI18: =MIN(1+MAX(0,TODAY()-DATE(2026,5,7))/365*'⚙ Parámetros'!B33,'⚙ Parámetros'!B34) -> 1.0147945 | AJ18: =IFERROR(MIN(AH18*AI18,10),0) -> 5.9001069 | AK18: =IF(AB18>='⚙ Parámetros'!B23,"⚑ AUTO-PRIOR.(D1≥8)",IF(AJ18>='⚙ Parámetros'!B23,"PRIORITARIO",IF(AJ18>='⚙ Parámetros'!B24,"ALTA PRIORIDAD",IF(AJ18>='⚙ Parámetros'!B25,"PRIORIDAD MEDIA",IF(AJ18>='⚙ Parámetros'!B26,"BAJA PRIORIDAD","DESCARTAR"))))) -> PRIORIDAD MEDIA | AL18: =IF(AB18>=8,"SÍ ⚑","—") -> SÍ ⚑ | AM18: 41 | AN18: =IF(AM18="","—",IF(AM18<'⚙ Parámetros'!B29,"🟢 Corto",IF(AM18<'⚙ Parámetros'!B30,"🟡 Medio","🔴 Largo"))) -> 🟡 Medio
A19: 15 | B19: MPG-COM-016 Aviso de la cantidad de muestra al crear líneas de PC | C19: Supply chain y logística | D19: Julio Cesar Escobar Ascanio | E19: 03/07/2025 | F19: 6 | G19: 5 | H19: 1 | I19: 5 | J19: 1 | K19: 1 | L19: 8 | M19: 3 | N19: 7 | O19: 6 | P19: 1 | Q19: 8 | R19: 9 | S19: 9 | T19: 5 | U19: 5 | V19: 8 | W19: 6 | X19: 9 | Y19: 4 | Z19: 2 | AA19: 5 | AB19: =IFERROR((30/100*MAX('⚙ Parámetros'!D15/(1+2^(-'⚙ Parámetros'!C15*(F19-'⚙ Parámetros'!B15))),'⚙ Parámetros'!G15/(1+2^(-'⚙ Parámetros'!F15*(F19-'⚙ Parámetros'!E15))),1)*F19+30/100*MAX('⚙ Parámetros'!D15/(1+2^(-'⚙ Parámetros'!C15*(G19-'⚙ Parámetros'!B15))),'⚙ Parámetros'!G15/(1+2^(-'⚙ Parámetros'!F15*(G19-'⚙ Parámetros'!E15))),1)*G19+20/100*MAX('⚙ Parámetros'!D15/(1+2^(-'⚙ Parámetros'!C15*(H19-'⚙ Parámetros'!B15))),'⚙ Parámetros'!G15/(1+2^(-'⚙ Parámetros'!F15*(H19-'⚙ Parámetros'!E15))),1)*H19+20/100*MAX('⚙ Parámetros'!D15/(1+2^(-'⚙ Parámetros'!C15*(I19-'⚙ Parámetros'!B15))),'⚙ Parámetros'!G15/(1+2^(-'⚙ Parámetros'!F15*(I19-'⚙ Parámetros'!E15))),1)*I19)/(30/100*MAX('⚙ Parámetros'!D15/(1+2^(-'⚙ Parámetros'!C15*(F19-'⚙ Parámetros'!B15))),'⚙ Parámetros'!G15/(1+2^(-'⚙ Parámetros'!F15*(F19-'⚙ Parámetros'!E15))),1)+30/100*MAX('⚙ Parámetros'!D15/(1+2^(-'⚙ Parámetros'!C15*(G19-'⚙ Parámetros'!B15))),'⚙ Parámetros'!G15/(1+2^(-'⚙ Parámetros'!F15*(G19-'⚙ Parámetros'!E15))),1)+20/100*MAX('⚙ Parámetros'!D15/(1+2^(-'⚙ Parámetros'!C15*(H19-'⚙ Parámetros'!B15))),'⚙ Parámetros'!G15/(1+2^(-'⚙ Parámetros'!F15*(H19-'⚙ Parámetros'!E15))),1)+20/100*MAX('⚙ Parámetros'!D15/(1+2^(-'⚙ Parámetros'!C15*(I19-'⚙ Parámetros'!B15))),'⚙ Parámetros'!G15/(1+2^(-'⚙ Parámetros'!F15*(I19-'⚙ Parámetros'!E15))),1)),0) -> 4.8311688 | AC19: =IFERROR((35/100*MAX('⚙ Parámetros'!D16/(1+2^(-'⚙ Parámetros'!C16*(J19-'⚙ Parámetros'!B16))),'⚙ Parámetros'!G16/(1+2^(-'⚙ Parámetros'!F16*(J19-'⚙ Parámetros'!E16))),1)*J19+25/100*MAX('⚙ Parámetros'!D16/(1+2^(-'⚙ Parámetros'!C16*(K19-'⚙ Parámetros'!B16))),'⚙ Parámetros'!G16/(1+2^(-'⚙ Parámetros'!F16*(K19-'⚙ Parámetros'!E16))),1)*K19+20/100*MAX('⚙ Parámetros'!D16/(1+2^(-'⚙ Parámetros'!C16*(L19-'⚙ Parámetros'!B16))),'⚙ Parámetros'!G16/(1+2^(-'⚙ Parámetros'!F16*(L19-'⚙ Parámetros'!E16))),1)*L19+20/100*MAX('⚙ Parámetros'!D16/(1+2^(-'⚙ Parámetros'!C16*(M19-'⚙ Parámetros'!B16))),'⚙ Parámetros'!G16/(1+2^(-'⚙ Parámetros'!F16*(M19-'⚙ Parámetros'!E16))),1)*M19)/(35/100*MAX('⚙ Parámetros'!D16/(1+2^(-'⚙ Parámetros'!C16*(J19-'⚙ Parámetros'!B16))),'⚙ Parámetros'!G16/(1+2^(-'⚙ Parámetros'!F16*(J19-'⚙ Parámetros'!E16))),1)+25/100*MAX('⚙ Parámetros'!D16/(1+2^(-'⚙ Parámetros'!C16*(K19-'⚙ Parámetros'!B16))),'⚙ Parámetros'!G16/(1+2^(-'⚙ Parámetros'!F16*(K19-'⚙ Parámetros'!E16))),1)+20/100*MAX('⚙ Parámetros'!D16/(1+2^(-'⚙ Parámetros'!C16*(L19-'⚙ Parámetros'!B16))),'⚙ Parámetros'!G16/(1+2^(-'⚙ Parámetros'!F16*(L19-'⚙ Parámetros'!E16))),1)+20/100*MAX('⚙ Parámetros'!D16/(1+2^(-'⚙ Parámetros'!C16*(M19-'⚙ Parámetros'!B16))),'⚙ Parámetros'!G16/(1+2^(-'⚙ Parámetros'!F16*(M19-'⚙ Parámetros'!E16))),1)),0) -> 4.9411765 | AD19: =IFERROR((30/100*MAX('⚙ Parámetros'!D17/(1+2^(-'⚙ Parámetros'!C17*(N19-'⚙ Parámetros'!B17))),'⚙ Parámetros'!G17/(1+2^(-'⚙ Parámetros'!F17*(N19-'⚙ Parámetros'!E17))),1)*N19+25/100*MAX('⚙ Parámetros'!D17/(1+2^(-'⚙ Parámetros'!C17*(O19-'⚙ Parámetros'!B17))),'⚙ Parámetros'!G17/(1+2^(-'⚙ Parámetros'!F17*(O19-'⚙ Parámetros'!E17))),1)*O19+25/100*MAX('⚙ Parámetros'!D17/(1+2^(-'⚙ Parámetros'!C17*(P19-'⚙ Parámetros'!B17))),'⚙ Parámetros'!G17/(1+2^(-'⚙ Parámetros'!F17*(P19-'⚙ Parámetros'!E17))),1)*P19+20/100*MAX('⚙ Parámetros'!D17/(1+2^(-'⚙ Parámetros'!C17*(Q19-'⚙ Parámetros'!B17))),'⚙ Parámetros'!G17/(1+2^(-'⚙ Parámetros'!F17*(Q19-'⚙ Parámetros'!E17))),1)*Q19)/(30/100*MAX('⚙ Parámetros'!D17/(1+2^(-'⚙ Parámetros'!C17*(N19-'⚙ Parámetros'!B17))),'⚙ Parámetros'!G17/(1+2^(-'⚙ Parámetros'!F17*(N19-'⚙ Parámetros'!E17))),1)+25/100*MAX('⚙ Parámetros'!D17/(1+2^(-'⚙ Parámetros'!C17*(O19-'⚙ Parámetros'!B17))),'⚙ Parámetros'!G17/(1+2^(-'⚙ Parámetros'!F17*(O19-'⚙ Parámetros'!E17))),1)+25/100*MAX('⚙ Parámetros'!D17/(1+2^(-'⚙ Parámetros'!C17*(P19-'⚙ Parámetros'!B17))),'⚙ Parámetros'!G17/(1+2^(-'⚙ Parámetros'!F17*(P19-'⚙ Parámetros'!E17))),1)+20/100*MAX('⚙ Parámetros'!D17/(1+2^(-'⚙ Parámetros'!C17*(Q19-'⚙ Parámetros'!B17))),'⚙ Parámetros'!G17/(1+2^(-'⚙ Parámetros'!F17*(Q19-'⚙ Parámetros'!E17))),1)),0) -> 6.4693878 | AE19: =IFERROR((30/100*MAX('⚙ Parámetros'!D18/(1+2^(-'⚙ Parámetros'!C18*(R19-'⚙ Parámetros'!B18))),'⚙ Parámetros'!G18/(1+2^(-'⚙ Parámetros'!F18*(R19-'⚙ Parámetros'!E18))),1)*R19+30/100*MAX('⚙ Parámetros'!D18/(1+2^(-'⚙ Parámetros'!C18*(S19-'⚙ Parámetros'!B18))),'⚙ Parámetros'!G18/(1+2^(-'⚙ Parámetros'!F18*(S19-'⚙ Parámetros'!E18))),1)*S19+20/100*MAX('⚙ Parámetros'!D18/(1+2^(-'⚙ Parámetros'!C18*(T19-'⚙ Parámetros'!B18))),'⚙ Parámetros'!G18/(1+2^(-'⚙ Parámetros'!F18*(T19-'⚙ Parámetros'!E18))),1)*T19+20/100*MAX('⚙ Parámetros'!D18/(1+2^(-'⚙ Parámetros'!C18*(U19-'⚙ Parámetros'!B18))),'⚙ Parámetros'!G18/(1+2^(-'⚙ Parámetros'!F18*(U19-'⚙ Parámetros'!E18))),1)*U19)/(30/100*MAX('⚙ Parámetros'!D18/(1+2^(-'⚙ Parámetros'!C18*(R19-'⚙ Parámetros'!B18))),'⚙ Parámetros'!G18/(1+2^(-'⚙ Parámetros'!F18*(R19-'⚙ Parámetros'!E18))),1)+30/100*MAX('⚙ Parámetros'!D18/(1+2^(-'⚙ Parámetros'!C18*(S19-'⚙ Parámetros'!B18))),'⚙ Parámetros'!G18/(1+2^(-'⚙ Parámetros'!F18*(S19-'⚙ Parámetros'!E18))),1)+20/100*MAX('⚙ Parámetros'!D18/(1+2^(-'⚙ Parámetros'!C18*(T19-'⚙ Parámetros'!B18))),'⚙ Parámetros'!G18/(1+2^(-'⚙ Parámetros'!F18*(T19-'⚙ Parámetros'!E18))),1)+20/100*MAX('⚙ Parámetros'!D18/(1+2^(-'⚙ Parámetros'!C18*(U19-'⚙ Parámetros'!B18))),'⚙ Parámetros'!G18/(1+2^(-'⚙ Parámetros'!F18*(U19-'⚙ Parámetros'!E18))),1)),0) -> 8.180106 | AF19: =IFERROR((30/100*MAX('⚙ Parámetros'!D19/(1+2^(-'⚙ Parámetros'!C19*(V19-'⚙ Parámetros'!B19))),'⚙ Parámetros'!G19/(1+2^(-'⚙ Parámetros'!F19*(V19-'⚙ Parámetros'!E19))),1)*V19+35/100*MAX('⚙ Parámetros'!D19/(1+2^(-'⚙ Parámetros'!C19*(W19-'⚙ Parámetros'!B19))),'⚙ Parámetros'!G19/(1+2^(-'⚙ Parámetros'!F19*(W19-'⚙ Parámetros'!E19))),1)*W19+35/100*MAX('⚙ Parámetros'!D19/(1+2^(-'⚙ Parámetros'!C19*(X19-'⚙ Parámetros'!B19))),'⚙ Parámetros'!G19/(1+2^(-'⚙ Parámetros'!F19*(X19-'⚙ Parámetros'!E19))),1)*X19)/(30/100*MAX('⚙ Parámetros'!D19/(1+2^(-'⚙ Parámetros'!C19*(V19-'⚙ Parámetros'!B19))),'⚙ Parámetros'!G19/(1+2^(-'⚙ Parámetros'!F19*(V19-'⚙ Parámetros'!E19))),1)+35/100*MAX('⚙ Parámetros'!D19/(1+2^(-'⚙ Parámetros'!C19*(W19-'⚙ Parámetros'!B19))),'⚙ Parámetros'!G19/(1+2^(-'⚙ Parámetros'!F19*(W19-'⚙ Parámetros'!E19))),1)+35/100*MAX('⚙ Parámetros'!D19/(1+2^(-'⚙ Parámetros'!C19*(X19-'⚙ Parámetros'!B19))),'⚙ Parámetros'!G19/(1+2^(-'⚙ Parámetros'!F19*(X19-'⚙ Parámetros'!E19))),1)),0) -> 8.0351483 | AG19: =IFERROR((35/100*MAX('⚙ Parámetros'!D20/(1+2^(-'⚙ Parámetros'!C20*(Y19-'⚙ Parámetros'!B20))),'⚙ Parámetros'!G20/(1+2^(-'⚙ Parámetros'!F20*(Y19-'⚙ Parámetros'!E20))),1)*Y19+35/100*MAX('⚙ Parámetros'!D20/(1+2^(-'⚙ Parámetros'!C20*(Z19-'⚙ Parámetros'!B20))),'⚙ Parámetros'!G20/(1+2^(-'⚙ Parámetros'!F20*(Z19-'⚙ Parámetros'!E20))),1)*Z19+30/100*MAX('⚙ Parámetros'!D20/(1+2^(-'⚙ Parámetros'!C20*(AA19-'⚙ Parámetros'!B20))),'⚙ Parámetros'!G20/(1+2^(-'⚙ Parámetros'!F20*(AA19-'⚙ Parámetros'!E20))),1)*AA19)/(35/100*MAX('⚙ Parámetros'!D20/(1+2^(-'⚙ Parámetros'!C20*(Y19-'⚙ Parámetros'!B20))),'⚙ Parámetros'!G20/(1+2^(-'⚙ Parámetros'!F20*(Y19-'⚙ Parámetros'!E20))),1)+35/100*MAX('⚙ Parámetros'!D20/(1+2^(-'⚙ Parámetros'!C20*(Z19-'⚙ Parámetros'!B20))),'⚙ Parámetros'!G20/(1+2^(-'⚙ Parámetros'!F20*(Z19-'⚙ Parámetros'!E20))),1)+30/100*MAX('⚙ Parámetros'!D20/(1+2^(-'⚙ Parámetros'!C20*(AA19-'⚙ Parámetros'!B20))),'⚙ Parámetros'!G20/(1+2^(-'⚙ Parámetros'!F20*(AA19-'⚙ Parámetros'!E20))),1)),0) -> 3.7272727 | AH19: =('⚙ Parámetros'!B5/100*AB19+'⚙ Parámetros'!B6/100*AC19+'⚙ Parámetros'!B7/100*AD19+'⚙ Parámetros'!B8/100*AE19+'⚙ Parámetros'!B9/100*AF19+'⚙ Parámetros'!B10/100*AG19) -> 5.8147729 | AI19: =MIN(1+MAX(0,TODAY()-DATE(2025,7,3))/365*'⚙ Parámetros'!B33,'⚙ Parámetros'!B34) -> 1.1413699 | AJ19: =IFERROR(MIN(AH19*AI19,10),0) -> 6.6368065 | AK19: =IF(AB19>='⚙ Parámetros'!B23,"⚑ AUTO-PRIOR.(D1≥8)",IF(AJ19>='⚙ Parámetros'!B23,"PRIORITARIO",IF(AJ19>='⚙ Parámetros'!B24,"ALTA PRIORIDAD",IF(AJ19>='⚙ Parámetros'!B25,"PRIORIDAD MEDIA",IF(AJ19>='⚙ Parámetros'!B26,"BAJA PRIORIDAD","DESCARTAR"))))) -> PRIORIDAD MEDIA | AL19: =IF(AB19>=8,"SÍ ⚑","—") -> — | AM19: 32 | AN19: =IF(AM19="","—",IF(AM19<'⚙ Parámetros'!B29,"🟢 Corto",IF(AM19<'⚙ Parámetros'!B30,"🟡 Medio","🔴 Largo"))) -> 🟡 Medio
A20: 16 | B20: MPG-FIN-023 Tickelia Importacion tickets + Guardar Foto | C20: Finanzas y control | D20: Julio Cesar Escobar Ascanio | E20: 10/06/2025 | F20: 9 | G20: 1 | H20: 1 | I20: 9 | J20: 7 | K20: 1 | L20: 8 | M20: 3 | N20: 1 | O20: 6 | P20: 1 | Q20: 1 | R20: 5 | S20: 5 | T20: 5 | U20: 5 | V20: 5 | W20: 6 | X20: 3 | Y20: 4 | Z20: 2 | AA20: 5 | AB20: =IFERROR((30/100*MAX('⚙ Parámetros'!D15/(1+2^(-'⚙ Parámetros'!C15*(F20-'⚙ Parámetros'!B15))),'⚙ Parámetros'!G15/(1+2^(-'⚙ Parámetros'!F15*(F20-'⚙ Parámetros'!E15))),1)*F20+30/100*MAX('⚙ Parámetros'!D15/(1+2^(-'⚙ Parámetros'!C15*(G20-'⚙ Parámetros'!B15))),'⚙ Parámetros'!G15/(1+2^(-'⚙ Parámetros'!F15*(G20-'⚙ Parámetros'!E15))),1)*G20+20/100*MAX('⚙ Parámetros'!D15/(1+2^(-'⚙ Parámetros'!C15*(H20-'⚙ Parámetros'!B15))),'⚙ Parámetros'!G15/(1+2^(-'⚙ Parámetros'!F15*(H20-'⚙ Parámetros'!E15))),1)*H20+20/100*MAX('⚙ Parámetros'!D15/(1+2^(-'⚙ Parámetros'!C15*(I20-'⚙ Parámetros'!B15))),'⚙ Parámetros'!G15/(1+2^(-'⚙ Parámetros'!F15*(I20-'⚙ Parámetros'!E15))),1)*I20)/(30/100*MAX('⚙ Parámetros'!D15/(1+2^(-'⚙ Parámetros'!C15*(F20-'⚙ Parámetros'!B15))),'⚙ Parámetros'!G15/(1+2^(-'⚙ Parámetros'!F15*(F20-'⚙ Parámetros'!E15))),1)+30/100*MAX('⚙ Parámetros'!D15/(1+2^(-'⚙ Parámetros'!C15*(G20-'⚙ Parámetros'!B15))),'⚙ Parámetros'!G15/(1+2^(-'⚙ Parámetros'!F15*(G20-'⚙ Parámetros'!E15))),1)+20/100*MAX('⚙ Parámetros'!D15/(1+2^(-'⚙ Parámetros'!C15*(H20-'⚙ Parámetros'!B15))),'⚙ Parámetros'!G15/(1+2^(-'⚙ Parámetros'!F15*(H20-'⚙ Parámetros'!E15))),1)+20/100*MAX('⚙ Parámetros'!D15/(1+2^(-'⚙ Parámetros'!C15*(I20-'⚙ Parámetros'!B15))),'⚙ Parámetros'!G15/(1+2^(-'⚙ Parámetros'!F15*(I20-'⚙ Parámetros'!E15))),1)),0) -> 8.1552795 | AC20: =IFERROR((35/100*MAX('⚙ Parámetros'!D16/(1+2^(-'⚙ Parámetros'!C16*(J20-'⚙ Parámetros'!B16))),'⚙ Parámetros'!G16/(1+2^(-'⚙ Parámetros'!F16*(J20-'⚙ Parámetros'!E16))),1)*J20+25/100*MAX('⚙ Parámetros'!D16/(1+2^(-'⚙ Parámetros'!C16*(K20-'⚙ Parámetros'!B16))),'⚙ Parámetros'!G16/(1+2^(-'⚙ Parámetros'!F16*(K20-'⚙ Parámetros'!E16))),1)*K20+20/100*MAX('⚙ Parámetros'!D16/(1+2^(-'⚙ Parámetros'!C16*(L20-'⚙ Parámetros'!B16))),'⚙ Parámetros'!G16/(1+2^(-'⚙ Parámetros'!F16*(L20-'⚙ Parámetros'!E16))),1)*L20+20/100*MAX('⚙ Parámetros'!D16/(1+2^(-'⚙ Parámetros'!C16*(M20-'⚙ Parámetros'!B16))),'⚙ Parámetros'!G16/(1+2^(-'⚙ Parámetros'!F16*(M20-'⚙ Parámetros'!E16))),1)*M20)/(35/100*MAX('⚙ Parámetros'!D16/(1+2^(-'⚙ Parámetros'!C16*(J20-'⚙ Parámetros'!B16))),'⚙ Parámetros'!G16/(1+2^(-'⚙ Parámetros'!F16*(J20-'⚙ Parámetros'!E16))),1)+25/100*MAX('⚙ Parámetros'!D16/(1+2^(-'⚙ Parámetros'!C16*(K20-'⚙ Parámetros'!B16))),'⚙ Parámetros'!G16/(1+2^(-'⚙ Parámetros'!F16*(K20-'⚙ Parámetros'!E16))),1)+20/100*MAX('⚙ Parámetros'!D16/(1+2^(-'⚙ Parámetros'!C16*(L20-'⚙ Parámetros'!B16))),'⚙ Parámetros'!G16/(1+2^(-'⚙ Parámetros'!F16*(L20-'⚙ Parámetros'!E16))),1)+20/100*MAX('⚙ Parámetros'!D16/(1+2^(-'⚙ Parámetros'!C16*(M20-'⚙ Parámetros'!B16))),'⚙ Parámetros'!G16/(1+2^(-'⚙ Parámetros'!F16*(M20-'⚙ Parámetros'!E16))),1)),0) -> 6.3868613 | AD20: =IFERROR((30/100*MAX('⚙ Parámetros'!D17/(1+2^(-'⚙ Parámetros'!C17*(N20-'⚙ Parámetros'!B17))),'⚙ Parámetros'!G17/(1+2^(-'⚙ Parámetros'!F17*(N20-'⚙ Parámetros'!E17))),1)*N20+25/100*MAX('⚙ Parámetros'!D17/(1+2^(-'⚙ Parámetros'!C17*(O20-'⚙ Parámetros'!B17))),'⚙ Parámetros'!G17/(1+2^(-'⚙ Parámetros'!F17*(O20-'⚙ Parámetros'!E17))),1)*O20+25/100*MAX('⚙ Parámetros'!D17/(1+2^(-'⚙ Parámetros'!C17*(P20-'⚙ Parámetros'!B17))),'⚙ Parámetros'!G17/(1+2^(-'⚙ Parámetros'!F17*(P20-'⚙ Parámetros'!E17))),1)*P20+20/100*MAX('⚙ Parámetros'!D17/(1+2^(-'⚙ Parámetros'!C17*(Q20-'⚙ Parámetros'!B17))),'⚙ Parámetros'!G17/(1+2^(-'⚙ Parámetros'!F17*(Q20-'⚙ Parámetros'!E17))),1)*Q20)/(30/100*MAX('⚙ Parámetros'!D17/(1+2^(-'⚙ Parámetros'!C17*(N20-'⚙ Parámetros'!B17))),'⚙ Parámetros'!G17/(1+2^(-'⚙ Parámetros'!F17*(N20-'⚙ Parámetros'!E17))),1)+25/100*MAX('⚙ Parámetros'!D17/(1+2^(-'⚙ Parámetros'!C17*(O20-'⚙ Parámetros'!B17))),'⚙ Parámetros'!G17/(1+2^(-'⚙ Parámetros'!F17*(O20-'⚙ Parámetros'!E17))),1)+25/100*MAX('⚙ Parámetros'!D17/(1+2^(-'⚙ Parámetros'!C17*(P20-'⚙ Parámetros'!B17))),'⚙ Parámetros'!G17/(1+2^(-'⚙ Parámetros'!F17*(P20-'⚙ Parámetros'!E17))),1)+20/100*MAX('⚙ Parámetros'!D17/(1+2^(-'⚙ Parámetros'!C17*(Q20-'⚙ Parámetros'!B17))),'⚙ Parámetros'!G17/(1+2^(-'⚙ Parámetros'!F17*(Q20-'⚙ Parámetros'!E17))),1)),0) -> 3.2222222 | AE20: =IFERROR((30/100*MAX('⚙ Parámetros'!D18/(1+2^(-'⚙ Parámetros'!C18*(R20-'⚙ Parámetros'!B18))),'⚙ Parámetros'!G18/(1+2^(-'⚙ Parámetros'!F18*(R20-'⚙ Parámetros'!E18))),1)*R20+30/100*MAX('⚙ Parámetros'!D18/(1+2^(-'⚙ Parámetros'!C18*(S20-'⚙ Parámetros'!B18))),'⚙ Parámetros'!G18/(1+2^(-'⚙ Parámetros'!F18*(S20-'⚙ Parámetros'!E18))),1)*S20+20/100*MAX('⚙ Parámetros'!D18/(1+2^(-'⚙ Parámetros'!C18*(T20-'⚙ Parámetros'!B18))),'⚙ Parámetros'!G18/(1+2^(-'⚙ Parámetros'!F18*(T20-'⚙ Parámetros'!E18))),1)*T20+20/100*MAX('⚙ Parámetros'!D18/(1+2^(-'⚙ Parámetros'!C18*(U20-'⚙ Parámetros'!B18))),'⚙ Parámetros'!G18/(1+2^(-'⚙ Parámetros'!F18*(U20-'⚙ Parámetros'!E18))),1)*U20)/(30/100*MAX('⚙ Parámetros'!D18/(1+2^(-'⚙ Parámetros'!C18*(R20-'⚙ Parámetros'!B18))),'⚙ Parámetros'!G18/(1+2^(-'⚙ Parámetros'!F18*(R20-'⚙ Parámetros'!E18))),1)+30/100*MAX('⚙ Parámetros'!D18/(1+2^(-'⚙ Parámetros'!C18*(S20-'⚙ Parámetros'!B18))),'⚙ Parámetros'!G18/(1+2^(-'⚙ Parámetros'!F18*(S20-'⚙ Parámetros'!E18))),1)+20/100*MAX('⚙ Parámetros'!D18/(1+2^(-'⚙ Parámetros'!C18*(T20-'⚙ Parámetros'!B18))),'⚙ Parámetros'!G18/(1+2^(-'⚙ Parámetros'!F18*(T20-'⚙ Parámetros'!E18))),1)+20/100*MAX('⚙ Parámetros'!D18/(1+2^(-'⚙ Parámetros'!C18*(U20-'⚙ Parámetros'!B18))),'⚙ Parámetros'!G18/(1+2^(-'⚙ Parámetros'!F18*(U20-'⚙ Parámetros'!E18))),1)),0) -> 5 | AF20: =IFERROR((30/100*MAX('⚙ Parámetros'!D19/(1+2^(-'⚙ Parámetros'!C19*(V20-'⚙ Parámetros'!B19))),'⚙ Parámetros'!G19/(1+2^(-'⚙ Parámetros'!F19*(V20-'⚙ Parámetros'!E19))),1)*V20+35/100*MAX('⚙ Parámetros'!D19/(1+2^(-'⚙ Parámetros'!C19*(W20-'⚙ Parámetros'!B19))),'⚙ Parámetros'!G19/(1+2^(-'⚙ Parámetros'!F19*(W20-'⚙ Parámetros'!E19))),1)*W20+35/100*MAX('⚙ Parámetros'!D19/(1+2^(-'⚙ Parámetros'!C19*(X20-'⚙ Parámetros'!B19))),'⚙ Parámetros'!G19/(1+2^(-'⚙ Parámetros'!F19*(X20-'⚙ Parámetros'!E19))),1)*X20)/(30/100*MAX('⚙ Parámetros'!D19/(1+2^(-'⚙ Parámetros'!C19*(V20-'⚙ Parámetros'!B19))),'⚙ Parámetros'!G19/(1+2^(-'⚙ Parámetros'!F19*(V20-'⚙ Parámetros'!E19))),1)+35/100*MAX('⚙ Parámetros'!D19/(1+2^(-'⚙ Parámetros'!C19*(W20-'⚙ Parámetros'!B19))),'⚙ Parámetros'!G19/(1+2^(-'⚙ Parámetros'!F19*(W20-'⚙ Parámetros'!E19))),1)+35/100*MAX('⚙ Parámetros'!D19/(1+2^(-'⚙ Parámetros'!C19*(X20-'⚙ Parámetros'!B19))),'⚙ Parámetros'!G19/(1+2^(-'⚙ Parámetros'!F19*(X20-'⚙ Parámetros'!E19))),1)),0) -> 5.0782123 | AG20: =IFERROR((35/100*MAX('⚙ Parámetros'!D20/(1+2^(-'⚙ Parámetros'!C20*(Y20-'⚙ Parámetros'!B20))),'⚙ Parámetros'!G20/(1+2^(-'⚙ Parámetros'!F20*(Y20-'⚙ Parámetros'!E20))),1)*Y20+35/100*MAX('⚙ Parámetros'!D20/(1+2^(-'⚙ Parámetros'!C20*(Z20-'⚙ Parámetros'!B20))),'⚙ Parámetros'!G20/(1+2^(-'⚙ Parámetros'!F20*(Z20-'⚙ Parámetros'!E20))),1)*Z20+30/100*MAX('⚙ Parámetros'!D20/(1+2^(-'⚙ Parámetros'!C20*(AA20-'⚙ Parámetros'!B20))),'⚙ Parámetros'!G20/(1+2^(-'⚙ Parámetros'!F20*(AA20-'⚙ Parámetros'!E20))),1)*AA20)/(35/100*MAX('⚙ Parámetros'!D20/(1+2^(-'⚙ Parámetros'!C20*(Y20-'⚙ Parámetros'!B20))),'⚙ Parámetros'!G20/(1+2^(-'⚙ Parámetros'!F20*(Y20-'⚙ Parámetros'!E20))),1)+35/100*MAX('⚙ Parámetros'!D20/(1+2^(-'⚙ Parámetros'!C20*(Z20-'⚙ Parámetros'!B20))),'⚙ Parámetros'!G20/(1+2^(-'⚙ Parámetros'!F20*(Z20-'⚙ Parámetros'!E20))),1)+30/100*MAX('⚙ Parámetros'!D20/(1+2^(-'⚙ Parámetros'!C20*(AA20-'⚙ Parámetros'!B20))),'⚙ Parámetros'!G20/(1+2^(-'⚙ Parámetros'!F20*(AA20-'⚙ Parámetros'!E20))),1)),0) -> 3.7272727 | AH20: =('⚙ Parámetros'!B5/100*AB20+'⚙ Parámetros'!B6/100*AC20+'⚙ Parámetros'!B7/100*AD20+'⚙ Parámetros'!B8/100*AE20+'⚙ Parámetros'!B9/100*AF20+'⚙ Parámetros'!B10/100*AG20) -> 5.7744036 | AI20: =MIN(1+MAX(0,TODAY()-DATE(2025,6,10))/365*'⚙ Parámetros'!B33,'⚙ Parámetros'!B34) -> 1.1508219 | AJ20: =IFERROR(MIN(AH20*AI20,10),0) -> 6.6453102 | AK20: =IF(AB20>='⚙ Parámetros'!B23,"⚑ AUTO-PRIOR.(D1≥8)",IF(AJ20>='⚙ Parámetros'!B23,"PRIORITARIO",IF(AJ20>='⚙ Parámetros'!B24,"ALTA PRIORIDAD",IF(AJ20>='⚙ Parámetros'!B25,"PRIORIDAD MEDIA",IF(AJ20>='⚙ Parámetros'!B26,"BAJA PRIORIDAD","DESCARTAR"))))) -> PRIORIDAD MEDIA | AL20: =IF(AB20>=8,"SÍ ⚑","—") -> SÍ ⚑ | AM20: 42 | AN20: =IF(AM20="","—",IF(AM20<'⚙ Parámetros'!B29,"🟢 Corto",IF(AM20<'⚙ Parámetros'!B30,"🟡 Medio","🔴 Largo"))) -> 🟡 Medio
A21: 17 | B21: MPG-FIN-005 Campos obligatorios clientes/proveedores | C21: Finanzas y control | D21: Marc Bometon | E21: 12/09/2024 | F21: 9 | G21: 1 | H21: 5 | I21: 9 | J21: 1 | K21: 1 | L21: 8 | M21: 3 | N21: 1 | O21: 1 | P21: 1 | Q21: 6 | R21: 5 | S21: 5 | T21: 5 | U21: 5 | V21: 8 | W21: 6 | X21: 9 | Y21: 4 | Z21: 2 | AA21: 5 | AB21: =IFERROR((30/100*MAX('⚙ Parámetros'!D15/(1+2^(-'⚙ Parámetros'!C15*(F21-'⚙ Parámetros'!B15))),'⚙ Parámetros'!G15/(1+2^(-'⚙ Parámetros'!F15*(F21-'⚙ Parámetros'!E15))),1)*F21+30/100*MAX('⚙ Parámetros'!D15/(1+2^(-'⚙ Parámetros'!C15*(G21-'⚙ Parámetros'!B15))),'⚙ Parámetros'!G15/(1+2^(-'⚙ Parámetros'!F15*(G21-'⚙ Parámetros'!E15))),1)*G21+20/100*MAX('⚙ Parámetros'!D15/(1+2^(-'⚙ Parámetros'!C15*(H21-'⚙ Parámetros'!B15))),'⚙ Parámetros'!G15/(1+2^(-'⚙ Parámetros'!F15*(H21-'⚙ Parámetros'!E15))),1)*H21+20/100*MAX('⚙ Parámetros'!D15/(1+2^(-'⚙ Parámetros'!C15*(I21-'⚙ Parámetros'!B15))),'⚙ Parámetros'!G15/(1+2^(-'⚙ Parámetros'!F15*(I21-'⚙ Parámetros'!E15))),1)*I21)/(30/100*MAX('⚙ Parámetros'!D15/(1+2^(-'⚙ Parámetros'!C15*(F21-'⚙ Parámetros'!B15))),'⚙ Parámetros'!G15/(1+2^(-'⚙ Parámetros'!F15*(F21-'⚙ Parámetros'!E15))),1)+30/100*MAX('⚙ Parámetros'!D15/(1+2^(-'⚙ Parámetros'!C15*(G21-'⚙ Parámetros'!B15))),'⚙ Parámetros'!G15/(1+2^(-'⚙ Parámetros'!F15*(G21-'⚙ Parámetros'!E15))),1)+20/100*MAX('⚙ Parámetros'!D15/(1+2^(-'⚙ Parámetros'!C15*(H21-'⚙ Parámetros'!B15))),'⚙ Parámetros'!G15/(1+2^(-'⚙ Parámetros'!F15*(H21-'⚙ Parámetros'!E15))),1)+20/100*MAX('⚙ Parámetros'!D15/(1+2^(-'⚙ Parámetros'!C15*(I21-'⚙ Parámetros'!B15))),'⚙ Parámetros'!G15/(1+2^(-'⚙ Parámetros'!F15*(I21-'⚙ Parámetros'!E15))),1)),0) -> 8.2420645 | AC21: =IFERROR((35/100*MAX('⚙ Parámetros'!D16/(1+2^(-'⚙ Parámetros'!C16*(J21-'⚙ Parámetros'!B16))),'⚙ Parámetros'!G16/(1+2^(-'⚙ Parámetros'!F16*(J21-'⚙ Parámetros'!E16))),1)*J21+25/100*MAX('⚙ Parámetros'!D16/(1+2^(-'⚙ Parámetros'!C16*(K21-'⚙ Parámetros'!B16))),'⚙ Parámetros'!G16/(1+2^(-'⚙ Parámetros'!F16*(K21-'⚙ Parámetros'!E16))),1)*K21+20/100*MAX('⚙ Parámetros'!D16/(1+2^(-'⚙ Parámetros'!C16*(L21-'⚙ Parámetros'!B16))),'⚙ Parámetros'!G16/(1+2^(-'⚙ Parámetros'!F16*(L21-'⚙ Parámetros'!E16))),1)*L21+20/100*MAX('⚙ Parámetros'!D16/(1+2^(-'⚙ Parámetros'!C16*(M21-'⚙ Parámetros'!B16))),'⚙ Parámetros'!G16/(1+2^(-'⚙ Parámetros'!F16*(M21-'⚙ Parámetros'!E16))),1)*M21)/(35/100*MAX('⚙ Parámetros'!D16/(1+2^(-'⚙ Parámetros'!C16*(J21-'⚙ Parámetros'!B16))),'⚙ Parámetros'!G16/(1+2^(-'⚙ Parámetros'!F16*(J21-'⚙ Parámetros'!E16))),1)+25/100*MAX('⚙ Parámetros'!D16/(1+2^(-'⚙ Parámetros'!C16*(K21-'⚙ Parámetros'!B16))),'⚙ Parámetros'!G16/(1+2^(-'⚙ Parámetros'!F16*(K21-'⚙ Parámetros'!E16))),1)+20/100*MAX('⚙ Parámetros'!D16/(1+2^(-'⚙ Parámetros'!C16*(L21-'⚙ Parámetros'!B16))),'⚙ Parámetros'!G16/(1+2^(-'⚙ Parámetros'!F16*(L21-'⚙ Parámetros'!E16))),1)+20/100*MAX('⚙ Parámetros'!D16/(1+2^(-'⚙ Parámetros'!C16*(M21-'⚙ Parámetros'!B16))),'⚙ Parámetros'!G16/(1+2^(-'⚙ Parámetros'!F16*(M21-'⚙ Parámetros'!E16))),1)),0) -> 4.9411765 | AD21: =IFERROR((30/100*MAX('⚙ Parámetros'!D17/(1+2^(-'⚙ Parámetros'!C17*(N21-'⚙ Parámetros'!B17))),'⚙ Parámetros'!G17/(1+2^(-'⚙ Parámetros'!F17*(N21-'⚙ Parámetros'!E17))),1)*N21+25/100*MAX('⚙ Parámetros'!D17/(1+2^(-'⚙ Parámetros'!C17*(O21-'⚙ Parámetros'!B17))),'⚙ Parámetros'!G17/(1+2^(-'⚙ Parámetros'!F17*(O21-'⚙ Parámetros'!E17))),1)*O21+25/100*MAX('⚙ Parámetros'!D17/(1+2^(-'⚙ Parámetros'!C17*(P21-'⚙ Parámetros'!B17))),'⚙ Parámetros'!G17/(1+2^(-'⚙ Parámetros'!F17*(P21-'⚙ Parámetros'!E17))),1)*P21+20/100*MAX('⚙ Parámetros'!D17/(1+2^(-'⚙ Parámetros'!C17*(Q21-'⚙ Parámetros'!B17))),'⚙ Parámetros'!G17/(1+2^(-'⚙ Parámetros'!F17*(Q21-'⚙ Parámetros'!E17))),1)*Q21)/(30/100*MAX('⚙ Parámetros'!D17/(1+2^(-'⚙ Parámetros'!C17*(N21-'⚙ Parámetros'!B17))),'⚙ Parámetros'!G17/(1+2^(-'⚙ Parámetros'!F17*(N21-'⚙ Parámetros'!E17))),1)+25/100*MAX('⚙ Parámetros'!D17/(1+2^(-'⚙ Parámetros'!C17*(O21-'⚙ Parámetros'!B17))),'⚙ Parámetros'!G17/(1+2^(-'⚙ Parámetros'!F17*(O21-'⚙ Parámetros'!E17))),1)+25/100*MAX('⚙ Parámetros'!D17/(1+2^(-'⚙ Parámetros'!C17*(P21-'⚙ Parámetros'!B17))),'⚙ Parámetros'!G17/(1+2^(-'⚙ Parámetros'!F17*(P21-'⚙ Parámetros'!E17))),1)+20/100*MAX('⚙ Parámetros'!D17/(1+2^(-'⚙ Parámetros'!C17*(Q21-'⚙ Parámetros'!B17))),'⚙ Parámetros'!G17/(1+2^(-'⚙ Parámetros'!F17*(Q21-'⚙ Parámetros'!E17))),1)),0) -> 2.875 | AE21: =IFERROR((30/100*MAX('⚙ Parámetros'!D18/(1+2^(-'⚙ Parámetros'!C18*(R21-'⚙ Parámetros'!B18))),'⚙ Parámetros'!G18/(1+2^(-'⚙ Parámetros'!F18*(R21-'⚙ Parámetros'!E18))),1)*R21+30/100*MAX('⚙ Parámetros'!D18/(1+2^(-'⚙ Parámetros'!C18*(S21-'⚙ Parámetros'!B18))),'⚙ Parámetros'!G18/(1+2^(-'⚙ Parámetros'!F18*(S21-'⚙ Parámetros'!E18))),1)*S21+20/100*MAX('⚙ Parámetros'!D18/(1+2^(-'⚙ Parámetros'!C18*(T21-'⚙ Parámetros'!B18))),'⚙ Parámetros'!G18/(1+2^(-'⚙ Parámetros'!F18*(T21-'⚙ Parámetros'!E18))),1)*T21+20/100*MAX('⚙ Parámetros'!D18/(1+2^(-'⚙ Parámetros'!C18*(U21-'⚙ Parámetros'!B18))),'⚙ Parámetros'!G18/(1+2^(-'⚙ Parámetros'!F18*(U21-'⚙ Parámetros'!E18))),1)*U21)/(30/100*MAX('⚙ Parámetros'!D18/(1+2^(-'⚙ Parámetros'!C18*(R21-'⚙ Parámetros'!B18))),'⚙ Parámetros'!G18/(1+2^(-'⚙ Parámetros'!F18*(R21-'⚙ Parámetros'!E18))),1)+30/100*MAX('⚙ Parámetros'!D18/(1+2^(-'⚙ Parámetros'!C18*(S21-'⚙ Parámetros'!B18))),'⚙ Parámetros'!G18/(1+2^(-'⚙ Parámetros'!F18*(S21-'⚙ Parámetros'!E18))),1)+20/100*MAX('⚙ Parámetros'!D18/(1+2^(-'⚙ Parámetros'!C18*(T21-'⚙ Parámetros'!B18))),'⚙ Parámetros'!G18/(1+2^(-'⚙ Parámetros'!F18*(T21-'⚙ Parámetros'!E18))),1)+20/100*MAX('⚙ Parámetros'!D18/(1+2^(-'⚙ Parámetros'!C18*(U21-'⚙ Parámetros'!B18))),'⚙ Parámetros'!G18/(1+2^(-'⚙ Parámetros'!F18*(U21-'⚙ Parámetros'!E18))),1)),0) -> 5 | AF21: =IFERROR((30/100*MAX('⚙ Parámetros'!D19/(1+2^(-'⚙ Parámetros'!C19*(V21-'⚙ Parámetros'!B19))),'⚙ Parámetros'!G19/(1+2^(-'⚙ Parámetros'!F19*(V21-'⚙ Parámetros'!E19))),1)*V21+35/100*MAX('⚙ Parámetros'!D19/(1+2^(-'⚙ Parámetros'!C19*(W21-'⚙ Parámetros'!B19))),'⚙ Parámetros'!G19/(1+2^(-'⚙ Parámetros'!F19*(W21-'⚙ Parámetros'!E19))),1)*W21+35/100*MAX('⚙ Parámetros'!D19/(1+2^(-'⚙ Parámetros'!C19*(X21-'⚙ Parámetros'!B19))),'⚙ Parámetros'!G19/(1+2^(-'⚙ Parámetros'!F19*(X21-'⚙ Parámetros'!E19))),1)*X21)/(30/100*MAX('⚙ Parámetros'!D19/(1+2^(-'⚙ Parámetros'!C19*(V21-'⚙ Parámetros'!B19))),'⚙ Parámetros'!G19/(1+2^(-'⚙ Parámetros'!F19*(V21-'⚙ Parámetros'!E19))),1)+35/100*MAX('⚙ Parámetros'!D19/(1+2^(-'⚙ Parámetros'!C19*(W21-'⚙ Parámetros'!B19))),'⚙ Parámetros'!G19/(1+2^(-'⚙ Parámetros'!F19*(W21-'⚙ Parámetros'!E19))),1)+35/100*MAX('⚙ Parámetros'!D19/(1+2^(-'⚙ Parámetros'!C19*(X21-'⚙ Parámetros'!B19))),'⚙ Parámetros'!G19/(1+2^(-'⚙ Parámetros'!F19*(X21-'⚙ Parámetros'!E19))),1)),0) -> 8.0351483 | AG21: =IFERROR((35/100*MAX('⚙ Parámetros'!D20/(1+2^(-'⚙ Parámetros'!C20*(Y21-'⚙ Parámetros'!B20))),'⚙ Parámetros'!G20/(1+2^(-'⚙ Parámetros'!F20*(Y21-'⚙ Parámetros'!E20))),1)*Y21+35/100*MAX('⚙ Parámetros'!D20/(1+2^(-'⚙ Parámetros'!C20*(Z21-'⚙ Parámetros'!B20))),'⚙ Parámetros'!G20/(1+2^(-'⚙ Parámetros'!F20*(Z21-'⚙ Parámetros'!E20))),1)*Z21+30/100*MAX('⚙ Parámetros'!D20/(1+2^(-'⚙ Parámetros'!C20*(AA21-'⚙ Parámetros'!B20))),'⚙ Parámetros'!G20/(1+2^(-'⚙ Parámetros'!F20*(AA21-'⚙ Parámetros'!E20))),1)*AA21)/(35/100*MAX('⚙ Parámetros'!D20/(1+2^(-'⚙ Parámetros'!C20*(Y21-'⚙ Parámetros'!B20))),'⚙ Parámetros'!G20/(1+2^(-'⚙ Parámetros'!F20*(Y21-'⚙ Parámetros'!E20))),1)+35/100*MAX('⚙ Parámetros'!D20/(1+2^(-'⚙ Parámetros'!C20*(Z21-'⚙ Parámetros'!B20))),'⚙ Parámetros'!G20/(1+2^(-'⚙ Parámetros'!F20*(Z21-'⚙ Parámetros'!E20))),1)+30/100*MAX('⚙ Parámetros'!D20/(1+2^(-'⚙ Parámetros'!C20*(AA21-'⚙ Parámetros'!B20))),'⚙ Parámetros'!G20/(1+2^(-'⚙ Parámetros'!F20*(AA21-'⚙ Parámetros'!E20))),1)),0) -> 3.7272727 | AH21: =('⚙ Parámetros'!B5/100*AB21+'⚙ Parámetros'!B6/100*AC21+'⚙ Parámetros'!B7/100*AD21+'⚙ Parámetros'!B8/100*AE21+'⚙ Parámetros'!B9/100*AF21+'⚙ Parámetros'!B10/100*AG21) -> 5.7375513 | AI21: =MIN(1+MAX(0,TODAY()-DATE(2024,9,12))/365*'⚙ Parámetros'!B33,'⚙ Parámetros'!B34) -> 1.25 | AJ21: =IFERROR(MIN(AH21*AI21,10),0) -> 7.1719391 | AK21: =IF(AB21>='⚙ Parámetros'!B23,"⚑ AUTO-PRIOR.(D1≥8)",IF(AJ21>='⚙ Parámetros'!B23,"PRIORITARIO",IF(AJ21>='⚙ Parámetros'!B24,"ALTA PRIORIDAD",IF(AJ21>='⚙ Parámetros'!B25,"PRIORIDAD MEDIA",IF(AJ21>='⚙ Parámetros'!B26,"BAJA PRIORIDAD","DESCARTAR"))))) -> ALTA PRIORIDAD | AL21: =IF(AB21>=8,"SÍ ⚑","—") -> SÍ ⚑ | AM21: 13 | AN21: =IF(AM21="","—",IF(AM21<'⚙ Parámetros'!B29,"🟢 Corto",IF(AM21<'⚙ Parámetros'!B30,"🟡 Medio","🔴 Largo"))) -> 🟢 Corto
A22: 18 | B22: MPG-CAL-019_01 Formulario pedidos calidad | C22: Regulatorio y calidad | D22: Marc Bometon | E22: 14/01/2026 | F22: 6 | G22: 5 | H22: 1 | I22: 5 | J22: 1 | K22: 1 | L22: 8 | M22: 3 | N22: 7 | O22: 1 | P22: 1 | Q22: 8 | R22: 9 | S22: 9 | T22: 5 | U22: 5 | V22: 8 | W22: 6 | X22: 9 | Y22: 4 | Z22: 2 | AA22: 5 | AB22: =IFERROR((30/100*MAX('⚙ Parámetros'!D15/(1+2^(-'⚙ Parámetros'!C15*(F22-'⚙ Parámetros'!B15))),'⚙ Parámetros'!G15/(1+2^(-'⚙ Parámetros'!F15*(F22-'⚙ Parámetros'!E15))),1)*F22+30/100*MAX('⚙ Parámetros'!D15/(1+2^(-'⚙ Parámetros'!C15*(G22-'⚙ Parámetros'!B15))),'⚙ Parámetros'!G15/(1+2^(-'⚙ Parámetros'!F15*(G22-'⚙ Parámetros'!E15))),1)*G22+20/100*MAX('⚙ Parámetros'!D15/(1+2^(-'⚙ Parámetros'!C15*(H22-'⚙ Parámetros'!B15))),'⚙ Parámetros'!G15/(1+2^(-'⚙ Parámetros'!F15*(H22-'⚙ Parámetros'!E15))),1)*H22+20/100*MAX('⚙ Parámetros'!D15/(1+2^(-'⚙ Parámetros'!C15*(I22-'⚙ Parámetros'!B15))),'⚙ Parámetros'!G15/(1+2^(-'⚙ Parámetros'!F15*(I22-'⚙ Parámetros'!E15))),1)*I22)/(30/100*MAX('⚙ Parámetros'!D15/(1+2^(-'⚙ Parámetros'!C15*(F22-'⚙ Parámetros'!B15))),'⚙ Parámetros'!G15/(1+2^(-'⚙ Parámetros'!F15*(F22-'⚙ Parámetros'!E15))),1)+30/100*MAX('⚙ Parámetros'!D15/(1+2^(-'⚙ Parámetros'!C15*(G22-'⚙ Parámetros'!B15))),'⚙ Parámetros'!G15/(1+2^(-'⚙ Parámetros'!F15*(G22-'⚙ Parámetros'!E15))),1)+20/100*MAX('⚙ Parámetros'!D15/(1+2^(-'⚙ Parámetros'!C15*(H22-'⚙ Parámetros'!B15))),'⚙ Parámetros'!G15/(1+2^(-'⚙ Parámetros'!F15*(H22-'⚙ Parámetros'!E15))),1)+20/100*MAX('⚙ Parámetros'!D15/(1+2^(-'⚙ Parámetros'!C15*(I22-'⚙ Parámetros'!B15))),'⚙ Parámetros'!G15/(1+2^(-'⚙ Parámetros'!F15*(I22-'⚙ Parámetros'!E15))),1)),0) -> 4.8311688 | AC22: =IFERROR((35/100*MAX('⚙ Parámetros'!D16/(1+2^(-'⚙ Parámetros'!C16*(J22-'⚙ Parámetros'!B16))),'⚙ Parámetros'!G16/(1+2^(-'⚙ Parámetros'!F16*(J22-'⚙ Parámetros'!E16))),1)*J22+25/100*MAX('⚙ Parámetros'!D16/(1+2^(-'⚙ Parámetros'!C16*(K22-'⚙ Parámetros'!B16))),'⚙ Parámetros'!G16/(1+2^(-'⚙ Parámetros'!F16*(K22-'⚙ Parámetros'!E16))),1)*K22+20/100*MAX('⚙ Parámetros'!D16/(1+2^(-'⚙ Parámetros'!C16*(L22-'⚙ Parámetros'!B16))),'⚙ Parámetros'!G16/(1+2^(-'⚙ Parámetros'!F16*(L22-'⚙ Parámetros'!E16))),1)*L22+20/100*MAX('⚙ Parámetros'!D16/(1+2^(-'⚙ Parámetros'!C16*(M22-'⚙ Parámetros'!B16))),'⚙ Parámetros'!G16/(1+2^(-'⚙ Parámetros'!F16*(M22-'⚙ Parámetros'!E16))),1)*M22)/(35/100*MAX('⚙ Parámetros'!D16/(1+2^(-'⚙ Parámetros'!C16*(J22-'⚙ Parámetros'!B16))),'⚙ Parámetros'!G16/(1+2^(-'⚙ Parámetros'!F16*(J22-'⚙ Parámetros'!E16))),1)+25/100*MAX('⚙ Parámetros'!D16/(1+2^(-'⚙ Parámetros'!C16*(K22-'⚙ Parámetros'!B16))),'⚙ Parámetros'!G16/(1+2^(-'⚙ Parámetros'!F16*(K22-'⚙ Parámetros'!E16))),1)+20/100*MAX('⚙ Parámetros'!D16/(1+2^(-'⚙ Parámetros'!C16*(L22-'⚙ Parámetros'!B16))),'⚙ Parámetros'!G16/(1+2^(-'⚙ Parámetros'!F16*(L22-'⚙ Parámetros'!E16))),1)+20/100*MAX('⚙ Parámetros'!D16/(1+2^(-'⚙ Parámetros'!C16*(M22-'⚙ Parámetros'!B16))),'⚙ Parámetros'!G16/(1+2^(-'⚙ Parámetros'!F16*(M22-'⚙ Parámetros'!E16))),1)),0) -> 4.9411765 | AD22: =IFERROR((30/100*MAX('⚙ Parámetros'!D17/(1+2^(-'⚙ Parámetros'!C17*(N22-'⚙ Parámetros'!B17))),'⚙ Parámetros'!G17/(1+2^(-'⚙ Parámetros'!F17*(N22-'⚙ Parámetros'!E17))),1)*N22+25/100*MAX('⚙ Parámetros'!D17/(1+2^(-'⚙ Parámetros'!C17*(O22-'⚙ Parámetros'!B17))),'⚙ Parámetros'!G17/(1+2^(-'⚙ Parámetros'!F17*(O22-'⚙ Parámetros'!E17))),1)*O22+25/100*MAX('⚙ Parámetros'!D17/(1+2^(-'⚙ Parámetros'!C17*(P22-'⚙ Parámetros'!B17))),'⚙ Parámetros'!G17/(1+2^(-'⚙ Parámetros'!F17*(P22-'⚙ Parámetros'!E17))),1)*P22+20/100*MAX('⚙ Parámetros'!D17/(1+2^(-'⚙ Parámetros'!C17*(Q22-'⚙ Parámetros'!B17))),'⚙ Parámetros'!G17/(1+2^(-'⚙ Parámetros'!F17*(Q22-'⚙ Parámetros'!E17))),1)*Q22)/(30/100*MAX('⚙ Parámetros'!D17/(1+2^(-'⚙ Parámetros'!C17*(N22-'⚙ Parámetros'!B17))),'⚙ Parámetros'!G17/(1+2^(-'⚙ Parámetros'!F17*(N22-'⚙ Parámetros'!E17))),1)+25/100*MAX('⚙ Parámetros'!D17/(1+2^(-'⚙ Parámetros'!C17*(O22-'⚙ Parámetros'!B17))),'⚙ Parámetros'!G17/(1+2^(-'⚙ Parámetros'!F17*(O22-'⚙ Parámetros'!E17))),1)+25/100*MAX('⚙ Parámetros'!D17/(1+2^(-'⚙ Parámetros'!C17*(P22-'⚙ Parámetros'!B17))),'⚙ Parámetros'!G17/(1+2^(-'⚙ Parámetros'!F17*(P22-'⚙ Parámetros'!E17))),1)+20/100*MAX('⚙ Parámetros'!D17/(1+2^(-'⚙ Parámetros'!C17*(Q22-'⚙ Parámetros'!B17))),'⚙ Parámetros'!G17/(1+2^(-'⚙ Parámetros'!F17*(Q22-'⚙ Parámetros'!E17))),1)),0) -> 5.952381 | AE22: =IFERROR((30/100*MAX('⚙ Parámetros'!D18/(1+2^(-'⚙ Parámetros'!C18*(R22-'⚙ Parámetros'!B18))),'⚙ Parámetros'!G18/(1+2^(-'⚙ Parámetros'!F18*(R22-'⚙ Parámetros'!E18))),1)*R22+30/100*MAX('⚙ Parámetros'!D18/(1+2^(-'⚙ Parámetros'!C18*(S22-'⚙ Parámetros'!B18))),'⚙ Parámetros'!G18/(1+2^(-'⚙ Parámetros'!F18*(S22-'⚙ Parámetros'!E18))),1)*S22+20/100*MAX('⚙ Parámetros'!D18/(1+2^(-'⚙ Parámetros'!C18*(T22-'⚙ Parámetros'!B18))),'⚙ Parámetros'!G18/(1+2^(-'⚙ Parámetros'!F18*(T22-'⚙ Parámetros'!E18))),1)*T22+20/100*MAX('⚙ Parámetros'!D18/(1+2^(-'⚙ Parámetros'!C18*(U22-'⚙ Parámetros'!B18))),'⚙ Parámetros'!G18/(1+2^(-'⚙ Parámetros'!F18*(U22-'⚙ Parámetros'!E18))),1)*U22)/(30/100*MAX('⚙ Parámetros'!D18/(1+2^(-'⚙ Parámetros'!C18*(R22-'⚙ Parámetros'!B18))),'⚙ Parámetros'!G18/(1+2^(-'⚙ Parámetros'!F18*(R22-'⚙ Parámetros'!E18))),1)+30/100*MAX('⚙ Parámetros'!D18/(1+2^(-'⚙ Parámetros'!C18*(S22-'⚙ Parámetros'!B18))),'⚙ Parámetros'!G18/(1+2^(-'⚙ Parámetros'!F18*(S22-'⚙ Parámetros'!E18))),1)+20/100*MAX('⚙ Parámetros'!D18/(1+2^(-'⚙ Parámetros'!C18*(T22-'⚙ Parámetros'!B18))),'⚙ Parámetros'!G18/(1+2^(-'⚙ Parámetros'!F18*(T22-'⚙ Parámetros'!E18))),1)+20/100*MAX('⚙ Parámetros'!D18/(1+2^(-'⚙ Parámetros'!C18*(U22-'⚙ Parámetros'!B18))),'⚙ Parámetros'!G18/(1+2^(-'⚙ Parámetros'!F18*(U22-'⚙ Parámetros'!E18))),1)),0) -> 8.180106 | AF22: =IFERROR((30/100*MAX('⚙ Parámetros'!D19/(1+2^(-'⚙ Parámetros'!C19*(V22-'⚙ Parámetros'!B19))),'⚙ Parámetros'!G19/(1+2^(-'⚙ Parámetros'!F19*(V22-'⚙ Parámetros'!E19))),1)*V22+35/100*MAX('⚙ Parámetros'!D19/(1+2^(-'⚙ Parámetros'!C19*(W22-'⚙ Parámetros'!B19))),'⚙ Parámetros'!G19/(1+2^(-'⚙ Parámetros'!F19*(W22-'⚙ Parámetros'!E19))),1)*W22+35/100*MAX('⚙ Parámetros'!D19/(1+2^(-'⚙ Parámetros'!C19*(X22-'⚙ Parámetros'!B19))),'⚙ Parámetros'!G19/(1+2^(-'⚙ Parámetros'!F19*(X22-'⚙ Parámetros'!E19))),1)*X22)/(30/100*MAX('⚙ Parámetros'!D19/(1+2^(-'⚙ Parámetros'!C19*(V22-'⚙ Parámetros'!B19))),'⚙ Parámetros'!G19/(1+2^(-'⚙ Parámetros'!F19*(V22-'⚙ Parámetros'!E19))),1)+35/100*MAX('⚙ Parámetros'!D19/(1+2^(-'⚙ Parámetros'!C19*(W22-'⚙ Parámetros'!B19))),'⚙ Parámetros'!G19/(1+2^(-'⚙ Parámetros'!F19*(W22-'⚙ Parámetros'!E19))),1)+35/100*MAX('⚙ Parámetros'!D19/(1+2^(-'⚙ Parámetros'!C19*(X22-'⚙ Parámetros'!B19))),'⚙ Parámetros'!G19/(1+2^(-'⚙ Parámetros'!F19*(X22-'⚙ Parámetros'!E19))),1)),0) -> 8.0351483 | AG22: =IFERROR((35/100*MAX('⚙ Parámetros'!D20/(1+2^(-'⚙ Parámetros'!C20*(Y22-'⚙ Parámetros'!B20))),'⚙ Parámetros'!G20/(1+2^(-'⚙ Parámetros'!F20*(Y22-'⚙ Parámetros'!E20))),1)*Y22+35/100*MAX('⚙ Parámetros'!D20/(1+2^(-'⚙ Parámetros'!C20*(Z22-'⚙ Parámetros'!B20))),'⚙ Parámetros'!G20/(1+2^(-'⚙ Parámetros'!F20*(Z22-'⚙ Parámetros'!E20))),1)*Z22+30/100*MAX('⚙ Parámetros'!D20/(1+2^(-'⚙ Parámetros'!C20*(AA22-'⚙ Parámetros'!B20))),'⚙ Parámetros'!G20/(1+2^(-'⚙ Parámetros'!F20*(AA22-'⚙ Parámetros'!E20))),1)*AA22)/(35/100*MAX('⚙ Parámetros'!D20/(1+2^(-'⚙ Parámetros'!C20*(Y22-'⚙ Parámetros'!B20))),'⚙ Parámetros'!G20/(1+2^(-'⚙ Parámetros'!F20*(Y22-'⚙ Parámetros'!E20))),1)+35/100*MAX('⚙ Parámetros'!D20/(1+2^(-'⚙ Parámetros'!C20*(Z22-'⚙ Parámetros'!B20))),'⚙ Parámetros'!G20/(1+2^(-'⚙ Parámetros'!F20*(Z22-'⚙ Parámetros'!E20))),1)+30/100*MAX('⚙ Parámetros'!D20/(1+2^(-'⚙ Parámetros'!C20*(AA22-'⚙ Parámetros'!B20))),'⚙ Parámetros'!G20/(1+2^(-'⚙ Parámetros'!F20*(AA22-'⚙ Parámetros'!E20))),1)),0) -> 3.7272727 | AH22: =('⚙ Parámetros'!B5/100*AB22+'⚙ Parámetros'!B6/100*AC22+'⚙ Parámetros'!B7/100*AD22+'⚙ Parámetros'!B8/100*AE22+'⚙ Parámetros'!B9/100*AF22+'⚙ Parámetros'!B10/100*AG22) -> 5.7113715 | AI22: =MIN(1+MAX(0,TODAY()-DATE(2026,1,14))/365*'⚙ Parámetros'!B33,'⚙ Parámetros'!B34) -> 1.0612329 | AJ22: =IFERROR(MIN(AH22*AI22,10),0) -> 6.0610952 | AK22: =IF(AB22>='⚙ Parámetros'!B23,"⚑ AUTO-PRIOR.(D1≥8)",IF(AJ22>='⚙ Parámetros'!B23,"PRIORITARIO",IF(AJ22>='⚙ Parámetros'!B24,"ALTA PRIORIDAD",IF(AJ22>='⚙ Parámetros'!B25,"PRIORIDAD MEDIA",IF(AJ22>='⚙ Parámetros'!B26,"BAJA PRIORIDAD","DESCARTAR"))))) -> PRIORIDAD MEDIA | AL22: =IF(AB22>=8,"SÍ ⚑","—") -> — | AM22: 43 | AN22: =IF(AM22="","—",IF(AM22<'⚙ Parámetros'!B29,"🟢 Corto",IF(AM22<'⚙ Parámetros'!B30,"🟡 Medio","🔴 Largo"))) -> 🟡 Medio
A23: 19 | B23: MPG-FIN-030 Integración para conciliación massiva de cobros | C23: Finanzas y control | D23: Joan Valverde | E23: 23/04/2026 | F23: 1 | G23: 1 | H23: 5 | I23: 1 | J23: 10 | K23: 1 | L23: 6 | M23: 9 | N23: 9 | O23: 8 | P23: 9 | Q23: 6 | R23: 5 | S23: 5 | T23: 5 | U23: 5 | V23: 5 | W23: 6 | X23: 3 | Y23: 4 | Z23: 2 | AA23: 8 | AB23: =IFERROR((30/100*MAX('⚙ Parámetros'!D15/(1+2^(-'⚙ Parámetros'!C15*(F23-'⚙ Parámetros'!B15))),'⚙ Parámetros'!G15/(1+2^(-'⚙ Parámetros'!F15*(F23-'⚙ Parámetros'!E15))),1)*F23+30/100*MAX('⚙ Parámetros'!D15/(1+2^(-'⚙ Parámetros'!C15*(G23-'⚙ Parámetros'!B15))),'⚙ Parámetros'!G15/(1+2^(-'⚙ Parámetros'!F15*(G23-'⚙ Parámetros'!E15))),1)*G23+20/100*MAX('⚙ Parámetros'!D15/(1+2^(-'⚙ Parámetros'!C15*(H23-'⚙ Parámetros'!B15))),'⚙ Parámetros'!G15/(1+2^(-'⚙ Parámetros'!F15*(H23-'⚙ Parámetros'!E15))),1)*H23+20/100*MAX('⚙ Parámetros'!D15/(1+2^(-'⚙ Parámetros'!C15*(I23-'⚙ Parámetros'!B15))),'⚙ Parámetros'!G15/(1+2^(-'⚙ Parámetros'!F15*(I23-'⚙ Parámetros'!E15))),1)*I23)/(30/100*MAX('⚙ Parámetros'!D15/(1+2^(-'⚙ Parámetros'!C15*(F23-'⚙ Parámetros'!B15))),'⚙ Parámetros'!G15/(1+2^(-'⚙ Parámetros'!F15*(F23-'⚙ Parámetros'!E15))),1)+30/100*MAX('⚙ Parámetros'!D15/(1+2^(-'⚙ Parámetros'!C15*(G23-'⚙ Parámetros'!B15))),'⚙ Parámetros'!G15/(1+2^(-'⚙ Parámetros'!F15*(G23-'⚙ Parámetros'!E15))),1)+20/100*MAX('⚙ Parámetros'!D15/(1+2^(-'⚙ Parámetros'!C15*(H23-'⚙ Parámetros'!B15))),'⚙ Parámetros'!G15/(1+2^(-'⚙ Parámetros'!F15*(H23-'⚙ Parámetros'!E15))),1)+20/100*MAX('⚙ Parámetros'!D15/(1+2^(-'⚙ Parámetros'!C15*(I23-'⚙ Parámetros'!B15))),'⚙ Parámetros'!G15/(1+2^(-'⚙ Parámetros'!F15*(I23-'⚙ Parámetros'!E15))),1)),0) -> 2.1428571 | AC23: =IFERROR((35/100*MAX('⚙ Parámetros'!D16/(1+2^(-'⚙ Parámetros'!C16*(J23-'⚙ Parámetros'!B16))),'⚙ Parámetros'!G16/(1+2^(-'⚙ Parámetros'!F16*(J23-'⚙ Parámetros'!E16))),1)*J23+25/100*MAX('⚙ Parámetros'!D16/(1+2^(-'⚙ Parámetros'!C16*(K23-'⚙ Parámetros'!B16))),'⚙ Parámetros'!G16/(1+2^(-'⚙ Parámetros'!F16*(K23-'⚙ Parámetros'!E16))),1)*K23+20/100*MAX('⚙ Parámetros'!D16/(1+2^(-'⚙ Parámetros'!C16*(L23-'⚙ Parámetros'!B16))),'⚙ Parámetros'!G16/(1+2^(-'⚙ Parámetros'!F16*(L23-'⚙ Parámetros'!E16))),1)*L23+20/100*MAX('⚙ Parámetros'!D16/(1+2^(-'⚙ Parámetros'!C16*(M23-'⚙ Parámetros'!B16))),'⚙ Parámetros'!G16/(1+2^(-'⚙ Parámetros'!F16*(M23-'⚙ Parámetros'!E16))),1)*M23)/(35/100*MAX('⚙ Parámetros'!D16/(1+2^(-'⚙ Parámetros'!C16*(J23-'⚙ Parámetros'!B16))),'⚙ Parámetros'!G16/(1+2^(-'⚙ Parámetros'!F16*(J23-'⚙ Parámetros'!E16))),1)+25/100*MAX('⚙ Parámetros'!D16/(1+2^(-'⚙ Parámetros'!C16*(K23-'⚙ Parámetros'!B16))),'⚙ Parámetros'!G16/(1+2^(-'⚙ Parámetros'!F16*(K23-'⚙ Parámetros'!E16))),1)+20/100*MAX('⚙ Parámetros'!D16/(1+2^(-'⚙ Parámetros'!C16*(L23-'⚙ Parámetros'!B16))),'⚙ Parámetros'!G16/(1+2^(-'⚙ Parámetros'!F16*(L23-'⚙ Parámetros'!E16))),1)+20/100*MAX('⚙ Parámetros'!D16/(1+2^(-'⚙ Parámetros'!C16*(M23-'⚙ Parámetros'!B16))),'⚙ Parámetros'!G16/(1+2^(-'⚙ Parámetros'!F16*(M23-'⚙ Parámetros'!E16))),1)),0) -> 8.907435 | AD23: =IFERROR((30/100*MAX('⚙ Parámetros'!D17/(1+2^(-'⚙ Parámetros'!C17*(N23-'⚙ Parámetros'!B17))),'⚙ Parámetros'!G17/(1+2^(-'⚙ Parámetros'!F17*(N23-'⚙ Parámetros'!E17))),1)*N23+25/100*MAX('⚙ Parámetros'!D17/(1+2^(-'⚙ Parámetros'!C17*(O23-'⚙ Parámetros'!B17))),'⚙ Parámetros'!G17/(1+2^(-'⚙ Parámetros'!F17*(O23-'⚙ Parámetros'!E17))),1)*O23+25/100*MAX('⚙ Parámetros'!D17/(1+2^(-'⚙ Parámetros'!C17*(P23-'⚙ Parámetros'!B17))),'⚙ Parámetros'!G17/(1+2^(-'⚙ Parámetros'!F17*(P23-'⚙ Parámetros'!E17))),1)*P23+20/100*MAX('⚙ Parámetros'!D17/(1+2^(-'⚙ Parámetros'!C17*(Q23-'⚙ Parámetros'!B17))),'⚙ Parámetros'!G17/(1+2^(-'⚙ Parámetros'!F17*(Q23-'⚙ Parámetros'!E17))),1)*Q23)/(30/100*MAX('⚙ Parámetros'!D17/(1+2^(-'⚙ Parámetros'!C17*(N23-'⚙ Parámetros'!B17))),'⚙ Parámetros'!G17/(1+2^(-'⚙ Parámetros'!F17*(N23-'⚙ Parámetros'!E17))),1)+25/100*MAX('⚙ Parámetros'!D17/(1+2^(-'⚙ Parámetros'!C17*(O23-'⚙ Parámetros'!B17))),'⚙ Parámetros'!G17/(1+2^(-'⚙ Parámetros'!F17*(O23-'⚙ Parámetros'!E17))),1)+25/100*MAX('⚙ Parámetros'!D17/(1+2^(-'⚙ Parámetros'!C17*(P23-'⚙ Parámetros'!B17))),'⚙ Parámetros'!G17/(1+2^(-'⚙ Parámetros'!F17*(P23-'⚙ Parámetros'!E17))),1)+20/100*MAX('⚙ Parámetros'!D17/(1+2^(-'⚙ Parámetros'!C17*(Q23-'⚙ Parámetros'!B17))),'⚙ Parámetros'!G17/(1+2^(-'⚙ Parámetros'!F17*(Q23-'⚙ Parámetros'!E17))),1)),0) -> 8.512 | AE23: =IFERROR((30/100*MAX('⚙ Parámetros'!D18/(1+2^(-'⚙ Parámetros'!C18*(R23-'⚙ Parámetros'!B18))),'⚙ Parámetros'!G18/(1+2^(-'⚙ Parámetros'!F18*(R23-'⚙ Parámetros'!E18))),1)*R23+30/100*MAX('⚙ Parámetros'!D18/(1+2^(-'⚙ Parámetros'!C18*(S23-'⚙ Parámetros'!B18))),'⚙ Parámetros'!G18/(1+2^(-'⚙ Parámetros'!F18*(S23-'⚙ Parámetros'!E18))),1)*S23+20/100*MAX('⚙ Parámetros'!D18/(1+2^(-'⚙ Parámetros'!C18*(T23-'⚙ Parámetros'!B18))),'⚙ Parámetros'!G18/(1+2^(-'⚙ Parámetros'!F18*(T23-'⚙ Parámetros'!E18))),1)*T23+20/100*MAX('⚙ Parámetros'!D18/(1+2^(-'⚙ Parámetros'!C18*(U23-'⚙ Parámetros'!B18))),'⚙ Parámetros'!G18/(1+2^(-'⚙ Parámetros'!F18*(U23-'⚙ Parámetros'!E18))),1)*U23)/(30/100*MAX('⚙ Parámetros'!D18/(1+2^(-'⚙ Parámetros'!C18*(R23-'⚙ Parámetros'!B18))),'⚙ Parámetros'!G18/(1+2^(-'⚙ Parámetros'!F18*(R23-'⚙ Parámetros'!E18))),1)+30/100*MAX('⚙ Parámetros'!D18/(1+2^(-'⚙ Parámetros'!C18*(S23-'⚙ Parámetros'!B18))),'⚙ Parámetros'!G18/(1+2^(-'⚙ Parámetros'!F18*(S23-'⚙ Parámetros'!E18))),1)+20/100*MAX('⚙ Parámetros'!D18/(1+2^(-'⚙ Parámetros'!C18*(T23-'⚙ Parámetros'!B18))),'⚙ Parámetros'!G18/(1+2^(-'⚙ Parámetros'!F18*(T23-'⚙ Parámetros'!E18))),1)+20/100*MAX('⚙ Parámetros'!D18/(1+2^(-'⚙ Parámetros'!C18*(U23-'⚙ Parámetros'!B18))),'⚙ Parámetros'!G18/(1+2^(-'⚙ Parámetros'!F18*(U23-'⚙ Parámetros'!E18))),1)),0) -> 5 | AF23: =IFERROR((30/100*MAX('⚙ Parámetros'!D19/(1+2^(-'⚙ Parámetros'!C19*(V23-'⚙ Parámetros'!B19))),'⚙ Parámetros'!G19/(1+2^(-'⚙ Parámetros'!F19*(V23-'⚙ Parámetros'!E19))),1)*V23+35/100*MAX('⚙ Parámetros'!D19/(1+2^(-'⚙ Parámetros'!C19*(W23-'⚙ Parámetros'!B19))),'⚙ Parámetros'!G19/(1+2^(-'⚙ Parámetros'!F19*(W23-'⚙ Parámetros'!E19))),1)*W23+35/100*MAX('⚙ Parámetros'!D19/(1+2^(-'⚙ Parámetros'!C19*(X23-'⚙ Parámetros'!B19))),'⚙ Parámetros'!G19/(1+2^(-'⚙ Parámetros'!F19*(X23-'⚙ Parámetros'!E19))),1)*X23)/(30/100*MAX('⚙ Parámetros'!D19/(1+2^(-'⚙ Parámetros'!C19*(V23-'⚙ Parámetros'!B19))),'⚙ Parámetros'!G19/(1+2^(-'⚙ Parámetros'!F19*(V23-'⚙ Parámetros'!E19))),1)+35/100*MAX('⚙ Parámetros'!D19/(1+2^(-'⚙ Parámetros'!C19*(W23-'⚙ Parámetros'!B19))),'⚙ Parámetros'!G19/(1+2^(-'⚙ Parámetros'!F19*(W23-'⚙ Parámetros'!E19))),1)+35/100*MAX('⚙ Parámetros'!D19/(1+2^(-'⚙ Parámetros'!C19*(X23-'⚙ Parámetros'!B19))),'⚙ Parámetros'!G19/(1+2^(-'⚙ Parámetros'!F19*(X23-'⚙ Parámetros'!E19))),1)),0) -> 5.0782123 | AG23: =IFERROR((35/100*MAX('⚙ Parámetros'!D20/(1+2^(-'⚙ Parámetros'!C20*(Y23-'⚙ Parámetros'!B20))),'⚙ Parámetros'!G20/(1+2^(-'⚙ Parámetros'!F20*(Y23-'⚙ Parámetros'!E20))),1)*Y23+35/100*MAX('⚙ Parámetros'!D20/(1+2^(-'⚙ Parámetros'!C20*(Z23-'⚙ Parámetros'!B20))),'⚙ Parámetros'!G20/(1+2^(-'⚙ Parámetros'!F20*(Z23-'⚙ Parámetros'!E20))),1)*Z23+30/100*MAX('⚙ Parámetros'!D20/(1+2^(-'⚙ Parámetros'!C20*(AA23-'⚙ Parámetros'!B20))),'⚙ Parámetros'!G20/(1+2^(-'⚙ Parámetros'!F20*(AA23-'⚙ Parámetros'!E20))),1)*AA23)/(35/100*MAX('⚙ Parámetros'!D20/(1+2^(-'⚙ Parámetros'!C20*(Y23-'⚙ Parámetros'!B20))),'⚙ Parámetros'!G20/(1+2^(-'⚙ Parámetros'!F20*(Y23-'⚙ Parámetros'!E20))),1)+35/100*MAX('⚙ Parámetros'!D20/(1+2^(-'⚙ Parámetros'!C20*(Z23-'⚙ Parámetros'!B20))),'⚙ Parámetros'!G20/(1+2^(-'⚙ Parámetros'!F20*(Z23-'⚙ Parámetros'!E20))),1)+30/100*MAX('⚙ Parámetros'!D20/(1+2^(-'⚙ Parámetros'!C20*(AA23-'⚙ Parámetros'!B20))),'⚙ Parámetros'!G20/(1+2^(-'⚙ Parámetros'!F20*(AA23-'⚙ Parámetros'!E20))),1)),0) -> 5.8125 | AH23: =('⚙ Parámetros'!B5/100*AB23+'⚙ Parámetros'!B6/100*AC23+'⚙ Parámetros'!B7/100*AD23+'⚙ Parámetros'!B8/100*AE23+'⚙ Parámetros'!B9/100*AF23+'⚙ Parámetros'!B10/100*AG23) -> 5.6995654 | AI23: =MIN(1+MAX(0,TODAY()-DATE(2026,4,23))/365*'⚙ Parámetros'!B33,'⚙ Parámetros'!B34) -> 1.0205479 | AJ23: =IFERROR(MIN(AH23*AI23,10),0) -> 5.8166797 | AK23: =IF(AB23>='⚙ Parámetros'!B23,"⚑ AUTO-PRIOR.(D1≥8)",IF(AJ23>='⚙ Parámetros'!B23,"PRIORITARIO",IF(AJ23>='⚙ Parámetros'!B24,"ALTA PRIORIDAD",IF(AJ23>='⚙ Parámetros'!B25,"PRIORIDAD MEDIA",IF(AJ23>='⚙ Parámetros'!B26,"BAJA PRIORIDAD","DESCARTAR"))))) -> PRIORIDAD MEDIA | AL23: =IF(AB23>=8,"SÍ ⚑","—") -> — | AM23: 32 | AN23: =IF(AM23="","—",IF(AM23<'⚙ Parámetros'!B29,"🟢 Corto",IF(AM23<'⚙ Parámetros'!B30,"🟡 Medio","🔴 Largo"))) -> 🟡 Medio
A24: 20 | B24: MPG-FIN-006_03 Problemas CYC_Mejoras | C24: Finanzas y control | D24: Alberto Fernández | E24: 17/03/2026 | F24: 9 | G24: 1 | H24: 5 | I24: 9 | J24: 1 | K24: 1 | L24: 1 | M24: 3 | N24: 1 | O24: 8 | P24: 7 | Q24: 6 | R24: 6 | S24: 6 | T24: 5 | U24: 5 | V24: 8 | W24: 4 | X24: 5 | Y24: 4 | Z24: 2 | AA24: 5 | AB24: =IFERROR((30/100*MAX('⚙ Parámetros'!D15/(1+2^(-'⚙ Parámetros'!C15*(F24-'⚙ Parámetros'!B15))),'⚙ Parámetros'!G15/(1+2^(-'⚙ Parámetros'!F15*(F24-'⚙ Parámetros'!E15))),1)*F24+30/100*MAX('⚙ Parámetros'!D15/(1+2^(-'⚙ Parámetros'!C15*(G24-'⚙ Parámetros'!B15))),'⚙ Parámetros'!G15/(1+2^(-'⚙ Parámetros'!F15*(G24-'⚙ Parámetros'!E15))),1)*G24+20/100*MAX('⚙ Parámetros'!D15/(1+2^(-'⚙ Parámetros'!C15*(H24-'⚙ Parámetros'!B15))),'⚙ Parámetros'!G15/(1+2^(-'⚙ Parámetros'!F15*(H24-'⚙ Parámetros'!E15))),1)*H24+20/100*MAX('⚙ Parámetros'!D15/(1+2^(-'⚙ Parámetros'!C15*(I24-'⚙ Parámetros'!B15))),'⚙ Parámetros'!G15/(1+2^(-'⚙ Parámetros'!F15*(I24-'⚙ Parámetros'!E15))),1)*I24)/(30/100*MAX('⚙ Parámetros'!D15/(1+2^(-'⚙ Parámetros'!C15*(F24-'⚙ Parámetros'!B15))),'⚙ Parámetros'!G15/(1+2^(-'⚙ Parámetros'!F15*(F24-'⚙ Parámetros'!E15))),1)+30/100*MAX('⚙ Parámetros'!D15/(1+2^(-'⚙ Parámetros'!C15*(G24-'⚙ Parámetros'!B15))),'⚙ Parámetros'!G15/(1+2^(-'⚙ Parámetros'!F15*(G24-'⚙ Parámetros'!E15))),1)+20/100*MAX('⚙ Parámetros'!D15/(1+2^(-'⚙ Parámetros'!C15*(H24-'⚙ Parámetros'!B15))),'⚙ Parámetros'!G15/(1+2^(-'⚙ Parámetros'!F15*(H24-'⚙ Parámetros'!E15))),1)+20/100*MAX('⚙ Parámetros'!D15/(1+2^(-'⚙ Parámetros'!C15*(I24-'⚙ Parámetros'!B15))),'⚙ Parámetros'!G15/(1+2^(-'⚙ Parámetros'!F15*(I24-'⚙ Parámetros'!E15))),1)),0) -> 8.2420645 | AC24: =IFERROR((35/100*MAX('⚙ Parámetros'!D16/(1+2^(-'⚙ Parámetros'!C16*(J24-'⚙ Parámetros'!B16))),'⚙ Parámetros'!G16/(1+2^(-'⚙ Parámetros'!F16*(J24-'⚙ Parámetros'!E16))),1)*J24+25/100*MAX('⚙ Parámetros'!D16/(1+2^(-'⚙ Parámetros'!C16*(K24-'⚙ Parámetros'!B16))),'⚙ Parámetros'!G16/(1+2^(-'⚙ Parámetros'!F16*(K24-'⚙ Parámetros'!E16))),1)*K24+20/100*MAX('⚙ Parámetros'!D16/(1+2^(-'⚙ Parámetros'!C16*(L24-'⚙ Parámetros'!B16))),'⚙ Parámetros'!G16/(1+2^(-'⚙ Parámetros'!F16*(L24-'⚙ Parámetros'!E16))),1)*L24+20/100*MAX('⚙ Parámetros'!D16/(1+2^(-'⚙ Parámetros'!C16*(M24-'⚙ Parámetros'!B16))),'⚙ Parámetros'!G16/(1+2^(-'⚙ Parámetros'!F16*(M24-'⚙ Parámetros'!E16))),1)*M24)/(35/100*MAX('⚙ Parámetros'!D16/(1+2^(-'⚙ Parámetros'!C16*(J24-'⚙ Parámetros'!B16))),'⚙ Parámetros'!G16/(1+2^(-'⚙ Parámetros'!F16*(J24-'⚙ Parámetros'!E16))),1)+25/100*MAX('⚙ Parámetros'!D16/(1+2^(-'⚙ Parámetros'!C16*(K24-'⚙ Parámetros'!B16))),'⚙ Parámetros'!G16/(1+2^(-'⚙ Parámetros'!F16*(K24-'⚙ Parámetros'!E16))),1)+20/100*MAX('⚙ Parámetros'!D16/(1+2^(-'⚙ Parámetros'!C16*(L24-'⚙ Parámetros'!B16))),'⚙ Parámetros'!G16/(1+2^(-'⚙ Parámetros'!F16*(L24-'⚙ Parámetros'!E16))),1)+20/100*MAX('⚙ Parámetros'!D16/(1+2^(-'⚙ Parámetros'!C16*(M24-'⚙ Parámetros'!B16))),'⚙ Parámetros'!G16/(1+2^(-'⚙ Parámetros'!F16*(M24-'⚙ Parámetros'!E16))),1)),0) -> 1.4 | AD24: =IFERROR((30/100*MAX('⚙ Parámetros'!D17/(1+2^(-'⚙ Parámetros'!C17*(N24-'⚙ Parámetros'!B17))),'⚙ Parámetros'!G17/(1+2^(-'⚙ Parámetros'!F17*(N24-'⚙ Parámetros'!E17))),1)*N24+25/100*MAX('⚙ Parámetros'!D17/(1+2^(-'⚙ Parámetros'!C17*(O24-'⚙ Parámetros'!B17))),'⚙ Parámetros'!G17/(1+2^(-'⚙ Parámetros'!F17*(O24-'⚙ Parámetros'!E17))),1)*O24+25/100*MAX('⚙ Parámetros'!D17/(1+2^(-'⚙ Parámetros'!C17*(P24-'⚙ Parámetros'!B17))),'⚙ Parámetros'!G17/(1+2^(-'⚙ Parámetros'!F17*(P24-'⚙ Parámetros'!E17))),1)*P24+20/100*MAX('⚙ Parámetros'!D17/(1+2^(-'⚙ Parámetros'!C17*(Q24-'⚙ Parámetros'!B17))),'⚙ Parámetros'!G17/(1+2^(-'⚙ Parámetros'!F17*(Q24-'⚙ Parámetros'!E17))),1)*Q24)/(30/100*MAX('⚙ Parámetros'!D17/(1+2^(-'⚙ Parámetros'!C17*(N24-'⚙ Parámetros'!B17))),'⚙ Parámetros'!G17/(1+2^(-'⚙ Parámetros'!F17*(N24-'⚙ Parámetros'!E17))),1)+25/100*MAX('⚙ Parámetros'!D17/(1+2^(-'⚙ Parámetros'!C17*(O24-'⚙ Parámetros'!B17))),'⚙ Parámetros'!G17/(1+2^(-'⚙ Parámetros'!F17*(O24-'⚙ Parámetros'!E17))),1)+25/100*MAX('⚙ Parámetros'!D17/(1+2^(-'⚙ Parámetros'!C17*(P24-'⚙ Parámetros'!B17))),'⚙ Parámetros'!G17/(1+2^(-'⚙ Parámetros'!F17*(P24-'⚙ Parámetros'!E17))),1)+20/100*MAX('⚙ Parámetros'!D17/(1+2^(-'⚙ Parámetros'!C17*(Q24-'⚙ Parámetros'!B17))),'⚙ Parámetros'!G17/(1+2^(-'⚙ Parámetros'!F17*(Q24-'⚙ Parámetros'!E17))),1)),0) -> 6.4768392 | AE24: =IFERROR((30/100*MAX('⚙ Parámetros'!D18/(1+2^(-'⚙ Parámetros'!C18*(R24-'⚙ Parámetros'!B18))),'⚙ Parámetros'!G18/(1+2^(-'⚙ Parámetros'!F18*(R24-'⚙ Parámetros'!E18))),1)*R24+30/100*MAX('⚙ Parámetros'!D18/(1+2^(-'⚙ Parámetros'!C18*(S24-'⚙ Parámetros'!B18))),'⚙ Parámetros'!G18/(1+2^(-'⚙ Parámetros'!F18*(S24-'⚙ Parámetros'!E18))),1)*S24+20/100*MAX('⚙ Parámetros'!D18/(1+2^(-'⚙ Parámetros'!C18*(T24-'⚙ Parámetros'!B18))),'⚙ Parámetros'!G18/(1+2^(-'⚙ Parámetros'!F18*(T24-'⚙ Parámetros'!E18))),1)*T24+20/100*MAX('⚙ Parámetros'!D18/(1+2^(-'⚙ Parámetros'!C18*(U24-'⚙ Parámetros'!B18))),'⚙ Parámetros'!G18/(1+2^(-'⚙ Parámetros'!F18*(U24-'⚙ Parámetros'!E18))),1)*U24)/(30/100*MAX('⚙ Parámetros'!D18/(1+2^(-'⚙ Parámetros'!C18*(R24-'⚙ Parámetros'!B18))),'⚙ Parámetros'!G18/(1+2^(-'⚙ Parámetros'!F18*(R24-'⚙ Parámetros'!E18))),1)+30/100*MAX('⚙ Parámetros'!D18/(1+2^(-'⚙ Parámetros'!C18*(S24-'⚙ Parámetros'!B18))),'⚙ Parámetros'!G18/(1+2^(-'⚙ Parámetros'!F18*(S24-'⚙ Parámetros'!E18))),1)+20/100*MAX('⚙ Parámetros'!D18/(1+2^(-'⚙ Parámetros'!C18*(T24-'⚙ Parámetros'!B18))),'⚙ Parámetros'!G18/(1+2^(-'⚙ Parámetros'!F18*(T24-'⚙ Parámetros'!E18))),1)+20/100*MAX('⚙ Parámetros'!D18/(1+2^(-'⚙ Parámetros'!C18*(U24-'⚙ Parámetros'!B18))),'⚙ Parámetros'!G18/(1+2^(-'⚙ Parámetros'!F18*(U24-'⚙ Parámetros'!E18))),1)),0) -> 5.6428571 | AF24: =IFERROR((30/100*MAX('⚙ Parámetros'!D19/(1+2^(-'⚙ Parámetros'!C19*(V24-'⚙ Parámetros'!B19))),'⚙ Parámetros'!G19/(1+2^(-'⚙ Parámetros'!F19*(V24-'⚙ Parámetros'!E19))),1)*V24+35/100*MAX('⚙ Parámetros'!D19/(1+2^(-'⚙ Parámetros'!C19*(W24-'⚙ Parámetros'!B19))),'⚙ Parámetros'!G19/(1+2^(-'⚙ Parámetros'!F19*(W24-'⚙ Parámetros'!E19))),1)*W24+35/100*MAX('⚙ Parámetros'!D19/(1+2^(-'⚙ Parámetros'!C19*(X24-'⚙ Parámetros'!B19))),'⚙ Parámetros'!G19/(1+2^(-'⚙ Parámetros'!F19*(X24-'⚙ Parámetros'!E19))),1)*X24)/(30/100*MAX('⚙ Parámetros'!D19/(1+2^(-'⚙ Parámetros'!C19*(V24-'⚙ Parámetros'!B19))),'⚙ Parámetros'!G19/(1+2^(-'⚙ Parámetros'!F19*(V24-'⚙ Parámetros'!E19))),1)+35/100*MAX('⚙ Parámetros'!D19/(1+2^(-'⚙ Parámetros'!C19*(W24-'⚙ Parámetros'!B19))),'⚙ Parámetros'!G19/(1+2^(-'⚙ Parámetros'!F19*(W24-'⚙ Parámetros'!E19))),1)+35/100*MAX('⚙ Parámetros'!D19/(1+2^(-'⚙ Parámetros'!C19*(X24-'⚙ Parámetros'!B19))),'⚙ Parámetros'!G19/(1+2^(-'⚙ Parámetros'!F19*(X24-'⚙ Parámetros'!E19))),1)),0) -> 6.1538462 | AG24: =IFERROR((35/100*MAX('⚙ Parámetros'!D20/(1+2^(-'⚙ Parámetros'!C20*(Y24-'⚙ Parámetros'!B20))),'⚙ Parámetros'!G20/(1+2^(-'⚙ Parámetros'!F20*(Y24-'⚙ Parámetros'!E20))),1)*Y24+35/100*MAX('⚙ Parámetros'!D20/(1+2^(-'⚙ Parámetros'!C20*(Z24-'⚙ Parámetros'!B20))),'⚙ Parámetros'!G20/(1+2^(-'⚙ Parámetros'!F20*(Z24-'⚙ Parámetros'!E20))),1)*Z24+30/100*MAX('⚙ Parámetros'!D20/(1+2^(-'⚙ Parámetros'!C20*(AA24-'⚙ Parámetros'!B20))),'⚙ Parámetros'!G20/(1+2^(-'⚙ Parámetros'!F20*(AA24-'⚙ Parámetros'!E20))),1)*AA24)/(35/100*MAX('⚙ Parámetros'!D20/(1+2^(-'⚙ Parámetros'!C20*(Y24-'⚙ Parámetros'!B20))),'⚙ Parámetros'!G20/(1+2^(-'⚙ Parámetros'!F20*(Y24-'⚙ Parámetros'!E20))),1)+35/100*MAX('⚙ Parámetros'!D20/(1+2^(-'⚙ Parámetros'!C20*(Z24-'⚙ Parámetros'!B20))),'⚙ Parámetros'!G20/(1+2^(-'⚙ Parámetros'!F20*(Z24-'⚙ Parámetros'!E20))),1)+30/100*MAX('⚙ Parámetros'!D20/(1+2^(-'⚙ Parámetros'!C20*(AA24-'⚙ Parámetros'!B20))),'⚙ Parámetros'!G20/(1+2^(-'⚙ Parámetros'!F20*(AA24-'⚙ Parámetros'!E20))),1)),0) -> 3.7272727 | AH24: =('⚙ Parámetros'!B5/100*AB24+'⚙ Parámetros'!B6/100*AC24+'⚙ Parámetros'!B7/100*AD24+'⚙ Parámetros'!B8/100*AE24+'⚙ Parámetros'!B9/100*AF24+'⚙ Parámetros'!B10/100*AG24) -> 5.6386965 | AI24: =MIN(1+MAX(0,TODAY()-DATE(2026,3,17))/365*'⚙ Parámetros'!B33,'⚙ Parámetros'!B34) -> 1.0357534 | AJ24: =IFERROR(MIN(AH24*AI24,10),0) -> 5.8402992 | AK24: =IF(AB24>='⚙ Parámetros'!B23,"⚑ AUTO-PRIOR.(D1≥8)",IF(AJ24>='⚙ Parámetros'!B23,"PRIORITARIO",IF(AJ24>='⚙ Parámetros'!B24,"ALTA PRIORIDAD",IF(AJ24>='⚙ Parámetros'!B25,"PRIORIDAD MEDIA",IF(AJ24>='⚙ Parámetros'!B26,"BAJA PRIORIDAD","DESCARTAR"))))) -> PRIORIDAD MEDIA | AL24: =IF(AB24>=8,"SÍ ⚑","—") -> SÍ ⚑ | AM24: 46 | AN24: =IF(AM24="","—",IF(AM24<'⚙ Parámetros'!B29,"🟢 Corto",IF(AM24<'⚙ Parámetros'!B30,"🟡 Medio","🔴 Largo"))) -> 🟡 Medio
A25: 21 | B25: MPG-LOG-043_03_1 Pesadas - Cancelación trabajos + ud. de fórmula | C25: Supply chain y logística | D25: Laura Ortíz | E25: 02/02/2026 | F25: 1 | G25: 7 | H25: 1 | I25: 1 | J25: 1 | K25: 1 | L25: 8 | M25: 3 | N25: 7 | O25: 1 | P25: 6 | Q25: 1 | R25: 9 | S25: 9 | T25: 5 | U25: 5 | V25: 8 | W25: 6 | X25: 9 | Y25: 4 | Z25: 2 | AA25: 5 | AB25: =IFERROR((30/100*MAX('⚙ Parámetros'!D15/(1+2^(-'⚙ Parámetros'!C15*(F25-'⚙ Parámetros'!B15))),'⚙ Parámetros'!G15/(1+2^(-'⚙ Parámetros'!F15*(F25-'⚙ Parámetros'!E15))),1)*F25+30/100*MAX('⚙ Parámetros'!D15/(1+2^(-'⚙ Parámetros'!C15*(G25-'⚙ Parámetros'!B15))),'⚙ Parámetros'!G15/(1+2^(-'⚙ Parámetros'!F15*(G25-'⚙ Parámetros'!E15))),1)*G25+20/100*MAX('⚙ Parámetros'!D15/(1+2^(-'⚙ Parámetros'!C15*(H25-'⚙ Parámetros'!B15))),'⚙ Parámetros'!G15/(1+2^(-'⚙ Parámetros'!F15*(H25-'⚙ Parámetros'!E15))),1)*H25+20/100*MAX('⚙ Parámetros'!D15/(1+2^(-'⚙ Parámetros'!C15*(I25-'⚙ Parámetros'!B15))),'⚙ Parámetros'!G15/(1+2^(-'⚙ Parámetros'!F15*(I25-'⚙ Parámetros'!E15))),1)*I25)/(30/100*MAX('⚙ Parámetros'!D15/(1+2^(-'⚙ Parámetros'!C15*(F25-'⚙ Parámetros'!B15))),'⚙ Parámetros'!G15/(1+2^(-'⚙ Parámetros'!F15*(F25-'⚙ Parámetros'!E15))),1)+30/100*MAX('⚙ Parámetros'!D15/(1+2^(-'⚙ Parámetros'!C15*(G25-'⚙ Parámetros'!B15))),'⚙ Parámetros'!G15/(1+2^(-'⚙ Parámetros'!F15*(G25-'⚙ Parámetros'!E15))),1)+20/100*MAX('⚙ Parámetros'!D15/(1+2^(-'⚙ Parámetros'!C15*(H25-'⚙ Parámetros'!B15))),'⚙ Parámetros'!G15/(1+2^(-'⚙ Parámetros'!F15*(H25-'⚙ Parámetros'!E15))),1)+20/100*MAX('⚙ Parámetros'!D15/(1+2^(-'⚙ Parámetros'!C15*(I25-'⚙ Parámetros'!B15))),'⚙ Parámetros'!G15/(1+2^(-'⚙ Parámetros'!F15*(I25-'⚙ Parámetros'!E15))),1)),0) -> 4.9512195 | AC25: =IFERROR((35/100*MAX('⚙ Parámetros'!D16/(1+2^(-'⚙ Parámetros'!C16*(J25-'⚙ Parámetros'!B16))),'⚙ Parámetros'!G16/(1+2^(-'⚙ Parámetros'!F16*(J25-'⚙ Parámetros'!E16))),1)*J25+25/100*MAX('⚙ Parámetros'!D16/(1+2^(-'⚙ Parámetros'!C16*(K25-'⚙ Parámetros'!B16))),'⚙ Parámetros'!G16/(1+2^(-'⚙ Parámetros'!F16*(K25-'⚙ Parámetros'!E16))),1)*K25+20/100*MAX('⚙ Parámetros'!D16/(1+2^(-'⚙ Parámetros'!C16*(L25-'⚙ Parámetros'!B16))),'⚙ Parámetros'!G16/(1+2^(-'⚙ Parámetros'!F16*(L25-'⚙ Parámetros'!E16))),1)*L25+20/100*MAX('⚙ Parámetros'!D16/(1+2^(-'⚙ Parámetros'!C16*(M25-'⚙ Parámetros'!B16))),'⚙ Parámetros'!G16/(1+2^(-'⚙ Parámetros'!F16*(M25-'⚙ Parámetros'!E16))),1)*M25)/(35/100*MAX('⚙ Parámetros'!D16/(1+2^(-'⚙ Parámetros'!C16*(J25-'⚙ Parámetros'!B16))),'⚙ Parámetros'!G16/(1+2^(-'⚙ Parámetros'!F16*(J25-'⚙ Parámetros'!E16))),1)+25/100*MAX('⚙ Parámetros'!D16/(1+2^(-'⚙ Parámetros'!C16*(K25-'⚙ Parámetros'!B16))),'⚙ Parámetros'!G16/(1+2^(-'⚙ Parámetros'!F16*(K25-'⚙ Parámetros'!E16))),1)+20/100*MAX('⚙ Parámetros'!D16/(1+2^(-'⚙ Parámetros'!C16*(L25-'⚙ Parámetros'!B16))),'⚙ Parámetros'!G16/(1+2^(-'⚙ Parámetros'!F16*(L25-'⚙ Parámetros'!E16))),1)+20/100*MAX('⚙ Parámetros'!D16/(1+2^(-'⚙ Parámetros'!C16*(M25-'⚙ Parámetros'!B16))),'⚙ Parámetros'!G16/(1+2^(-'⚙ Parámetros'!F16*(M25-'⚙ Parámetros'!E16))),1)),0) -> 4.9411765 | AD25: =IFERROR((30/100*MAX('⚙ Parámetros'!D17/(1+2^(-'⚙ Parámetros'!C17*(N25-'⚙ Parámetros'!B17))),'⚙ Parámetros'!G17/(1+2^(-'⚙ Parámetros'!F17*(N25-'⚙ Parámetros'!E17))),1)*N25+25/100*MAX('⚙ Parámetros'!D17/(1+2^(-'⚙ Parámetros'!C17*(O25-'⚙ Parámetros'!B17))),'⚙ Parámetros'!G17/(1+2^(-'⚙ Parámetros'!F17*(O25-'⚙ Parámetros'!E17))),1)*O25+25/100*MAX('⚙ Parámetros'!D17/(1+2^(-'⚙ Parámetros'!C17*(P25-'⚙ Parámetros'!B17))),'⚙ Parámetros'!G17/(1+2^(-'⚙ Parámetros'!F17*(P25-'⚙ Parámetros'!E17))),1)*P25+20/100*MAX('⚙ Parámetros'!D17/(1+2^(-'⚙ Parámetros'!C17*(Q25-'⚙ Parámetros'!B17))),'⚙ Parámetros'!G17/(1+2^(-'⚙ Parámetros'!F17*(Q25-'⚙ Parámetros'!E17))),1)*Q25)/(30/100*MAX('⚙ Parámetros'!D17/(1+2^(-'⚙ Parámetros'!C17*(N25-'⚙ Parámetros'!B17))),'⚙ Parámetros'!G17/(1+2^(-'⚙ Parámetros'!F17*(N25-'⚙ Parámetros'!E17))),1)+25/100*MAX('⚙ Parámetros'!D17/(1+2^(-'⚙ Parámetros'!C17*(O25-'⚙ Parámetros'!B17))),'⚙ Parámetros'!G17/(1+2^(-'⚙ Parámetros'!F17*(O25-'⚙ Parámetros'!E17))),1)+25/100*MAX('⚙ Parámetros'!D17/(1+2^(-'⚙ Parámetros'!C17*(P25-'⚙ Parámetros'!B17))),'⚙ Parámetros'!G17/(1+2^(-'⚙ Parámetros'!F17*(P25-'⚙ Parámetros'!E17))),1)+20/100*MAX('⚙ Parámetros'!D17/(1+2^(-'⚙ Parámetros'!C17*(Q25-'⚙ Parámetros'!B17))),'⚙ Parámetros'!G17/(1+2^(-'⚙ Parámetros'!F17*(Q25-'⚙ Parámetros'!E17))),1)),0) -> 5.2162162 | AE25: =IFERROR((30/100*MAX('⚙ Parámetros'!D18/(1+2^(-'⚙ Parámetros'!C18*(R25-'⚙ Parámetros'!B18))),'⚙ Parámetros'!G18/(1+2^(-'⚙ Parámetros'!F18*(R25-'⚙ Parámetros'!E18))),1)*R25+30/100*MAX('⚙ Parámetros'!D18/(1+2^(-'⚙ Parámetros'!C18*(S25-'⚙ Parámetros'!B18))),'⚙ Parámetros'!G18/(1+2^(-'⚙ Parámetros'!F18*(S25-'⚙ Parámetros'!E18))),1)*S25+20/100*MAX('⚙ Parámetros'!D18/(1+2^(-'⚙ Parámetros'!C18*(T25-'⚙ Parámetros'!B18))),'⚙ Parámetros'!G18/(1+2^(-'⚙ Parámetros'!F18*(T25-'⚙ Parámetros'!E18))),1)*T25+20/100*MAX('⚙ Parámetros'!D18/(1+2^(-'⚙ Parámetros'!C18*(U25-'⚙ Parámetros'!B18))),'⚙ Parámetros'!G18/(1+2^(-'⚙ Parámetros'!F18*(U25-'⚙ Parámetros'!E18))),1)*U25)/(30/100*MAX('⚙ Parámetros'!D18/(1+2^(-'⚙ Parámetros'!C18*(R25-'⚙ Parámetros'!B18))),'⚙ Parámetros'!G18/(1+2^(-'⚙ Parámetros'!F18*(R25-'⚙ Parámetros'!E18))),1)+30/100*MAX('⚙ Parámetros'!D18/(1+2^(-'⚙ Parámetros'!C18*(S25-'⚙ Parámetros'!B18))),'⚙ Parámetros'!G18/(1+2^(-'⚙ Parámetros'!F18*(S25-'⚙ Parámetros'!E18))),1)+20/100*MAX('⚙ Parámetros'!D18/(1+2^(-'⚙ Parámetros'!C18*(T25-'⚙ Parámetros'!B18))),'⚙ Parámetros'!G18/(1+2^(-'⚙ Parámetros'!F18*(T25-'⚙ Parámetros'!E18))),1)+20/100*MAX('⚙ Parámetros'!D18/(1+2^(-'⚙ Parámetros'!C18*(U25-'⚙ Parámetros'!B18))),'⚙ Parámetros'!G18/(1+2^(-'⚙ Parámetros'!F18*(U25-'⚙ Parámetros'!E18))),1)),0) -> 8.180106 | AF25: =IFERROR((30/100*MAX('⚙ Parámetros'!D19/(1+2^(-'⚙ Parámetros'!C19*(V25-'⚙ Parámetros'!B19))),'⚙ Parámetros'!G19/(1+2^(-'⚙ Parámetros'!F19*(V25-'⚙ Parámetros'!E19))),1)*V25+35/100*MAX('⚙ Parámetros'!D19/(1+2^(-'⚙ Parámetros'!C19*(W25-'⚙ Parámetros'!B19))),'⚙ Parámetros'!G19/(1+2^(-'⚙ Parámetros'!F19*(W25-'⚙ Parámetros'!E19))),1)*W25+35/100*MAX('⚙ Parámetros'!D19/(1+2^(-'⚙ Parámetros'!C19*(X25-'⚙ Parámetros'!B19))),'⚙ Parámetros'!G19/(1+2^(-'⚙ Parámetros'!F19*(X25-'⚙ Parámetros'!E19))),1)*X25)/(30/100*MAX('⚙ Parámetros'!D19/(1+2^(-'⚙ Parámetros'!C19*(V25-'⚙ Parámetros'!B19))),'⚙ Parámetros'!G19/(1+2^(-'⚙ Parámetros'!F19*(V25-'⚙ Parámetros'!E19))),1)+35/100*MAX('⚙ Parámetros'!D19/(1+2^(-'⚙ Parámetros'!C19*(W25-'⚙ Parámetros'!B19))),'⚙ Parámetros'!G19/(1+2^(-'⚙ Parámetros'!F19*(W25-'⚙ Parámetros'!E19))),1)+35/100*MAX('⚙ Parámetros'!D19/(1+2^(-'⚙ Parámetros'!C19*(X25-'⚙ Parámetros'!B19))),'⚙ Parámetros'!G19/(1+2^(-'⚙ Parámetros'!F19*(X25-'⚙ Parámetros'!E19))),1)),0) -> 8.0351483 | AG25: =IFERROR((35/100*MAX('⚙ Parámetros'!D20/(1+2^(-'⚙ Parámetros'!C20*(Y25-'⚙ Parámetros'!B20))),'⚙ Parámetros'!G20/(1+2^(-'⚙ Parámetros'!F20*(Y25-'⚙ Parámetros'!E20))),1)*Y25+35/100*MAX('⚙ Parámetros'!D20/(1+2^(-'⚙ Parámetros'!C20*(Z25-'⚙ Parámetros'!B20))),'⚙ Parámetros'!G20/(1+2^(-'⚙ Parámetros'!F20*(Z25-'⚙ Parámetros'!E20))),1)*Z25+30/100*MAX('⚙ Parámetros'!D20/(1+2^(-'⚙ Parámetros'!C20*(AA25-'⚙ Parámetros'!B20))),'⚙ Parámetros'!G20/(1+2^(-'⚙ Parámetros'!F20*(AA25-'⚙ Parámetros'!E20))),1)*AA25)/(35/100*MAX('⚙ Parámetros'!D20/(1+2^(-'⚙ Parámetros'!C20*(Y25-'⚙ Parámetros'!B20))),'⚙ Parámetros'!G20/(1+2^(-'⚙ Parámetros'!F20*(Y25-'⚙ Parámetros'!E20))),1)+35/100*MAX('⚙ Parámetros'!D20/(1+2^(-'⚙ Parámetros'!C20*(Z25-'⚙ Parámetros'!B20))),'⚙ Parámetros'!G20/(1+2^(-'⚙ Parámetros'!F20*(Z25-'⚙ Parámetros'!E20))),1)+30/100*MAX('⚙ Parámetros'!D20/(1+2^(-'⚙ Parámetros'!C20*(AA25-'⚙ Parámetros'!B20))),'⚙ Parámetros'!G20/(1+2^(-'⚙ Parámetros'!F20*(AA25-'⚙ Parámetros'!E20))),1)),0) -> 3.7272727 | AH25: =('⚙ Parámetros'!B5/100*AB25+'⚙ Parámetros'!B6/100*AC25+'⚙ Parámetros'!B7/100*AD25+'⚙ Parámetros'!B8/100*AE25+'⚙ Parámetros'!B9/100*AF25+'⚙ Parámetros'!B10/100*AG25) -> 5.6001538 | AI25: =MIN(1+MAX(0,TODAY()-DATE(2026,2,2))/365*'⚙ Parámetros'!B33,'⚙ Parámetros'!B34) -> 1.0534247 | AJ25: =IFERROR(MIN(AH25*AI25,10),0) -> 5.8993401 | AK25: =IF(AB25>='⚙ Parámetros'!B23,"⚑ AUTO-PRIOR.(D1≥8)",IF(AJ25>='⚙ Parámetros'!B23,"PRIORITARIO",IF(AJ25>='⚙ Parámetros'!B24,"ALTA PRIORIDAD",IF(AJ25>='⚙ Parámetros'!B25,"PRIORIDAD MEDIA",IF(AJ25>='⚙ Parámetros'!B26,"BAJA PRIORIDAD","DESCARTAR"))))) -> PRIORIDAD MEDIA | AL25: =IF(AB25>=8,"SÍ ⚑","—") -> — | AM25: 24 | AN25: =IF(AM25="","—",IF(AM25<'⚙ Parámetros'!B29,"🟢 Corto",IF(AM25<'⚙ Parámetros'!B30,"🟡 Medio","🔴 Largo"))) -> 🟢 Corto
A26: 22 | B26: MPG-PRO-004_01 Mejoras informe loteado múltiple | C26: Producción | D26: Joan Valverde | E26: 20/01/2026 | F26: 6 | G26: 5 | H26: 1 | I26: 1 | J26: 1 | K26: 1 | L26: 8 | M26: 3 | N26: 1 | O26: 6 | P26: 1 | Q26: 8 | R26: 9 | S26: 9 | T26: 5 | U26: 5 | V26: 8 | W26: 6 | X26: 9 | Y26: 4 | Z26: 2 | AA26: 8 | AB26: =IFERROR((30/100*MAX('⚙ Parámetros'!D15/(1+2^(-'⚙ Parámetros'!C15*(F26-'⚙ Parámetros'!B15))),'⚙ Parámetros'!G15/(1+2^(-'⚙ Parámetros'!F15*(F26-'⚙ Parámetros'!E15))),1)*F26+30/100*MAX('⚙ Parámetros'!D15/(1+2^(-'⚙ Parámetros'!C15*(G26-'⚙ Parámetros'!B15))),'⚙ Parámetros'!G15/(1+2^(-'⚙ Parámetros'!F15*(G26-'⚙ Parámetros'!E15))),1)*G26+20/100*MAX('⚙ Parámetros'!D15/(1+2^(-'⚙ Parámetros'!C15*(H26-'⚙ Parámetros'!B15))),'⚙ Parámetros'!G15/(1+2^(-'⚙ Parámetros'!F15*(H26-'⚙ Parámetros'!E15))),1)*H26+20/100*MAX('⚙ Parámetros'!D15/(1+2^(-'⚙ Parámetros'!C15*(I26-'⚙ Parámetros'!B15))),'⚙ Parámetros'!G15/(1+2^(-'⚙ Parámetros'!F15*(I26-'⚙ Parámetros'!E15))),1)*I26)/(30/100*MAX('⚙ Parámetros'!D15/(1+2^(-'⚙ Parámetros'!C15*(F26-'⚙ Parámetros'!B15))),'⚙ Parámetros'!G15/(1+2^(-'⚙ Parámetros'!F15*(F26-'⚙ Parámetros'!E15))),1)+30/100*MAX('⚙ Parámetros'!D15/(1+2^(-'⚙ Parámetros'!C15*(G26-'⚙ Parámetros'!B15))),'⚙ Parámetros'!G15/(1+2^(-'⚙ Parámetros'!F15*(G26-'⚙ Parámetros'!E15))),1)+20/100*MAX('⚙ Parámetros'!D15/(1+2^(-'⚙ Parámetros'!C15*(H26-'⚙ Parámetros'!B15))),'⚙ Parámetros'!G15/(1+2^(-'⚙ Parámetros'!F15*(H26-'⚙ Parámetros'!E15))),1)+20/100*MAX('⚙ Parámetros'!D15/(1+2^(-'⚙ Parámetros'!C15*(I26-'⚙ Parámetros'!B15))),'⚙ Parámetros'!G15/(1+2^(-'⚙ Parámetros'!F15*(I26-'⚙ Parámetros'!E15))),1)),0) -> 4.2535211 | AC26: =IFERROR((35/100*MAX('⚙ Parámetros'!D16/(1+2^(-'⚙ Parámetros'!C16*(J26-'⚙ Parámetros'!B16))),'⚙ Parámetros'!G16/(1+2^(-'⚙ Parámetros'!F16*(J26-'⚙ Parámetros'!E16))),1)*J26+25/100*MAX('⚙ Parámetros'!D16/(1+2^(-'⚙ Parámetros'!C16*(K26-'⚙ Parámetros'!B16))),'⚙ Parámetros'!G16/(1+2^(-'⚙ Parámetros'!F16*(K26-'⚙ Parámetros'!E16))),1)*K26+20/100*MAX('⚙ Parámetros'!D16/(1+2^(-'⚙ Parámetros'!C16*(L26-'⚙ Parámetros'!B16))),'⚙ Parámetros'!G16/(1+2^(-'⚙ Parámetros'!F16*(L26-'⚙ Parámetros'!E16))),1)*L26+20/100*MAX('⚙ Parámetros'!D16/(1+2^(-'⚙ Parámetros'!C16*(M26-'⚙ Parámetros'!B16))),'⚙ Parámetros'!G16/(1+2^(-'⚙ Parámetros'!F16*(M26-'⚙ Parámetros'!E16))),1)*M26)/(35/100*MAX('⚙ Parámetros'!D16/(1+2^(-'⚙ Parámetros'!C16*(J26-'⚙ Parámetros'!B16))),'⚙ Parámetros'!G16/(1+2^(-'⚙ Parámetros'!F16*(J26-'⚙ Parámetros'!E16))),1)+25/100*MAX('⚙ Parámetros'!D16/(1+2^(-'⚙ Parámetros'!C16*(K26-'⚙ Parámetros'!B16))),'⚙ Parámetros'!G16/(1+2^(-'⚙ Parámetros'!F16*(K26-'⚙ Parámetros'!E16))),1)+20/100*MAX('⚙ Parámetros'!D16/(1+2^(-'⚙ Parámetros'!C16*(L26-'⚙ Parámetros'!B16))),'⚙ Parámetros'!G16/(1+2^(-'⚙ Parámetros'!F16*(L26-'⚙ Parámetros'!E16))),1)+20/100*MAX('⚙ Parámetros'!D16/(1+2^(-'⚙ Parámetros'!C16*(M26-'⚙ Parámetros'!B16))),'⚙ Parámetros'!G16/(1+2^(-'⚙ Parámetros'!F16*(M26-'⚙ Parámetros'!E16))),1)),0) -> 4.9411765 | AD26: =IFERROR((30/100*MAX('⚙ Parámetros'!D17/(1+2^(-'⚙ Parámetros'!C17*(N26-'⚙ Parámetros'!B17))),'⚙ Parámetros'!G17/(1+2^(-'⚙ Parámetros'!F17*(N26-'⚙ Parámetros'!E17))),1)*N26+25/100*MAX('⚙ Parámetros'!D17/(1+2^(-'⚙ Parámetros'!C17*(O26-'⚙ Parámetros'!B17))),'⚙ Parámetros'!G17/(1+2^(-'⚙ Parámetros'!F17*(O26-'⚙ Parámetros'!E17))),1)*O26+25/100*MAX('⚙ Parámetros'!D17/(1+2^(-'⚙ Parámetros'!C17*(P26-'⚙ Parámetros'!B17))),'⚙ Parámetros'!G17/(1+2^(-'⚙ Parámetros'!F17*(P26-'⚙ Parámetros'!E17))),1)*P26+20/100*MAX('⚙ Parámetros'!D17/(1+2^(-'⚙ Parámetros'!C17*(Q26-'⚙ Parámetros'!B17))),'⚙ Parámetros'!G17/(1+2^(-'⚙ Parámetros'!F17*(Q26-'⚙ Parámetros'!E17))),1)*Q26)/(30/100*MAX('⚙ Parámetros'!D17/(1+2^(-'⚙ Parámetros'!C17*(N26-'⚙ Parámetros'!B17))),'⚙ Parámetros'!G17/(1+2^(-'⚙ Parámetros'!F17*(N26-'⚙ Parámetros'!E17))),1)+25/100*MAX('⚙ Parámetros'!D17/(1+2^(-'⚙ Parámetros'!C17*(O26-'⚙ Parámetros'!B17))),'⚙ Parámetros'!G17/(1+2^(-'⚙ Parámetros'!F17*(O26-'⚙ Parámetros'!E17))),1)+25/100*MAX('⚙ Parámetros'!D17/(1+2^(-'⚙ Parámetros'!C17*(P26-'⚙ Parámetros'!B17))),'⚙ Parámetros'!G17/(1+2^(-'⚙ Parámetros'!F17*(P26-'⚙ Parámetros'!E17))),1)+20/100*MAX('⚙ Parámetros'!D17/(1+2^(-'⚙ Parámetros'!C17*(Q26-'⚙ Parámetros'!B17))),'⚙ Parámetros'!G17/(1+2^(-'⚙ Parámetros'!F17*(Q26-'⚙ Parámetros'!E17))),1)),0) -> 5.4102564 | AE26: =IFERROR((30/100*MAX('⚙ Parámetros'!D18/(1+2^(-'⚙ Parámetros'!C18*(R26-'⚙ Parámetros'!B18))),'⚙ Parámetros'!G18/(1+2^(-'⚙ Parámetros'!F18*(R26-'⚙ Parámetros'!E18))),1)*R26+30/100*MAX('⚙ Parámetros'!D18/(1+2^(-'⚙ Parámetros'!C18*(S26-'⚙ Parámetros'!B18))),'⚙ Parámetros'!G18/(1+2^(-'⚙ Parámetros'!F18*(S26-'⚙ Parámetros'!E18))),1)*S26+20/100*MAX('⚙ Parámetros'!D18/(1+2^(-'⚙ Parámetros'!C18*(T26-'⚙ Parámetros'!B18))),'⚙ Parámetros'!G18/(1+2^(-'⚙ Parámetros'!F18*(T26-'⚙ Parámetros'!E18))),1)*T26+20/100*MAX('⚙ Parámetros'!D18/(1+2^(-'⚙ Parámetros'!C18*(U26-'⚙ Parámetros'!B18))),'⚙ Parámetros'!G18/(1+2^(-'⚙ Parámetros'!F18*(U26-'⚙ Parámetros'!E18))),1)*U26)/(30/100*MAX('⚙ Parámetros'!D18/(1+2^(-'⚙ Parámetros'!C18*(R26-'⚙ Parámetros'!B18))),'⚙ Parámetros'!G18/(1+2^(-'⚙ Parámetros'!F18*(R26-'⚙ Parámetros'!E18))),1)+30/100*MAX('⚙ Parámetros'!D18/(1+2^(-'⚙ Parámetros'!C18*(S26-'⚙ Parámetros'!B18))),'⚙ Parámetros'!G18/(1+2^(-'⚙ Parámetros'!F18*(S26-'⚙ Parámetros'!E18))),1)+20/100*MAX('⚙ Parámetros'!D18/(1+2^(-'⚙ Parámetros'!C18*(T26-'⚙ Parámetros'!B18))),'⚙ Parámetros'!G18/(1+2^(-'⚙ Parámetros'!F18*(T26-'⚙ Parámetros'!E18))),1)+20/100*MAX('⚙ Parámetros'!D18/(1+2^(-'⚙ Parámetros'!C18*(U26-'⚙ Parámetros'!B18))),'⚙ Parámetros'!G18/(1+2^(-'⚙ Parámetros'!F18*(U26-'⚙ Parámetros'!E18))),1)),0) -> 8.180106 | AF26: =IFERROR((30/100*MAX('⚙ Parámetros'!D19/(1+2^(-'⚙ Parámetros'!C19*(V26-'⚙ Parámetros'!B19))),'⚙ Parámetros'!G19/(1+2^(-'⚙ Parámetros'!F19*(V26-'⚙ Parámetros'!E19))),1)*V26+35/100*MAX('⚙ Parámetros'!D19/(1+2^(-'⚙ Parámetros'!C19*(W26-'⚙ Parámetros'!B19))),'⚙ Parámetros'!G19/(1+2^(-'⚙ Parámetros'!F19*(W26-'⚙ Parámetros'!E19))),1)*W26+35/100*MAX('⚙ Parámetros'!D19/(1+2^(-'⚙ Parámetros'!C19*(X26-'⚙ Parámetros'!B19))),'⚙ Parámetros'!G19/(1+2^(-'⚙ Parámetros'!F19*(X26-'⚙ Parámetros'!E19))),1)*X26)/(30/100*MAX('⚙ Parámetros'!D19/(1+2^(-'⚙ Parámetros'!C19*(V26-'⚙ Parámetros'!B19))),'⚙ Parámetros'!G19/(1+2^(-'⚙ Parámetros'!F19*(V26-'⚙ Parámetros'!E19))),1)+35/100*MAX('⚙ Parámetros'!D19/(1+2^(-'⚙ Parámetros'!C19*(W26-'⚙ Parámetros'!B19))),'⚙ Parámetros'!G19/(1+2^(-'⚙ Parámetros'!F19*(W26-'⚙ Parámetros'!E19))),1)+35/100*MAX('⚙ Parámetros'!D19/(1+2^(-'⚙ Parámetros'!C19*(X26-'⚙ Parámetros'!B19))),'⚙ Parámetros'!G19/(1+2^(-'⚙ Parámetros'!F19*(X26-'⚙ Parámetros'!E19))),1)),0) -> 8.0351483 | AG26: =IFERROR((35/100*MAX('⚙ Parámetros'!D20/(1+2^(-'⚙ Parámetros'!C20*(Y26-'⚙ Parámetros'!B20))),'⚙ Parámetros'!G20/(1+2^(-'⚙ Parámetros'!F20*(Y26-'⚙ Parámetros'!E20))),1)*Y26+35/100*MAX('⚙ Parámetros'!D20/(1+2^(-'⚙ Parámetros'!C20*(Z26-'⚙ Parámetros'!B20))),'⚙ Parámetros'!G20/(1+2^(-'⚙ Parámetros'!F20*(Z26-'⚙ Parámetros'!E20))),1)*Z26+30/100*MAX('⚙ Parámetros'!D20/(1+2^(-'⚙ Parámetros'!C20*(AA26-'⚙ Parámetros'!B20))),'⚙ Parámetros'!G20/(1+2^(-'⚙ Parámetros'!F20*(AA26-'⚙ Parámetros'!E20))),1)*AA26)/(35/100*MAX('⚙ Parámetros'!D20/(1+2^(-'⚙ Parámetros'!C20*(Y26-'⚙ Parámetros'!B20))),'⚙ Parámetros'!G20/(1+2^(-'⚙ Parámetros'!F20*(Y26-'⚙ Parámetros'!E20))),1)+35/100*MAX('⚙ Parámetros'!D20/(1+2^(-'⚙ Parámetros'!C20*(Z26-'⚙ Parámetros'!B20))),'⚙ Parámetros'!G20/(1+2^(-'⚙ Parámetros'!F20*(Z26-'⚙ Parámetros'!E20))),1)+30/100*MAX('⚙ Parámetros'!D20/(1+2^(-'⚙ Parámetros'!C20*(AA26-'⚙ Parámetros'!B20))),'⚙ Parámetros'!G20/(1+2^(-'⚙ Parámetros'!F20*(AA26-'⚙ Parámetros'!E20))),1)),0) -> 5.8125 | AH26: =('⚙ Parámetros'!B5/100*AB26+'⚙ Parámetros'!B6/100*AC26+'⚙ Parámetros'!B7/100*AD26+'⚙ Parámetros'!B8/100*AE26+'⚙ Parámetros'!B9/100*AF26+'⚙ Parámetros'!B10/100*AG26) -> 5.5964705 | AI26: =MIN(1+MAX(0,TODAY()-DATE(2026,1,20))/365*'⚙ Parámetros'!B33,'⚙ Parámetros'!B34) -> 1.0587671 | AJ26: =IFERROR(MIN(AH26*AI26,10),0) -> 5.9253589 | AK26: =IF(AB26>='⚙ Parámetros'!B23,"⚑ AUTO-PRIOR.(D1≥8)",IF(AJ26>='⚙ Parámetros'!B23,"PRIORITARIO",IF(AJ26>='⚙ Parámetros'!B24,"ALTA PRIORIDAD",IF(AJ26>='⚙ Parámetros'!B25,"PRIORIDAD MEDIA",IF(AJ26>='⚙ Parámetros'!B26,"BAJA PRIORIDAD","DESCARTAR"))))) -> PRIORIDAD MEDIA | AL26: =IF(AB26>=8,"SÍ ⚑","—") -> — | AM26: 22 | AN26: =IF(AM26="","—",IF(AM26<'⚙ Parámetros'!B29,"🟢 Corto",IF(AM26<'⚙ Parámetros'!B30,"🟡 Medio","🔴 Largo"))) -> 🟢 Corto
A27: 23 | B27: Herencia de datos en la generación de CoA (MPG-CAL-010) | C27: Regulatorio y calidad | D27: Silvia Martin | E27: 13/03/2026 | F27: 8 | G27: 1 | H27: 7 | I27: 8 | J27: 1 | K27: 1 | L27: 8 | M27: 3 | N27: 1 | O27: 1 | P27: 1 | Q27: 8 | R27: 5 | S27: 5 | T27: 5 | U27: 5 | V27: 5 | W27: 6 | X27: 6 | Y27: 4 | Z27: 2 | AA27: 5 | AB27: =IFERROR((30/100*MAX('⚙ Parámetros'!D15/(1+2^(-'⚙ Parámetros'!C15*(F27-'⚙ Parámetros'!B15))),'⚙ Parámetros'!G15/(1+2^(-'⚙ Parámetros'!F15*(F27-'⚙ Parámetros'!E15))),1)*F27+30/100*MAX('⚙ Parámetros'!D15/(1+2^(-'⚙ Parámetros'!C15*(G27-'⚙ Parámetros'!B15))),'⚙ Parámetros'!G15/(1+2^(-'⚙ Parámetros'!F15*(G27-'⚙ Parámetros'!E15))),1)*G27+20/100*MAX('⚙ Parámetros'!D15/(1+2^(-'⚙ Parámetros'!C15*(H27-'⚙ Parámetros'!B15))),'⚙ Parámetros'!G15/(1+2^(-'⚙ Parámetros'!F15*(H27-'⚙ Parámetros'!E15))),1)*H27+20/100*MAX('⚙ Parámetros'!D15/(1+2^(-'⚙ Parámetros'!C15*(I27-'⚙ Parámetros'!B15))),'⚙ Parámetros'!G15/(1+2^(-'⚙ Parámetros'!F15*(I27-'⚙ Parámetros'!E15))),1)*I27)/(30/100*MAX('⚙ Parámetros'!D15/(1+2^(-'⚙ Parámetros'!C15*(F27-'⚙ Parámetros'!B15))),'⚙ Parámetros'!G15/(1+2^(-'⚙ Parámetros'!F15*(F27-'⚙ Parámetros'!E15))),1)+30/100*MAX('⚙ Parámetros'!D15/(1+2^(-'⚙ Parámetros'!C15*(G27-'⚙ Parámetros'!B15))),'⚙ Parámetros'!G15/(1+2^(-'⚙ Parámetros'!F15*(G27-'⚙ Parámetros'!E15))),1)+20/100*MAX('⚙ Parámetros'!D15/(1+2^(-'⚙ Parámetros'!C15*(H27-'⚙ Parámetros'!B15))),'⚙ Parámetros'!G15/(1+2^(-'⚙ Parámetros'!F15*(H27-'⚙ Parámetros'!E15))),1)+20/100*MAX('⚙ Parámetros'!D15/(1+2^(-'⚙ Parámetros'!C15*(I27-'⚙ Parámetros'!B15))),'⚙ Parámetros'!G15/(1+2^(-'⚙ Parámetros'!F15*(I27-'⚙ Parámetros'!E15))),1)),0) -> 7.375 | AC27: =IFERROR((35/100*MAX('⚙ Parámetros'!D16/(1+2^(-'⚙ Parámetros'!C16*(J27-'⚙ Parámetros'!B16))),'⚙ Parámetros'!G16/(1+2^(-'⚙ Parámetros'!F16*(J27-'⚙ Parámetros'!E16))),1)*J27+25/100*MAX('⚙ Parámetros'!D16/(1+2^(-'⚙ Parámetros'!C16*(K27-'⚙ Parámetros'!B16))),'⚙ Parámetros'!G16/(1+2^(-'⚙ Parámetros'!F16*(K27-'⚙ Parámetros'!E16))),1)*K27+20/100*MAX('⚙ Parámetros'!D16/(1+2^(-'⚙ Parámetros'!C16*(L27-'⚙ Parámetros'!B16))),'⚙ Parámetros'!G16/(1+2^(-'⚙ Parámetros'!F16*(L27-'⚙ Parámetros'!E16))),1)*L27+20/100*MAX('⚙ Parámetros'!D16/(1+2^(-'⚙ Parámetros'!C16*(M27-'⚙ Parámetros'!B16))),'⚙ Parámetros'!G16/(1+2^(-'⚙ Parámetros'!F16*(M27-'⚙ Parámetros'!E16))),1)*M27)/(35/100*MAX('⚙ Parámetros'!D16/(1+2^(-'⚙ Parámetros'!C16*(J27-'⚙ Parámetros'!B16))),'⚙ Parámetros'!G16/(1+2^(-'⚙ Parámetros'!F16*(J27-'⚙ Parámetros'!E16))),1)+25/100*MAX('⚙ Parámetros'!D16/(1+2^(-'⚙ Parámetros'!C16*(K27-'⚙ Parámetros'!B16))),'⚙ Parámetros'!G16/(1+2^(-'⚙ Parámetros'!F16*(K27-'⚙ Parámetros'!E16))),1)+20/100*MAX('⚙ Parámetros'!D16/(1+2^(-'⚙ Parámetros'!C16*(L27-'⚙ Parámetros'!B16))),'⚙ Parámetros'!G16/(1+2^(-'⚙ Parámetros'!F16*(L27-'⚙ Parámetros'!E16))),1)+20/100*MAX('⚙ Parámetros'!D16/(1+2^(-'⚙ Parámetros'!C16*(M27-'⚙ Parámetros'!B16))),'⚙ Parámetros'!G16/(1+2^(-'⚙ Parámetros'!F16*(M27-'⚙ Parámetros'!E16))),1)),0) -> 4.9411765 | AD27: =IFERROR((30/100*MAX('⚙ Parámetros'!D17/(1+2^(-'⚙ Parámetros'!C17*(N27-'⚙ Parámetros'!B17))),'⚙ Parámetros'!G17/(1+2^(-'⚙ Parámetros'!F17*(N27-'⚙ Parámetros'!E17))),1)*N27+25/100*MAX('⚙ Parámetros'!D17/(1+2^(-'⚙ Parámetros'!C17*(O27-'⚙ Parámetros'!B17))),'⚙ Parámetros'!G17/(1+2^(-'⚙ Parámetros'!F17*(O27-'⚙ Parámetros'!E17))),1)*O27+25/100*MAX('⚙ Parámetros'!D17/(1+2^(-'⚙ Parámetros'!C17*(P27-'⚙ Parámetros'!B17))),'⚙ Parámetros'!G17/(1+2^(-'⚙ Parámetros'!F17*(P27-'⚙ Parámetros'!E17))),1)*P27+20/100*MAX('⚙ Parámetros'!D17/(1+2^(-'⚙ Parámetros'!C17*(Q27-'⚙ Parámetros'!B17))),'⚙ Parámetros'!G17/(1+2^(-'⚙ Parámetros'!F17*(Q27-'⚙ Parámetros'!E17))),1)*Q27)/(30/100*MAX('⚙ Parámetros'!D17/(1+2^(-'⚙ Parámetros'!C17*(N27-'⚙ Parámetros'!B17))),'⚙ Parámetros'!G17/(1+2^(-'⚙ Parámetros'!F17*(N27-'⚙ Parámetros'!E17))),1)+25/100*MAX('⚙ Parámetros'!D17/(1+2^(-'⚙ Parámetros'!C17*(O27-'⚙ Parámetros'!B17))),'⚙ Parámetros'!G17/(1+2^(-'⚙ Parámetros'!F17*(O27-'⚙ Parámetros'!E17))),1)+25/100*MAX('⚙ Parámetros'!D17/(1+2^(-'⚙ Parámetros'!C17*(P27-'⚙ Parámetros'!B17))),'⚙ Parámetros'!G17/(1+2^(-'⚙ Parámetros'!F17*(P27-'⚙ Parámetros'!E17))),1)+20/100*MAX('⚙ Parámetros'!D17/(1+2^(-'⚙ Parámetros'!C17*(Q27-'⚙ Parámetros'!B17))),'⚙ Parámetros'!G17/(1+2^(-'⚙ Parámetros'!F17*(Q27-'⚙ Parámetros'!E17))),1)),0) -> 4.5 | AE27: =IFERROR((30/100*MAX('⚙ Parámetros'!D18/(1+2^(-'⚙ Parámetros'!C18*(R27-'⚙ Parámetros'!B18))),'⚙ Parámetros'!G18/(1+2^(-'⚙ Parámetros'!F18*(R27-'⚙ Parámetros'!E18))),1)*R27+30/100*MAX('⚙ Parámetros'!D18/(1+2^(-'⚙ Parámetros'!C18*(S27-'⚙ Parámetros'!B18))),'⚙ Parámetros'!G18/(1+2^(-'⚙ Parámetros'!F18*(S27-'⚙ Parámetros'!E18))),1)*S27+20/100*MAX('⚙ Parámetros'!D18/(1+2^(-'⚙ Parámetros'!C18*(T27-'⚙ Parámetros'!B18))),'⚙ Parámetros'!G18/(1+2^(-'⚙ Parámetros'!F18*(T27-'⚙ Parámetros'!E18))),1)*T27+20/100*MAX('⚙ Parámetros'!D18/(1+2^(-'⚙ Parámetros'!C18*(U27-'⚙ Parámetros'!B18))),'⚙ Parámetros'!G18/(1+2^(-'⚙ Parámetros'!F18*(U27-'⚙ Parámetros'!E18))),1)*U27)/(30/100*MAX('⚙ Parámetros'!D18/(1+2^(-'⚙ Parámetros'!C18*(R27-'⚙ Parámetros'!B18))),'⚙ Parámetros'!G18/(1+2^(-'⚙ Parámetros'!F18*(R27-'⚙ Parámetros'!E18))),1)+30/100*MAX('⚙ Parámetros'!D18/(1+2^(-'⚙ Parámetros'!C18*(S27-'⚙ Parámetros'!B18))),'⚙ Parámetros'!G18/(1+2^(-'⚙ Parámetros'!F18*(S27-'⚙ Parámetros'!E18))),1)+20/100*MAX('⚙ Parámetros'!D18/(1+2^(-'⚙ Parámetros'!C18*(T27-'⚙ Parámetros'!B18))),'⚙ Parámetros'!G18/(1+2^(-'⚙ Parámetros'!F18*(T27-'⚙ Parámetros'!E18))),1)+20/100*MAX('⚙ Parámetros'!D18/(1+2^(-'⚙ Parámetros'!C18*(U27-'⚙ Parámetros'!B18))),'⚙ Parámetros'!G18/(1+2^(-'⚙ Parámetros'!F18*(U27-'⚙ Parámetros'!E18))),1)),0) -> 5 | AF27: =IFERROR((30/100*MAX('⚙ Parámetros'!D19/(1+2^(-'⚙ Parámetros'!C19*(V27-'⚙ Parámetros'!B19))),'⚙ Parámetros'!G19/(1+2^(-'⚙ Parámetros'!F19*(V27-'⚙ Parámetros'!E19))),1)*V27+35/100*MAX('⚙ Parámetros'!D19/(1+2^(-'⚙ Parámetros'!C19*(W27-'⚙ Parámetros'!B19))),'⚙ Parámetros'!G19/(1+2^(-'⚙ Parámetros'!F19*(W27-'⚙ Parámetros'!E19))),1)*W27+35/100*MAX('⚙ Parámetros'!D19/(1+2^(-'⚙ Parámetros'!C19*(X27-'⚙ Parámetros'!B19))),'⚙ Parámetros'!G19/(1+2^(-'⚙ Parámetros'!F19*(X27-'⚙ Parámetros'!E19))),1)*X27)/(30/100*MAX('⚙ Parámetros'!D19/(1+2^(-'⚙ Parámetros'!C19*(V27-'⚙ Parámetros'!B19))),'⚙ Parámetros'!G19/(1+2^(-'⚙ Parámetros'!F19*(V27-'⚙ Parámetros'!E19))),1)+35/100*MAX('⚙ Parámetros'!D19/(1+2^(-'⚙ Parámetros'!C19*(W27-'⚙ Parámetros'!B19))),'⚙ Parámetros'!G19/(1+2^(-'⚙ Parámetros'!F19*(W27-'⚙ Parámetros'!E19))),1)+35/100*MAX('⚙ Parámetros'!D19/(1+2^(-'⚙ Parámetros'!C19*(X27-'⚙ Parámetros'!B19))),'⚙ Parámetros'!G19/(1+2^(-'⚙ Parámetros'!F19*(X27-'⚙ Parámetros'!E19))),1)),0) -> 5.7368421 | AG27: =IFERROR((35/100*MAX('⚙ Parámetros'!D20/(1+2^(-'⚙ Parámetros'!C20*(Y27-'⚙ Parámetros'!B20))),'⚙ Parámetros'!G20/(1+2^(-'⚙ Parámetros'!F20*(Y27-'⚙ Parámetros'!E20))),1)*Y27+35/100*MAX('⚙ Parámetros'!D20/(1+2^(-'⚙ Parámetros'!C20*(Z27-'⚙ Parámetros'!B20))),'⚙ Parámetros'!G20/(1+2^(-'⚙ Parámetros'!F20*(Z27-'⚙ Parámetros'!E20))),1)*Z27+30/100*MAX('⚙ Parámetros'!D20/(1+2^(-'⚙ Parámetros'!C20*(AA27-'⚙ Parámetros'!B20))),'⚙ Parámetros'!G20/(1+2^(-'⚙ Parámetros'!F20*(AA27-'⚙ Parámetros'!E20))),1)*AA27)/(35/100*MAX('⚙ Parámetros'!D20/(1+2^(-'⚙ Parámetros'!C20*(Y27-'⚙ Parámetros'!B20))),'⚙ Parámetros'!G20/(1+2^(-'⚙ Parámetros'!F20*(Y27-'⚙ Parámetros'!E20))),1)+35/100*MAX('⚙ Parámetros'!D20/(1+2^(-'⚙ Parámetros'!C20*(Z27-'⚙ Parámetros'!B20))),'⚙ Parámetros'!G20/(1+2^(-'⚙ Parámetros'!F20*(Z27-'⚙ Parámetros'!E20))),1)+30/100*MAX('⚙ Parámetros'!D20/(1+2^(-'⚙ Parámetros'!C20*(AA27-'⚙ Parámetros'!B20))),'⚙ Parámetros'!G20/(1+2^(-'⚙ Parámetros'!F20*(AA27-'⚙ Parámetros'!E20))),1)),0) -> 3.7272727 | AH27: =('⚙ Parámetros'!B5/100*AB27+'⚙ Parámetros'!B6/100*AC27+'⚙ Parámetros'!B7/100*AD27+'⚙ Parámetros'!B8/100*AE27+'⚙ Parámetros'!B9/100*AF27+'⚙ Parámetros'!B10/100*AG27) -> 5.5726013 | AI27: =MIN(1+MAX(0,TODAY()-DATE(2026,3,13))/365*'⚙ Parámetros'!B33,'⚙ Parámetros'!B34) -> 1.0373973 | AJ27: =IFERROR(MIN(AH27*AI27,10),0) -> 5.7810013 | AK27: =IF(AB27>='⚙ Parámetros'!B23,"⚑ AUTO-PRIOR.(D1≥8)",IF(AJ27>='⚙ Parámetros'!B23,"PRIORITARIO",IF(AJ27>='⚙ Parámetros'!B24,"ALTA PRIORIDAD",IF(AJ27>='⚙ Parámetros'!B25,"PRIORIDAD MEDIA",IF(AJ27>='⚙ Parámetros'!B26,"BAJA PRIORIDAD","DESCARTAR"))))) -> PRIORIDAD MEDIA | AL27: =IF(AB27>=8,"SÍ ⚑","—") -> — | AM27: 29 | AN27: =IF(AM27="","—",IF(AM27<'⚙ Parámetros'!B29,"🟢 Corto",IF(AM27<'⚙ Parámetros'!B30,"🟡 Medio","🔴 Largo"))) -> 🟢 Corto
